Workbook

Sheet Özet
A2: Corteqs · Şehir içerik teslimi
A3: Sevilla · İspanya · CITY-107
A5: İçerik türü | B5: Dosyada | C5: Asgari | D5: Hedef | E5: Asgariye kalan | F5: Hedefe kalan
A6: Pratik yaşam yanıtı | B6: =COUNTA('Yanıtlar'!$A$8:$A$307) | C6: 212 | D6: 240 | E6: =MAX(C6-B6,0) | F6: =MAX(D6-B6,0)
A7: Keşif noktası | B7: =COUNTA('Mekânlar'!$A$8:$A$187) | C7: 92 | D7: 120 | E7: =MAX(C7-B7,0) | F7: =MAX(D7-B7,0)
A8: Mahalle / yerel bölge | B8: =COUNTA('Mahalleler'!$A$8:$A$47) | C8: 12 | D8: 16 | E8: =MAX(C8-B8,0) | F8: =MAX(D8-B8,0)
A9: Yanıt içeren konu | B9: =SUM('Konular'!$H$8:$H$37) | C9: 12 | D9: 12 | E9: =MAX(C9-B9,0) | F9: =MAX(D9-B9,0)
A10: Farklı mekân fotoğrafı | B10: =SUM('Fotoğraflar'!$S$8:$S$607) | C10: 187 | D10: 250 | E10: =MAX(C10-B10,0) | F10: =MAX(D10-B10,0)
A11: Farklı kapak fotoğrafı | B11: =SUM('Fotoğraflar'!$T$8:$T$607) | C11: 6 | D11: 8 | E11: =MAX(C11-B11,0) | F11: =MAX(D11-B11,0)
A12: Rota | B12: =COUNTA('Rotalar'!$A$8:$A$37) | C12: 9 | D12: 12 | E12: =MAX(C12-B12,0) | F12: =MAX(D12-B12,0)
A13: Sözlük terimi | B13: =COUNTA('Sözlük'!$A$8:$A$107) | C13: 48 | D13: 60 | E13: =MAX(C13-B13,0) | F13: =MAX(D13-B13,0)
A14: v7 · Kaynak zinciri: FotoğrafKaynakları. Miktar, onay değildir.
A16: Dosyayı doldurma sırası
A18: 1. Teslimat ve Şehir alanlarını doldurun; şehir kimliğini tüm sayfalarda aynı kullanın.
A19: 2. Kaynaklar ve Konular kaydını açın. Yanıt, mekân ve mahalle satırlarını bu kimliklere bağlayın.
A20: 3. Bağlantılar, Fotoğraflar ve Kanıtlar satırlarını tamamlayın; rota ve sözlük kaynaklarını ekleyin.
A21: 4. Kaynak kontrol tarihini yazın. Çekim tarihi bilinmiyorsa boş bırakın; tarih uydurmayın.
A22: 5. Paketin tamamı insan editör tarafından incelenir; tek paket kararı yönetim ekranında verilir. Excel’de satır satır onay işaretlemek gerekmez.
A25: Sarı alanlar düzenlenebilir. Koyu satırdaki makine sütun adları (7. satır) ve sayfa adları değişmez. Veri 8. satırdan başlar. Kimlik listelerinde ; kullanın; işlem, belge ve durakları hücre içinde ayrı satırlara yazın.
A28: Fotoğraf miktarı dosya SHA-256 özeti ve rolüyle ölçülür; aynı kareye ait türevler ayrıca ayıklanır. Sayımda kullanılabilir eski alanı korunur, insan onayı yerine geçmez. Paket kararı yönetim ekranındadır.
A31: Asgari eşikler: 212 yanıt, 92 mekân, 12 mahalle, 12 konu, 187 farklı mekân fotoğrafı, 6 kapak, 9 rota, 48 terim. Hedefler: 240 / 120 / 16 / 12 / 250 / 8 / 12 / 60. Bu dosya uygulamaya veya veritabanına içerik yayımlamaz.

Sheet Teslimat
A2: Corteqs · Teslimat bilgileri
A3: Türkçe başlığı okuyun; veriyi 8. satırdan yazın. 7. satırdaki alan adını ve sayfa adını değiştirmeyin.
A5: Zorunlu | B5: Zorunlu | C5: Zorunlu | D5: Zorunlu | E5: İsteğe bağlı | F5: Zorunlu | G5: Zorunlu · tarih | H5: Zorunlu | I5: İsteğe bağlı
A6: Şema sürümü | B6: Teslimat kimliği | C6: Şehir kimliği | D6: Hazırlayan | E6: İnceleyen | F6: Dosya kapsamı | G6: Dosya güncelleme tarihi | H6: Editör durumu | I6: Teslim notu
A7: schema_version | B7: delivery_id | C7: city_id | D7: editor | E7: reviewer | F7: scope | G7: updated_on | H7: editorial_status | I7: notes
A8: 1.0 | B8: city-107-v001 | C8: sevilla | D8: Atınç | F8: Tam teslim | G8: 46320 | H8: Taslak | I8: Claude üretimi (city-pack, ülke paketi ES v9 + Endülüs v2); insan onayı yok; açık konular Teslimler\ACIK_KONULAR.txt.

Sheet Şehir
A2: Corteqs · Şehir profili
A3: Türkçe başlığı okuyun; veriyi 8. satırdan yazın. 7. satırdaki alan adını ve sayfa adını değiştirmeyin.
A5: Zorunlu | B5: Zorunlu | C5: Zorunlu | D5: Zorunlu | E5: Zorunlu | F5: Zorunlu | G5: Zorunlu | H5: Zorunlu | I5: Zorunlu | J5: İsteğe bağlı | K5: İsteğe bağlı | L5: Zorunlu | M5: Zorunlu | N5: Zorunlu | O5: Zorunlu | P5: Zorunlu | Q5: Zorunlu · tarih | R5: İsteğe bağlı | S5: Zorunlu | T5: Zorunlu · tarih | U5: Zorunlu | V5: Zorunlu · tarih | W5: Zorunlu | X5: İsteğe bağlı | Y5: İsteğe bağlı | Z5: İsteğe bağlı | AA5: İsteğe bağlı | AB5: İsteğe bağlı | AC5: İsteğe bağlı | AD5: İsteğe bağlı | AE5: İsteğe bağlı | AF5: İsteğe bağlı | AG5: Zorunlu
A6: Şehir kimliği | B6: Şehir adı | C6: Ülke | D6: Ülke kodu | E6: Dünya bölgesi | F6: Coğrafi kapsam | G6: Rehber başlığı | H6: Rehber giriş metni | I6: Para birimi kodu | J6: Para simgesi | K6: Para birimi adı | L6: Yerel dil | M6: Saat dilimi | N6: Enlem | O6: Boylam | P6: Konum kaynağı | Q6: Konum kontrol tarihi | R6: Konum açıklaması | S6: Kapsam kaynağı | T6: Kapsam kontrol tarihi | U6: Katalog sıra numarası | V6: Rehber kontrol tarihi | W6: Öncelik | X6: Diğer adlar | Y6: Yerel ad | Z6: Şehir cümlesi | AA6: Şehir dizini sırası | AB6: Hava tahmini bağlantısı | AC6: Hava veri sağlayıcısı | AD6: Tahmin bağlantı metni | AE6: Ana kapak kimliği | AF6: Editoryal şehir notları | AG6: Editör durumu
A7: city_id | B7: name | C7: country | D7: country_code | E7: region | F7: kind | G7: title | H7: intro | I7: currency | J7: currency_symbol | K7: currency_label | L7: language | M7: timezone | N7: latitude | O7: longitude | P7: coordinate_source_url | Q7: coordinate_checked_on | R7: coordinate_note | S7: source_url | T7: source_checked_on | U7: source_position | V7: reviewed_on | W7: priority | X7: aliases | Y7: locality | Z7: tagline | AA7: directory_order | AB7: forecast_url | AC7: provider_url | AD7: forecast_label | AE7: hero_photo_id | AF7: editorial_notes | AG7: editorial_status
A8: sevilla | B8: Sevilla | C8: İspanya | D8: ES | E8: EU | F8: city | G8: Sevilla'ya taşınma rehberi: oturum, konut, sağlık ve günlük yaşam | H8: Sevilla'da oturum izni ve adres kaydından sağlığa, kiradan ulaşıma kadar ilk adımları resmî kaynaklara dayanarak sade Türkçeyle öğren; flamenko, Semana Santa ve Feria de Abril ile şehrin kendine özgü yaşamını keşfet. | I8: EUR | J8: € | K8: Euro | L8: İspanyolca | M8: Europe/Madrid | N8: 37.405015 | O8: -5.980007 | P8: https://www.naturalearthdata.com/downloads/10m-cultural-vectors/10m-populated-places/ | Q8: 46305 | S8: https://www.internations.org/all-internations-cities/ | T8: 46305 | U8: 107 | V8: 46320 | W8: 3 | X8: Seville | Y8: Endülüs | Z8: Yeni hayatın için sade adımlar | AB8: https://www.aemet.es/es/eltiempo/prediccion/municipios/sevilla-id41091 | AC8: https://www.aemet.es | AD8: AEMET Sevilla hava tahmini | AE8: sevilla:photo:kapak-01 | AG8: Taslak

Sheet Konular
A2: Corteqs · Pratik yaşam konuları
A3: Türkçe başlığı okuyun; veriyi 8. satırdan yazın. 7. satırdaki alan adını ve sayfa adını değiştirmeyin.
A5: Zorunlu | B5: Zorunlu | C5: Zorunlu | D5: Zorunlu | E5: Zorunlu | F5: Zorunlu | G5: Zorunlu | H5: Hesap · değiştirmeyin
A6: Konu kimliği | B6: Şehir kimliği | C6: Konu adres adı | D6: Konu başlığı | E6: Açıklama | F6: Simge anahtarı | G6: Sıra | H6: Yanıt içeren konu (hesap)
A7: topic_id | B7: city_id | C7: slug | D7: title | E7: description | F7: icon | G7: order | H7: used_count
A8: sevilla:planlama | B8: sevilla | C8: planlama | D8: Taşınmadan önce plan | E8: Sevilla'ya gelmeden önce hazırlanacak belgeler, ilk haftanın sırası, yaz sıcağı ve yeni gelenlere resmî destek veren yerler. | F8: book | G8: 1 | H8: =IF(A8="",0,IF(COUNTIFS('Yanıtlar'!$N$8:$N$307,A8)>0,1,0))
A9: sevilla:oturum | B9: sevilla | C9: oturum | D9: Vize, oturum ve çalışma izni | E9: Oturum vizeleri, TIE ve NIE, AB kayıt sertifikası, Sevilla'daki yabancılar ofisi ve polis randevusu, aile birleşimi. | F9: plane | G9: 2 | H9: =IF(A9="",0,IF(COUNTIFS('Yanıtlar'!$N$8:$N$307,A9)>0,1,0))
A10: sevilla:resmi | B10: sevilla | C10: resmi | D10: Kimlik ve resmî işlemler | E10: Sevilla'da nüfus kaydı (empadronamiento), sosyal güvenlik numarası, Cl@ve ve dijital sertifika, belge tercümesi, ehliyet. | F10: shield | G10: 3 | H10: =IF(A10="",0,IF(COUNTIFS('Yanıtlar'!$N$8:$N$307,A10)>0,1,0))
A11: sevilla:ev | B11: sevilla | C11: ev | D11: Ev ve kira | E11: Sevilla'da kiralık ev arama, kira sözleşmesi ve depozito, kiracı hakları, kira yardımları ve ev satın alma. | F11: home | G11: 4 | H11: =IF(A11="",0,IF(COUNTIFS('Yanıtlar'!$N$8:$N$307,A11)>0,1,0))
A12: sevilla:fatura | B12: sevilla | C12: fatura | D12: Elektrik, gaz, su ve internet | E12: Elektrik ve doğalgaz aboneliği, Sevilla'da su (EMASESA) ve çöp, fatura indirimleri, internet ve mobil hat. | F12: bolt | G12: 5 | H12: =IF(A12="",0,IF(COUNTIFS('Yanıtlar'!$N$8:$N$307,A12)>0,1,0))
A13: sevilla:para | B13: sevilla | C13: para | D13: Banka, vergi ve destekler | E13: Banka hesabı, gelir vergisi beyanı, Endülüs bölge vergileri, belediye vergileri ve sosyal yardımlar. | F13: transfer | G13: 6 | H13: =IF(A13="",0,IF(COUNTIFS('Yanıtlar'!$N$8:$N$307,A13)>0,1,0))
A14: sevilla:saglik | B14: sevilla | C14: saglik | D14: Sağlık ve sigorta | E14: Endülüs sağlık kartı, aile hekimi ve sağlık merkezi, Sevilla'daki hastaneler, acil servis, eczane ve aşılar. | F14: heart | G14: 7 | H14: =IF(A14="",0,IF(COUNTIFS('Yanıtlar'!$N$8:$N$307,A14)>0,1,0))
A15: sevilla:is | B15: sevilla | C15: is | D15: İş ve çalışma hakları | E15: İş arama ve SAE kaydı, asgari ücret ve sözleşmeler, işsizlik ödeneği, Sevilla'da iş kurma ve diploma denkliği. | F15: briefcase | G15: 8 | H15: =IF(A15="",0,IF(COUNTIFS('Yanıtlar'!$N$8:$N$307,A15)>0,1,0))
A16: sevilla:aile | B16: sevilla | C16: aile | D16: Aile, okul ve çocuk | E16: Endülüs'te okul kaydı, okul öncesi eğitim, İspanyolca desteği, çocuk yardımları ve doğum kaydı. | F16: family | G16: 9 | H16: =IF(A16="",0,IF(COUNTIFS('Yanıtlar'!$N$8:$N$307,A16)>0,1,0))
A17: sevilla:ulasim | B17: sevilla | C17: ulasim | D17: Ulaşım ve araç | E17: Sevilla metrosu, otobüs ve tramvay, Cercanías treni, bisiklet, ehliyet ve araç, havalimanı ve şehirlerarası yolculuk. | F17: train | G17: 10 | H17: =IF(A17="",0,IF(COUNTIFS('Yanıtlar'!$N$8:$N$307,A17)>0,1,0))
A18: sevilla:gunluk | B18: sevilla | C18: gunluk | D18: Günlük yaşam ve güvenlik | E18: Acil numaralar, çöp ve geri dönüşüm, kütüphaneler, İspanyolca kursları, yaz sıcağı ve yerel bayramlar. | F18: bag | G18: 11 | H18: =IF(A18="",0,IF(COUNTIFS('Yanıtlar'!$N$8:$N$307,A18)>0,1,0))
A19: sevilla:kesif | B19: sevilla | C19: kesif | D19: Keşif, kültür, doğa ve spor | E19: Sevilla'nın anıtları ve müzeleri, flamenko, parklar ve Guadalquivir kıyısı, çocuklarla gezilecek yerler ve spor. | F19: people | G19: 12 | H19: =IF(A19="",0,IF(COUNTIFS('Yanıtlar'!$N$8:$N$307,A19)>0,1,0))
H20: =IF(A20="",0,IF(COUNTIFS('Yanıtlar'!$N$8:$N$307,A20)>0,1,0))
H21: =IF(A21="",0,IF(COUNTIFS('Yanıtlar'!$N$8:$N$307,A21)>0,1,0))
H22: =IF(A22="",0,IF(COUNTIFS('Yanıtlar'!$N$8:$N$307,A22)>0,1,0))
H23: =IF(A23="",0,IF(COUNTIFS('Yanıtlar'!$N$8:$N$307,A23)>0,1,0))
H24: =IF(A24="",0,IF(COUNTIFS('Yanıtlar'!$N$8:$N$307,A24)>0,1,0))
H25: =IF(A25="",0,IF(COUNTIFS('Yanıtlar'!$N$8:$N$307,A25)>0,1,0))
H26: =IF(A26="",0,IF(COUNTIFS('Yanıtlar'!$N$8:$N$307,A26)>0,1,0))
H27: =IF(A27="",0,IF(COUNTIFS('Yanıtlar'!$N$8:$N$307,A27)>0,1,0))
H28: =IF(A28="",0,IF(COUNTIFS('Yanıtlar'!$N$8:$N$307,A28)>0,1,0))
H29: =IF(A29="",0,IF(COUNTIFS('Yanıtlar'!$N$8:$N$307,A29)>0,1,0))
H30: =IF(A30="",0,IF(COUNTIFS('Yanıtlar'!$N$8:$N$307,A30)>0,1,0))
H31: =IF(A31="",0,IF(COUNTIFS('Yanıtlar'!$N$8:$N$307,A31)>0,1,0))
... H37: =IF(A37="",0,IF(COUNTIFS('Yanıtlar'!$N$8:$N$307,A37)>0,1,0))

Sheet Yanıtlar
A2: Corteqs · Pratik yaşam yanıtları
A3: Türkçe başlığı okuyun; veriyi 8. satırdan yazın. 7. satırdaki alan adını ve sayfa adını değiştirmeyin.
A5: Zorunlu | B5: Zorunlu | C5: Zorunlu | D5: Zorunlu | E5: İsteğe bağlı | F5: Zorunlu | G5: İsteğe bağlı | H5: İsteğe bağlı · ; ile | I5: Zorunlu · ; ile | J5: Zorunlu · tarih | K5: Zorunlu | L5: Zorunlu | M5: Zorunlu | N5: Zorunlu | O5: Zorunlu · alt satır | P5: İsteğe bağlı · alt satır | Q5: İsteğe bağlı | R5: İsteğe bağlı | S5: İsteğe bağlı | T5: İsteğe bağlı · JSON
A6: İçerik kimliği | B6: Şehir kimliği | C6: Adres adı | D6: Başlık | E6: Alt başlık | F6: Türkçe kısa yanıt / özet | G6: Arama sözcükleri | H6: Yaşam aşamaları | I6: Kaynak kimlikleri | J6: İçerik kontrol tarihi | K6: Sıra | L6: Öne çıkar | M6: Editör durumu | N6: Konu kimliği | O6: İşlem adımları | P6: Gereken belgeler | Q6: Süre / son tarih | R6: Ücret / maliyet | S6: İstisna ve dikkat notu | T6: Görsel açıklama yapısı (JSON)
A7: entry_id | B7: city_id | C7: slug | D7: title | E7: subtitle | F7: summary | G7: keywords | H7: stages | I7: source_ids | J7: reviewed_on | K7: order | L7: featured | M7: editorial_status | N7: topic_id | O7: steps | P7: documents | Q7: timing | R7: cost | S7: note | T7: visual_json
A8: sevilla:egitim-sistemi-zorunlu-egitim-ve-okul-turleri | B8: sevilla | C8: egitim-sistemi-zorunlu-egitim-ve-okul-turleri | D8: İspanya'da zorunlu eğitim hangi yaşları kapsar, okul türleri nelerdir ve okula kayıt nasıl işler? | E8: Temel eğitim 6–16 yaş arasıdır, kanunda zorunlu ve ücretsizdir; okullar kamu ve özel (bir kısmı sözleşmeli, concertado); kayıt takvimi bölgene göre değişir | F8: Zorunlu temel eğitim (enseñanza básica) 6 ile 16 yaş arasında, toplam on yıllık okullaşmadır; LOE md. 4 onu herkes için zorunlu ve ücretsiz bir eğitim olarak tanımlar. Temel eğitimi ilkokul (educación primaria), zorunlu ortaöğretim (ESO) ve temel düzey meslek eğitimi döngüleri oluşturur; ESO dört sınıftır ve genellikle 12–16 yaşları arasında okunur. 0–6 yaş okul öncesi eğitim (educación infantil) isteğe bağlıdır. Okullar kamu okulları (sahibi bir kamu idaresi olanlar) ve özel okullar olarak ayrılır; devletle sözleşme rejimine alınan özel okullara centro concertado denir; kamu eğitim hizmeti kamu ve concertado okullar aracılığıyla verilir. Kamu ve concertado okullara kabulü eğitim idareleri düzenler; başvuru takvimi ve puanlama bölgene göre değişir. | G8: zorunlu eğitim, eğitim sistemi, okul türleri, escolarización, admisión, centro concertado, ESO, educación infantil | H8: planning;new | I8: sevilla:kaynak:103 | J8: 46319 | K8: 9081 | L8: Hayır | M8: Taslak | N8: sevilla:aile | O8: Çocuğunun yaşına göre etabı belirle: 0–6 yaş okul öncesi eğitim isteğe bağlıdır, 6–16 yaş temel eğitim kanunda zorunlu ve ücretsiz olarak tanımlanır. Okul türünü seç: kamu okulu, özel okul ya da concertado okul; ebeveyn olarak kamu okulunu da, kamu idarelerinin kurmadığı bir okulu da seçme hakkın var. Kamu ya da concertado okul istiyorsan başvuruyu bölgenin eğitim idaresinin düzenlediği kabul (admisión) süreci üzerinden yap; takvim ve puanlama bölgene göre değişir. Yer yetersizse sıralamayı öncelikli ölçütler belirler: okulda kayıtlı kardeşin, evinin ya da ebeveynlerinden birinin iş yerinin okula yakınlığı ve ailenin kişi başı geliri. Kamu okullarında yer yetersizse, okulun kendisine bağlı (adscrito) okullardan gelen öğrenciler öncelik alır; concertado okullarda benzer bir usul uygulanır. | R8: Kanun, temel eğitimi (6–16 yaş) herkes için zorunlu ve ücretsiz olarak tanımlar (LOE md. 4). | S8: Kabulde doğum, ırk veya etnik köken, cinsiyet, din, görüş, engellilik, yaş gibi nedenlerle ayrımcılık yapılamaz. Ebeveynlerinden birinin zorunlu görev değişikliği, ailede sonradan gelişen engellilik ya da toplumsal cinsiyete dayalı şiddet nedeniyle ikamet değişikliği yüzünden taşındıysan, oturduğun ya da çalıştığın bölgeye göre kabulde tercih hakkın vardır. Zorunlu eğitimden sonraki lise düzeyi (educación secundaria postobligatoria) bachillerato ve orta düzey meslek eğitimi (FP grado medio) gibi öğrenimleri kapsar.
A9: sevilla:yabanci-lise-diplomasi-ile-universiteye-giris | B9: sevilla | C9: yabanci-lise-diplomasi-ile-universiteye-giris | D9: İspanya'da yabancı lise diplomasıyla üniversiteye girmek için ne gerekir, hangi diplomalar giriş sınavından ve denklik (homologación) yaptırmaktan muaftır? | E9: Diplomanın eğitim sistemine bağlı: RD 534/2024 md. 6 kapsamındakilerde sınav ve homologación gerekmez; diğerleri için homologación, UNEDasiss ve PCE | F9: Yol diplomanın geldiği eğitim sistemine göre değişir. AB üye devletlerinin ve karşılıklılık esasıyla uluslararası anlaşma yapılmış devletlerin sistemlerinden gelenler (kendi sistemlerinde üniversiteye giriş şartlarını karşılamaları koşuluyla), Avrupa Okulları'nın Avrupa Bakalorya diploması sahipleri ve Uluslararası Bakalorya (IB) diploması sahipleri giriş sınavı (prueba de acceso) olmadan üniversiteye girebilir ve diplomalarının homologación (resmî denklik) işlemini yaptırmak zorunda değildir (RD 534/2024 md. 6); UNEDasiss bu gruptakiler için de, yabancı notları İspanyol ölçeğine çeviren Acreditación UNEDasiss ve Calificación de Acceso'yu şart koşar. UNEDasiss bu yolu 'AB, Avrupa Yükseköğretim Alanı, IB, Avrupa Okulları, Çin ve Kolombiya' başlığı altında verir; saydığı sistemlerin listesi nottadır. UNEDasiss'in 'AB dışı ülkeler' yolunda, yani diğer uluslararası eğitim sistemlerinden gelenler için UNEDasiss'in aradığı şart şudur: İspanyol bachillerato'suna homologación için gereken şartları karşılıyor olmak; devlet üniversitesi için ayrıca Calificación de Acceso ve PCE sınavları gerekir. Özel üniversitelerde kabul sistemi devlet üniversitelerinden farklıdır. | G9: yabancı diploma, üniversiteye giriş, UNEDasiss, PCE, homologación, prueba de acceso, RD 534/2024, Calificación de Acceso | H9: before;planning;new | I9: sevilla:kaynak:104;sevilla:kaynak:105 | J9: 46319 | K9: 9082 | L9: Hayır | M9: Taslak | N9: sevilla:aile | O9: Diplomanın hangi eğitim sistemine ait olduğuna bak: AB üye devleti, karşılıklılık anlaşmalı devlet, Avrupa Okulları ya da Uluslararası Bakalorya (IB) ise RD 534/2024 md. 6'ya göre sınavsız giriş grubundasın ve homologación yaptırman gerekmez; genel lise diplomanda kendi sisteminde üniversiteye giriş şartlarını karşılamış olman gerekir, meslek diplomaları için ek koşul notta yazılıdır. Bu gruptaysan UNEDasiss'ten Acreditación UNEDasiss'i ve notlarını İspanyol ölçeğine çeviren Calificación de Acceso'yu al. Giriş notunu yükseltmek istersen PCE sınavlarına gir (en az 2 ders önerilir) ve/ya da derslerinin tanınmasını (Reconocimiento de asignaturas) iste. UNEDasiss'in 'Otros países fuera de la UE' yolundaysan, yani diplomanın sistemi yukarıdaki 'AB, EHEA, IB, Avrupa Okulları, Çin ve Kolombiya' grubunda sayılmayan diğer uluslararası bir eğitim sistemindense: İspanyol bachillerato'suna homologación için gereken şartları karşılıyor olmalısın; meslek lisesi mezunuysan Técnico Superior unvanına homologación almış olmalısın. Devlet üniversitesi için Calificación de Acceso'ya ek olarak PCE sınavlarına gir (en az 4 ders önerilir); hangi derslere gireceğini üniversitenin kabul kriterleri belirler: bachillerato modalitesi (4 PCE dersi), PCE'yi İspanyol öğrencilerin PAU'su gibi yapılandırmak (en az 4 zorunlu ders, 1 ya da 2 isteğe bağlı ders) ya da dil belgesi. | P9: Acreditación UNEDasiss (Calificación de Acceso ile) PCE sınavları (ülke dışı diploma için devlet üniversitesinde) | S9: UNEDasiss'in 'AB, Avrupa Yükseköğretim Alanı, IB, Avrupa Okulları, Çin ve Kolombiya' grubunda saydığı sistemler: Almanya, Andorra, Avusturya, Uluslararası Bakalorya, Belçika, Bulgaristan, Çekya, Çin, Kıbrıs, Kolombiya, Hırvatistan, Danimarka, Avrupa Okulları, Slovakya, Slovenya, Estonya, Finlandiya, Fransa, Yunanistan, Macaristan, İrlanda, İzlanda, İtalya, Letonya, Lihtenştayn, Litvanya, Lüksemburg, Malta, Norveç, Hollanda, Polonya, Portekiz, Birleşik Krallık, Romanya, İsveç ve İsviçre. Giriş sınavını geçmesi gereken yabancı sistem öğrencileri RD 534/2024'te ayrı bir grup olarak sayılır ve kabulleri LOE'nin ilgili ek maddesini geliştiren yönetmeliğe göre yapılır. UNEDasiss'in 'AB, Avrupa Yükseköğretim Alanı, IB, Avrupa Okulları, Çin ve Kolombiya' grubunda meslek diplomaları için diplomanın Orden EFD/550/2025'te yer alması ya da Eğitim, Meslek Eğitimi ve Spor Bakanlığı'nın olumlu raporunu alması gerekir.
A10: sevilla:ingreso-minimo-vital-ve-cocuk-destegi | B10: sevilla | C10: ingreso-minimo-vital-ve-cocuk-destegi | D10: İspanya'da Ingreso Mínimo Vital ve çocuk yardımı eki (complemento de ayuda para la infancia) kimlere verilir, yabancı için ikamet şartı nedir? | E10: Başvurudan önceki en az 1 yıl yasal ve fiilî ikamet aranır; AB dışı yabancıda oturum izniyle kanıtlanır; 2026 çocuk eki aylık 115, 80,50 ya da 57,50 € | F10: Ingreso Mínimo Vital (IMV, asgari yaşamsal gelir), ekonomik açıdan kırılgan durumdaki kişilere ve birlikte yaşayan birimlere (unidad de convivencia) verilir; yararlanıcılar (bireysel başvuranlar ve birim üyeleri) için başvurudan önceki en az bir yıl boyunca İspanya'da yasal ve fiilî, kesintisiz ikamet şarttır. Gelirin yanında varlık da aranır: oturduğun ev (vivienda habitual) hariç net varlığı bireysel yararlanıcıda 2026'da 26.409,60 € ve üzerinde olanlar ekonomik kırılgan sayılmaz (ayrıntı notta). AB, AEA ya da İsviçre vatandaşı olmayan yabancıda yasal ikamet, oturum izniyle (autorización de residencia, her türü) ya da AB vatandaşı aile üyesi kartıyla kanıtlanır; Türk vatandaşı bu ikinci gruba girer, yani oturum izninle ya da AB vatandaşının aile üyesiysen aile üyesi kartınla kanıtlarsın. Bir yıl şartı doğum, evlat edinme, çocukların aile birleşimi (reagrupación familiar), evlat edinme amaçlı koruma ya da kalıcı aile yanında bakımla birime katılan reşit olmayanlar için, ayrıca insan ticareti ve cinsel sömürü mağdurları ile toplumsal cinsiyete dayalı şiddet mağduru kadınlar için aranmaz. Reşit olmayan çocuğu olan birimler için çocuk eki (complemento de ayuda para la infancia) de vardır; 2026 için tutarı çocuğun 1 Ocak'ta tamamlanmış yaşına göre aylık 115 €, 80,50 € ya da 57,50 €'dur. | G10: ingreso mínimo vital, IMV, complemento de ayuda para la infancia, çocuk yardımı, Seguridad Social, ikamet şartı, aile yardımı | H10: new;settled | I10: sevilla:kaynak:106;sevilla:kaynak:107 | J10: 46319 | K10: 9083 | L10: Hayır | M10: Taslak | N10: sevilla:aile | O10: Birimin (unidad de convivencia) başvurudan önceki en az altı ay kesintisiz oluşmuş olmalı; başvuru sahibi (titular) genel olarak en az 23 yaşında ve hukuki ehliyetli olmalı. Yasal ve fiilî ikametini en az bir yıllık kesintisiz süre için oturum izninle (her türü) ya da AB vatandaşı aile üyesi kartınla, İspanya'daki adresini ise empadronamiento (belediye nüfus kaydı) belgesiyle kanıtla. Kimlik olarak ülkenin kimlik belgesi, yabancı kimlik kartı (TIE) ya da pasaportunu ver; NIE belgelerde yoksa ayrıca ver. Çocukların için libro de familia ya da Registro Civil'in verdiği doğum belgesini ekle. Başvuruyu Seguridad Social'ın elektronik şubesindeki Servicio Ingreso Mínimo Vital üzerinden yap; IMV'yi ve çocuk ekini buradan talep edersin. Bilgi hattı 020'dir. Aynı çocuk için, engeli olmayan ya da engel oranı %33'ün altında olan çocuk başına aile yardımı (asignación económica por hijo o menor a cargo) alıyorsan IMV ile birlikte alamazsın. IMV tutarı aile yardımından yüksekse IMV tanınır ve aile yardımı hakkı sona erer; IMV daha düşükse ve aile yardımını seçersen IMV başvurusu reddedilir. | P10: Kimlik belgesi: ülkenin kimlik belgesi, yabancı kimlik kartı (TIE) ya da pasaport (ve NIE) Oturum izni (yasal ikamet için) Empadronamiento belgesi (belediye nüfus kaydı) Libro de familia ya da Registro Civil doğum belgesi (çocuklar için) | R10: 2026 için çocuk eki, reşit olmayan her çocuk için aylık: 3 yaşından küçük 115 €; 3 yaşından büyük, 6 yaşından küçük 80,50 €; 6 yaşından büyük, 18 yaşından küçük 57,50 € (yaş, ilgili yılın 1 Ocak'ında tamamlanmış yaşa göre). | S10: 2026'da bireysel yararlanıcı için aylık garantili gelir 733,6 €'dur; bir yetişkin ve bir çocuktan ya da iki yetişkinden oluşan birim için 953,68 €'dur. IMV tutarı, garantili gelirle kişinin ya da birimin gelirleri arasındaki farktır ve bu fark aylık 10 € ya da daha fazla olmalıdır. Çocuk eki, önceki yılın hesaba katılan geliri IMV'nin garantili tutarının %300'ünün altında ve net varlığı ilgili sınırların %150'sinin altında olan birimlere tanınır. Varlık sınırı: oturduğun ev (vivienda habitual) hariç net varlığı bireysel yararlanıcıda 2026'da 26.409,60 € ve üzerinde olanlar ekonomik kırılgan sayılmaz; birimlerde sınır, birimin büyüklüğüne ve yapısına göre yükselir (bir yetişkin ve bir çocuk için 36.973,44 €). Bunun yanında, oturduğun ev (vivienda habitual) hariç şirket dışı varlıkların değeri tek yetişkinli birimde 52.819,20 €'yu (bir yetişkin ve bir çocukta 73.946,88 €'yu) aşıyorsa net varlık değerlendirmesinden bağımsız olarak IMV'ye erişilemez. Birim üyelerinden biri faaliyeti sona ermemiş bir ticari şirketin yöneticisiyse (administrador de derecho) de ekonomik kırılgan sayılmazsın. Sayfa 2026 için geçerlidir.
A11: sevilla:mec-burslari-ab-disi-sart-ve-basvuru-donemi | B11: sevilla | C11: mec-burslari-ab-disi-sart-ve-basvuru-donemi | D11: İspanya'da Eğitim Bakanlığı (MEC) üniversite bursuna AB dışı vatandaş olarak başvurabilir miyim, hangi tutarlar verilir? | E11: AB dışı için üniversite bursu şartı: 18 yaşından küçük olmak ya da 31 Aralık 2025'te oturum izni almış olmak; tutarlar gelir eşiğine göre değişir (2026-2027) | F11: Koşullu evet: Bakanlığın üniversite (grado ve máster) bursunda genel şart İspanyol ya da AB üyesi devlet vatandaşı olmaktır; AB vatandaşı değilsen yabancıların hak ve özgürlüklerine ilişkin mevzuat uygulanır ve 18 yaşından küçüksen ya da 31 Aralık 2025 itibarıyla oturum izni (permiso de residencia) almışsan bursa hak kazanabilirsin; yalnız estancia izni (autorización de estancia) yetmez. 2026-2027 çağrısında üniversite bursunun tutarı aile gelirinin hangi eşikte olduğuna göre değişir; eşik değerleri aile biriminin üye sayısına göre belirlenir (örneğin 1 kişilik aile için yıllık 8.843 / 13.898 / 14.818 €, 4 kişilik aile için 22.107 / 38.242 / 40.773 €). Eşik 1'de ve altında: üniversiteye telafi edilen kayıt bursu, en az 1.700 € (gelire göre), öğrenim sırasında ikamet değiştirmen gerekiyorsa 2.700 €, 8 ve üzeri not için 50–125 € ve gelire ile nota göre hesaplanan değişken tutar. Eşik 2'de 1.700 € yoktur: kayıt bursu, değişken tutar, ikamet değişikliği için 2.700 € ve 8 ve üzeri not için 50–125 € verilir. Eşik 3'te kayıt bursu ve 8 ve üzeri not için en çok 125 € verilir; burs hakkı şu durumlarda yoktur: aile geliri eşik 3'ün üstündeyse; sermaye gelirleri ile değer artışı kazançları toplamı 2025'te 1.900 €'yu aşıyorsa; oturduğun ev dışındaki mülklerin katastro değeri çağrıdaki sınırları aşıyorsa; ticari faaliyet ve ortaklık gelirleri 2025'te 172.000 €'yu aşıyorsa. FP, bachillerato ve diğer üniversite dışı öğrenimlerin bursu için başvuru, Bakanlığın elektronik şubesi (sede electrónica) üzerinden yapılır ve süresi 19 Mayıs'ta sona ermiştir. | G11: MEC bursu, beca, becas y ayudas, AB dışı, oturum izni, sede electrónica, Ministerio de Educación, beca de matrícula | H11: planning;new;settled | I11: sevilla:kaynak:108;sevilla:kaynak:109 | J11: 46319 | K11: 9084 | L11: Hayır | M11: Taslak | N11: sevilla:aile | O11: Önce uyruğuna bak: İspanyol ya da AB üyesi devlet vatandaşıysan genel şartı karşılarsın; AB vatandaşı değilsen 18 yaşından küçük olmalı ya da 31 Aralık 2025 itibarıyla oturum izni (permiso de residencia) almış olmalısın. Üniversite bursunda diğer genel şartı da gör: aynı seviyede ya da daha yüksek bir diploman olmamalı. Akademik şartları gör: ilk yıl grado için 60 kredi kaydı ve üniversiteye girişi sağlayan sınavda ya da öğrenimde en az 5 puan; sonraki yıllarda önceki yıl kredilerinin alana göre belirli yüzdesini başarmış olmak gerekir (ayrıntı notta). FP, bachillerato ve diğer üniversite dışı bursların başvurusu Bakanlığın elektronik şubesinden (sede electrónica) yapılır: Cl@ve ya da elektronik sertifikanla ya da şubeye kayıtlı kullanıcı adı ve şifrenle giriş yap, çevrimiçi formu doldur. FP, bachillerato ve diğer üniversite dışı öğrenimlerde başvuru süresi 19 Mayıs'ta sona erdi; form doldurulurken belge istenmez, gerekli verileri bursları yürüten birimler kendileri sorgular. | R11: 2026-2027 çağrısında üniversite bursu bileşenleri (kayıt bursu üniversiteye telafi edilir, hesabına yatmaz). Eşik 1'de ve altında: en az 1.700 €; öğrenim sırasında ikamet değiştirmen gerekiyorsa 2.700 €; 8 ve üzeri not için 50 € – 125 €; ayrıca gelire ve nota göre hesaplanan değişken tutar. Eşik 2: kayıt bursu, değişken tutar, ikamet değişikliği için 2.700 €, 8 ve üzeri not için 50 € – 125 €. Eşik 3: kayıt bursu ve 8 ve üzeri not için en çok 125 €. | S11: Ekonomik şart olarak 2025 yılı aile birimi geliri esas alınır. AB vatandaşıysan ve sen ya da ailen İspanya'da sürekli ikamet etmiyor veya çalıştığını göstermiyorsa yalnız kayıt bedelini alabilirsin. Alana göre sonraki yıl şartı: mühendislik, mimarlık ve fen bilimlerinde önceki yıl kredilerinin en az %65'ini, sağlık bilimlerinde en az %80'ini, sosyal ve hukuk bilimleri, sanat ve beşeri bilimlerde en az %90'ını başarmış olmak gerekir. Tutarlar Real Decreto 179/2026 ile belirlenen 2026-2027 dönemine aittir.
A12: sevilla:endulus-okul-kaydi-basvuru-donemi-ve-gec-gelen-ogrenci | B12: sevilla | C12: endulus-okul-kaydi-basvuru-donemi-ve-gec-gelen-ogrenci | D12: Endülüs'te okul kaydı ne zaman ve nasıl yapılır, eğitim yılı ortasında gelen çocuk nasıl kaydolur? | E12: Genel kural Mart ayı başvurusu ve Secretaría Virtual; yıl ortasında gelen öğrenci için olağanüstü usul (Decreto 21/2020 md. 51) | F12: Genel kural: Endülüs'te kamu ve devlet destekli özel (concertado) okullara başvuru Mart ayında yapılır; 2026/27 için dönem 1-31 Mart (ikisi dahil) olarak açıklanmıştır. Kesin tarihler yıldan yıla değişebilir, başvurmadan önce Junta'nın eğitim portalından güncel dönemi doğrula. Mart başvurusu 2. kademe Educación Infantil (3-5 yaş), Educación Primaria, ESO ve Bachillerato içindir. O yıl kamu ya da concertado bir okulda kayıtlı olup aynı okulda devam edecek öğrenci Mart'ta başvuru vermez. Bir etabın son sınıfında okuyup sonraki etabın ilk sınıfına bağlı (adscrito) olduğu okulda devam edecek öğrenci de Mart'ta başvuru vermez; çoklu bağlantı (adscripción múltiple) durumu bunun dışındadır. Başvuru okula kâğıtla (Anexo III) ya da elektronik olarak Secretaría Virtual üzerinden verilir; her öğrenci için tek başvuru yapılır ve süre dışı başvuru öncelik kaybettirir. Genel usul bittikten sonra gelen öğrenci (incorporación tardía) için olağanüstü usul vardır: başvuru, çocuğun kabul edilmek istendiği okula ya da eğitim idaresinin il organına yapılır; boş yer varsa okul müdürü kabul eder ve kaydı Séneca sistemiyle yapar, boş yer yoksa başvuru il organına gönderilir. İl organı yer gösterirse matrikül, bildirimden sonraki günden başlayarak iki iş günü içinde yapılmalıdır. Genelleştirilmesi zor (difícil generalización) özel kaynaklar gerektiren çocukta, okulda boş yer olsa bile başvuru yalnız okulun bu kaynakları varsa kabul edilir; yoksa başvuru il organına gönderilir ve il organı bu kaynaklara sahip bir okulda yer verir. | G12: okul kaydı, escolarización, admisión, Secretaría Virtual, incorporación tardía, procedimiento extraordinario, Decreto 21/2020, plaza escolar | H12: planning;new;settled | I12: sevilla:kaynak:136;sevilla:kaynak:137 | J12: 46319 | K12: 9101 | L12: Hayır | M12: Taslak | N12: sevilla:aile | O12: Mart ayındaki genel başvuru döneminde tek bir başvuru formu doldur ve çocuğun öncelikle istediğin okulda (prioritario) başvurusunu ver; kâğıt için Anexo III'ü doldur, elektronik için Secretaría Virtual'ı kullan. Çocuk zaten kayıtlı olduğu okulda devam edecekse ya da bağlı (adscrito) okulda sonraki etabın ilk sınıfına geçecekse (çoklu bağlantı hariç) bu başvuru gerekmez. Başvuruda en çok dört yedek (subsidiario) okul yazabilirsin; okulun kayıtlı başvuru kopyasını sakla. Genel usul bittikten sonra geldiysen (taşınma, evlat edinme gibi acil okullaşma ihtiyacında) başvuruyu çocuğun gireceği okula ya da il eğitim organına ver. Okulda boş yer varsa müdür başvuruyu kabul eder ve kaydı Séneca sisteminde yapar; yer yoksa başvuru il organına gider. Çocuk genelleştirilmesi zor özel kaynaklar gerektiriyorsa başvuru yalnız okulun bu kaynakları varsa kabul edilir; yoksa il organı bu kaynaklara sahip bir okulda yer verir. İl organı sana yer gösterirse bildirimi izleyen günden başlayarak iki iş günü içinde atanan okulda matrikül yaptır. | P12: Başvuru formu: kâğıt için Anexo III, elektronik için Secretaría Virtual | Q12: Genel başvuru: Mart ayı (2026/27 için 1-31 Mart, ikisi dahil; kesin tarihler yıldan yıla değişebilir). Yıl ortası olağanüstü usul: genel usul bittikten sonra; il organı yer gösterirse matrikül için iki iş günü. | S12: Mart başvurusu genel kuraldır; her yılın kesin tarihleri değişebileceğinden güncel dönemi başvurmadan önce Junta'nın eğitim portalından doğrula. Yıl ortasındaki başvuru için belirli bir tarih yoktur; usul genel usul bittikten sonra başlar. Genelleştirilmesi zor özel kaynaklar gerektiren çocuk için başvuru yalnız okulun bu kaynakları varsa kabul edilir; yoksa başvuru il organına gönderilir ve il organı bu kaynaklara sahip bir okulda yer verir.
A13: sevilla:sevilla-kres-escuela-infantil-0-3-yas-basvurusu | B13: sevilla | C13: sevilla-kres-escuela-infantil-0-3-yas-basvurusu | D13: Sevilla'da 0-3 yaş kreş (escuela infantil) başvurusu nasıl yapılır, ne zaman? | E13: 16 haftalıktan 3 yaşa kadar; yeni başvuru her yıl Nisan'da, devam edenlerin yer ayırtma başvurusu Mart'ta başlar (2026/27'de 6 Nisan'a kadar sürdü) | F13: Junta de Andalucía'nın escuela infantil (0-3 yaş kreş) kayıtları 16 haftalıktan üç yaşına kadar olan çocuklar içindir; çocuğa bakan kişinin idari ikametinin (vecindad administrativa) Endülüs'te olması gerekir. Kreşe ilk kez girecekse yeni kabul (nueva admisión) başvurusu her yıl Nisan'da, eylülde başlayan eğitim yılı için yapılır; 2026/27 için dönem 1-30 Nisan 2026'ydı. Aynı kreşte devam edecek çocuklar için yer ayırtma (reserva de plaza) başvurusu Mart'ta başlar ve genel kurala göre bir ya da iki hafta açık kalır; 2026/27'de 16 Mart-6 Nisan 2026 arasındaydı, yani Nisan'ın başına kadar sürdü. Başvuru yılında üç yaşını dolduracak çocuk için kreş yeri istenemez. Bu süreç Junta'ya ait kreşler ile aile yardımı programına bağlı kreşler için işler. | G13: kreş, escuela infantil, 0-3 yaş, nueva admisión, reserva de plaza, Junta de Andalucía, Secretaría Virtual, Sevilla kreş başvurusu | H13: planning;new | I13: sevilla:kaynak:248;sevilla:kaynak:250 | J13: 46319 | K13: 900 | L13: Evet | M13: Taslak | N13: sevilla:aile | O13: Çocuğun yaşını ve ikametini kontrol et: 16 haftalık ile üç yaş arasında olmalı ve çocuğa bakan kişinin idari ikameti Endülüs'te olmalı. Çocuk kreşe ilk kez gidecekse Nisan'da yeni kabul başvurusu ver; form kreşlerde, Delegación Territorial'lerde ve Escolarización portalında bulunur. Çocuk bu yıl Junta'ya ait ya da yardım programına bağlı bir kreşe kayıtlıysa ve orada devam edecekse Mart'taki yer ayırtma başvurusunu ver; yeni kabul başvurusu yapma. İstersen başvuruyu Secretaría Virtual üzerinden elektronik ver; bunun için dijital sertifikan olmalı. Sonucu Mayıs'ta kreşin ilan panosunda yayımlanan listelerden izle. | P13: Başvuru formu (kreşlerden, Delegación Territorial'den ya da Escolarización portalından); elektronik başvuruda dijital sertifika | Q13: Yeni kabul: her yıl Nisan (2026/27 için 1-30 Nisan 2026). Yer ayırtma: Mart (2026/27 için 16 Mart-6 Nisan 2026). | S13: Yukarıdaki tarihler 2026/27 eğitim yılı takvimidir; sonraki yıllarda tarihler yeni takvimle yayımlanır, Nisan ayı yeni kabul için her yıl geçerli kuraldır.
A14: sevilla:sevilla-kres-sonuc-matrikul-bekleme-listesi-ve-olaganustu-basvuru | B14: sevilla | C14: sevilla-kres-sonuc-matrikul-bekleme-listesi-ve-olaganustu-basvuru | D14: Sevilla'da kreş başvurusundan sonra neler olur: sonuç, matrikül, bekleme listesi ve yeniden yerleştirme? | E14: Mayıs'ta puan listesi ve sonuç, Haziran'da matrikül; yer çıkmazsa yeniden yerleştirme ve Temmuz'da olağanüstü kabul | F14: Kreş başvurusunun ardından sırasıyla puan listesi, itiraz süresi, sonuç ve matrikül gelir. 2026/27 takviminde geçici puan listesi 7 Mayıs 2026'da yayımlandı, itiraz (alegaciones) süresi 8-21 Mayıs'tı, kabul sonucu 27 Mayıs'ta açıklandı. Kabul edilenlerin matrikülü 1-10 Haziran, bekleme listesindekilerin matrikülü 11-17 Haziran'dı. Kabul edilip matrikül yaptırmayanların başvurusu 18 Haziran'da vazgeçilmiş sayıldı. Yer bulamayanlar 19-25 Haziran'da yeniden yerleştirme (reubicación) isteyebildi; yer verilenler 26-30 Haziran'da matrikül yaptırdı. Olağanüstü kabul usulü (procedimiento extraordinario) 1 Temmuz'dan itibaren işler. | G14: kreş sonucu, matrikül, bekleme listesi, reubicación, renuncia, procedimiento extraordinario, Anexo, escuela infantil | H14: planning;new | I14: sevilla:kaynak:249;sevilla:kaynak:250 | J14: 46319 | K14: 901 | L14: Hayır | M14: Taslak | N14: sevilla:aile | O14: Mayıs'ta geçici puan listesine bak; puana itirazın varsa itiraz süresi içinde başvur (2026/27'de 8-21 Mayıs). Kabul edildiysen matrikülü Haziran başında yaptır (2026/27'de 1-10 Haziran); bekleme listesindeysen matrikül dönemini izle (2026/27'de 11-17 Haziran). Yer istemiyorsan Anexo VII (renuncia) formunu, kreşi değiştirmek istiyorsan Anexo VIII (cambio de centro) formunu, kreşten ayrılırken Anexo VI (baja) formunu kullan. Yer bulamadıysan Anexo IV formuyla yeniden yerleştirme iste (2026/27'de 19-25 Haziran); yer verilirse hemen sonra matrikül yaptır (26-30 Haziran). Hâlâ yer yoksa Temmuz'dan itibaren işleyen olağanüstü kabul için Anexo V formunu doldur. | P14: Anexo IV (yeniden yerleştirme) Anexo V (olağanüstü kabul) Anexo VI (kreşten ayrılma) Anexo VII (vazgeçme) Anexo VIII (kreş değiştirme) | Q14: 2026/27 takvimi: puan listesi 7 Mayıs, itiraz 8-21 Mayıs, sonuç 27 Mayıs, matrikül 1-10 Haziran, bekleme listesi matrikülü 11-17 Haziran, yeniden yerleştirme başvurusu 19-25 Haziran, olağanüstü kabul 1 Temmuz'dan itibaren. | S14: Tarihler 2026/27 eğitim yılı takvimidir; her yıl yeni takvim yayımlanır ve sıra aynı kalır.
A15: sevilla:sevilla-kres-ucret-yardimi-programa-de-ayuda-a-las-familias | B15: sevilla | C15: sevilla-kres-ucret-yardimi-programa-de-ayuda-a-las-familias | D15: Sevilla'da 0-3 yaş kreş için aile yardımı programı (Programa de ayuda a las familias) nasıl istenir? | E15: Junta'nın yıllık programı: yardım her eğitim yılı için ayrıca istenir, 2026/27'de başvuru 7 Nisan-6 Mayıs'tı | F15: Junta de Andalucía, üç yaşından küçük çocukların birinci kademe Educación Infantil merkezlerinde okullaşmasını teşvik etmek için ailelere yönelik bir yardım programı yürütür. Program yıllıktır; yardım her eğitim yılı için ayrıca istenmelidir. 2026/27 için yardım başvuru dönemi 7 Nisan-6 Mayıs 2026'ydı ve kreşte yer ayırtma ya da normal kabul sürecine katılan çocukları kapsıyordu. Programa bağlı (adherido) kreşler, kabul sürecine Junta'ya ait kreşlerle aynı takvimde katılır. | G15: kreş yardımı, Programa de ayuda a las familias, escuela infantil, 0-3 yaş, aile yardımı, Junta de Andalucía | H15: planning;new | I15: sevilla:kaynak:248;sevilla:kaynak:250 | J15: 46319 | K15: 902 | L15: Hayır | M15: Taslak | N15: sevilla:aile | O15: Çocuğun gideceği kreşin Junta'ya ait ya da yardım programına bağlı bir kreş olup olmadığını kreşin kendisinden öğren. Kreş yeri için yer ayırtma ya da normal kabul başvurunu yap. Yardım başvurusunu da aynı eğitim yılı için ayrıca yap; 2026/27'de dönem 7 Nisan-6 Mayıs 2026'ydı. Formu Escolarización portalının 0-3 yaş formlar sayfasından indir. Eğitim yılı değiştiğinde yardım için yeniden başvur. | P15: Yardım başvuru formu (Escolarización portalının 0-3 yaş formlar sayfasında) | Q15: Yıllık; 2026/27 için başvuru 7 Nisan-6 Mayıs 2026. | S15: Yardım her eğitim yılı için yeniden istenir; geçen yılın başvurusu yeni yıla geçmez.
A16: sevilla:sevilla-atal-ispanyolca-bilmeyen-cocuk-icin-okul-destegi | B16: sevilla | C16: sevilla-atal-ispanyolca-bilmeyen-cocuk-icin-okul-destegi | D16: Sevilla'daki devlet okullarında İspanyolca bilmeyen yabancı çocuklar için ATAL desteği nedir? | E16: Okul saatinde, özel öğretmenle verilen İspanyolca programı; ilkokul ve ESO'daki devlet okullarında | F16: ATAL (Aulas Temporales de Adaptación Lingüística, geçici dil uyum sınıfları), İspanyolca bilmeyen yabancı öğrencilere okul saatinde, bu iş için görevli öğretmenlerce verilen bir İspanyolca öğretim programıdır. Programda çocuğun okula ve çevreye uyumu, İspanyolcanın ders dili olarak öğrenilmesi ve köken kültürünün korunması hedeflenir. Endülüs Eğitim Bakanlığı (Consejería de Educación) programı devlet okullarının Educación Primaria ve ESO kademelerinde uygular; ders normalde çocuğun kendi sınıfında yürür, dili anlama ve konuşmada özel zorluk varsa sınıf dışı destek grupları kurulabilir ve çocuk dil artık belirleyici olmadığında sınıfa tam döner. ATAL öğretmeni üç ayda bir (trimestre başına) her çocuk için bireysel bir ilerleme raporu yazar ve sınıf öğretmenine verir. | G16: ATAL, İspanyolca desteği, yabancı öğrenci, Aulas Temporales de Adaptación Lingüística, Endülüs okul, ilkokul, ESO, uyum sınıfı | H16: new;settled | I16: sevilla:kaynak:251;sevilla:kaynak:246 | J16: 46319 | K16: 907 | L16: Hayır | M16: Taslak | N16: sevilla:aile | O16: Çocuğun okula kayıtlı olduğu devlet okulunun yönetimine İspanyolca bilmediğini bildir ve ATAL desteğini sor. Henüz okul belirlemediysen sorularını Sevilla'daki Delegación Territorial de Educación'a 955034200 numarasından ilet. Çocuk destek grubuna alınırsa dersin bir kısmını sınıf dışında İspanyolcayla geçirir; dili yeterince öğrendiğinde sınıfa tam döner. Üç ayda bir hazırlanan ilerleme raporunu sınıf öğretmeninden iste. | Q16: Okul saatinde, öğretim yılı boyunca | S16: Program devlet okullarının Educación Primaria ve ESO kademelerinde uygulanır.
A17: sevilla:sevilla-yenidogan-bebek-nufus-kaydi-registro-civil | B17: sevilla | C17: sevilla-yenidogan-bebek-nufus-kaydi-registro-civil | D17: Sevilla'da doğan bebeğin nüfus kaydı (Registro Civil) nerede ve hangi şartlarla yapılır? | E17: Sevilla'daki Registro Civil exclusivo Nº1; doğumdan 24 saat sonra 8 güne kadar süre, anne-baba evli olup olmamasına göre farklı usul | F17: Sevilla'da bebeğin kaydı Registro Civil exclusivo Nº1 de Sevilla'da yapılır. Bu ofis, Sevilla'da doğan bebekleri ya da Sevilla dışında doğmuş olsa da anne-babası kayıttan en az üç ay önce Sevilla'da empadronado (belediye kaydı) olanları, ya da ikisinin DNI'sinde aynı Sevilla adresi görünenleri kaydeder. Doğum kaydı için süre, doğumdan 24 saat sonra başlar ve 8 gündür; olağanüstü durumlarda 30 güne uzayabilir. Anne-baba evliyse biri ya da yetkilendirdiği kişi gelebilir; ilk çocuksa beyan formunu ikisi de imzalar ve soyadının babanınki mi annenin mi önce geleceğini gözlemler bölümüne yazar. Evli olmayan çiftlerde anne ve baba birlikte gelmek zorundadır. Kaydı yapılan ilk ortak çocuk için evli olmayan çiftlere aile cüzdanı (libro de familia) verilir. | G17: bebek kaydı, doğum kaydı, Registro Civil Sevilla, nüfus kaydı, libro de familia, empadronamiento, cita previa | H17: new;settled | I17: sevilla:kaynak:252;sevilla:kaynak:254 | J17: 46319 | K17: 908 | L17: Evet | M17: Taslak | N17: sevilla:aile | O17: Hastanenin verdiği sarı formu (impreso amarillo) anne-baba olarak ön ve arka yüzüyle doldur. Kayıt yerini belirle: Sevilla'da doğduysa ya da anne-baba kayıttan üç ay önce Sevilla'da empadronado ise ya da ikisinin DNI'sinde aynı Sevilla adresi varsa Sevilla'daki Registro Civil'e başvur. Anne-baba evliyse biri (ya da yetkilendirdiği kişi) gelebilir; ilk çocuksa beyan formunu ikisi de imzalar ve soyadı tercihini gözlemler kısmına yazar. Evli değillerse ikisi birlikte gider. Cita previa (randevu) için Adalet Bakanlığı'nın çevrim içi randevu sayfasını kullan ya da 600 15 80 95 numarasını ara; DNI'n yoksa aynı numaradan hangi kimlikle gelebileceğini sor. Anne boşanmışsa boşanma kararını ya da boşanmanın yazılı olduğu evlilik belgesini götür; baba reşit değilse expedientes bölümünden randevu al; anne reşit değilse velisiyle birlikte gel. | P17: Hastanenin sarı formu (ön ve arka yüz) Anne-babanın DNI'si (DNI'n yoksa kimlik için 600 15 80 95'i ara) Sevilla dışında doğan bebek için anne-babanın empadronamiento belgesi Boşanmış anne için boşanma kararı ya da boşanmanın yazılı olduğu evlilik belgesi | Q17: Doğumdan 24 saat sonra başlar, 8 güne kadar; olağanüstü durumda 30 güne kadar uzayabilir. | S17: Bazı sağlık merkezlerinde kayıt, anne-babanın merkezde imzaladığı resmî formla ve doktor raporunun elektronik gönderilmesiyle yapılır; bu durumda çoğunlukla Registro Civil ofisine gitmek gerekmez.
A18: sevilla:sevilla-dogum-sonrasi-saglik-sosyal-guvenlik-ve-padron-adimlari | B18: sevilla | C18: sevilla-dogum-sonrasi-saglik-sosyal-guvenlik-ve-padron-adimlari | D18: Sevilla'da doğumdan sonra hangi sağlık ve kayıt adımlarını sırayla yapmalısın? | E18: Taburcu belgeleri, lohusa ziyareti, topuk testi, Seguridad Social kaydı, sağlık kartı ve empadronamiento | F18: Doğum her şey yolundaysa 36-48 saat içinde taburcu ile sonuçlanır ve bu sırada anne ile bebeğin hastane çıkış raporu ile doğum belgesi verilir. Sonra sırayla: sağlık merkezinde randevular (lohusa ziyareti doğumdan 5-9 gün sonra ve bebeğin sağlık izlem programı), yaklaşık üçüncü günde topuk testi, Registro Civil kaydı, Seguridad Social'a (INSS) bebeğin kaydı, ardından sağlık kartı (tarjeta sanitaria) ve bebeğin oturduğun yerin belediyesinde padrón kaydı gelir. Hamilelik sırasında cinsel ve üreme sağlığı sorularını 7/24 ücretsiz 900 850 100 hattına sorabilirsin. | G18: doğum sonrası, taburcu, lohusa ziyareti, topuk testi, prueba del talón, Seguridad Social, tarjeta sanitaria, empadronamiento, libro de familia | H18: new | I18: sevilla:kaynak:254;sevilla:kaynak:273 | J18: 46319 | K18: 909 | L18: Hayır | M18: Taslak | N18: sevilla:aile | O18: Taburcu olurken anne ve bebeğin hastane çıkış raporunu ve doğum belgesini (certificado de nacimiento) al. Sağlık merkezinden lohusa ziyareti (doğumdan 5-9 gün sonra) ve bebeğin sağlık izlem programı için randevu iste. Topuk testini (prueba del talón) yaklaşık üçüncü günde yaptır; randevu gerekmez, sağlık merkezinde ya da tatil günlerinde acil birimlerinde yapılır. Bebeği Registro Civil'e kaydettir ve libro de familia'yı al. Bebeği INSS'in CAISS merkezlerinde ya da 'Tu Seguridad Social' sitesinden Seguridad Social'a kaydet; yüz yüze ya da posta yoluyla kayıtta Junta'nın sayfası libro de familia, DNI ve yararlanıcı başvuru formunu sayar; DNI'n yoksa hangi kimlikle başvurabileceğini INSS'in bilgi hattından (91 542 11 76 ya da 901 16 65 65) sor. Seguridad Social kaydından sonra bebek için sağlık kartı iste ve bebeği oturduğun yerin belediyesinde padrón'a yazdır. | P18: Hastane çıkış raporu ve doğum belgesi Libro de familia (ya da güncellenmemişse doğumun tam metin sertifikasıyla birlikte) DNI (yüz yüze ya da posta yoluyla kayıtta; DNI'n yoksa INSS bilgi hattını ara: 91 542 11 76 ya da 901 16 65 65) Seguridad Social yararlanıcı başvuru formu | Q18: Taburcu: normalde 36-48 saat; lohusa ziyareti 5.-9. gün; topuk testi yaklaşık 3. gün. | S18: Seguridad Social'a elektronik kayıt Tu Seguridad Social sitesinden yapılır.
A19: sevilla:sevilla-registro-civil-hangi-islem-icin-hangi-telefon | B19: sevilla | C19: sevilla-registro-civil-hangi-islem-icin-hangi-telefon | D19: Sevilla Registro Civil'de doğum belgesi, evlilik, babalık tanıma ve diğer işlemler için hangi numara aranır? | E19: İşleme göre ayrı telefon hatları ve babalık tanıma (reconocimiento de paternidad) için gerekenler | F19: Sevilla'daki Registro Civil exclusivo Nº1'in her işlem için ayrı bir telefon hattı var. Genel bilgi için 600 15 80 95 ya da 955 51 00 56; doğum, evlilik ve ölüm sertifikaları için 600 15 80 84; yeni doğan kaydı için 600 15 80 95; dinî nikâh için 600 15 80 91 ya da 955 51 00 39; medeni nikâh için 955 51 00 40; ölüm kaydı için 600 15 80 93; tanıma, soyadı sırası değişikliği gibi kenar not işlemleri için 600 15 80 92; vatandaşlık, hata düzeltme, ad-soyad değişikliği ve gecikmiş doğum kaydı gibi işlemler için 600 15 80 85 ya da 600 15 80 88. Sevilla Registro Civil sayfasına göre babalık tanıma için iki ebeveyn DNI'siyle birlikte gelir; DNI'n yoksa tanıma işlemlerinin hattı 600 15 80 92'den hangi kimlikle gelebileceğini sor. Baba Sevilla'da oturuyor olmalı ve tanınan kişinin doğum sertifikası (certificado literal de nacimiento) gerekir. | G19: Registro Civil Sevilla, telefon, doğum sertifikası, medeni nikâh, babalık tanıma, reconocimiento de paternidad, certificado literal, cita previa | H19: new;settled | I19: sevilla:kaynak:252;sevilla:kaynak:253 | J19: 46319 | K19: 910 | L19: Hayır | M19: Taslak | N19: sevilla:aile | O19: Yapmak istediğin işlemi yukarıdaki hatlardan uygun olana bağla; genel soru için 955 51 00 56 numarasını ya da registrocivil.sevilla@justicia.es adresini kullan. Medeni nikâh için registro.SE.matrimonio.jus@juntadeandalucia.es adresine yaz ya da 955 51 00 40 numarasını ara; belgeleri topla, cita previa al, çift ve bir tanıkla görüş ve törende iki tanık getir. Babalık tanıma için anne ve baba DNI'leriyle birlikte gelinir; DNI'n yoksa 600 15 80 92'yi arayıp hangi kimlikle gelebileceğini sor. Baba Sevilla'da oturuyorsa ve padrón kaydı sunuyorsa işlem Sevilla'da yapılır. Tanınan kişi 12 yaşından büyükse o da gelmelidir; reşitse tanınan gelir, anne gelmez. Randevuyu Adalet Bakanlığı'nın çevrim içi cita previa sayfasından al. | P19: Babalık tanıma için: iki ebeveynin DNI'si (DNI'n yoksa 600 15 80 92'yi ara), babanın padrón kaydı, tanınan kişinin certificado literal de nacimiento'su
A20: sevilla:sevilla-aile-destekleri-ekonomik-yardim-bulusma-noktasi-arabuluculuk | B20: sevilla | C20: sevilla-aile-destekleri-ekonomik-yardim-bulusma-noktasi-arabuluculuk | D20: Endülüs'te ve Sevilla'da çocuklu ailelere hangi sosyal destekler var: ekonomik yardım, buluşma noktası, arabuluculuk? | E20: Ayudas económicas familiares yalnız sosyal hizmetlerin önerisiyle başlar; Punto de Encuentro Familiar ve aile arabuluculuğu | F20: Junta'nın aile desteklerinin ilki ayudas económicas familiares'dir: bakmakla yükümlü olduğu çocukların temel ihtiyaçlarını karşılayacak kaynağı olmayan ailelere verilen geçici, nakdî ya da ayni yardımdır. Yardım süreci aile adına değil, toplum sosyal hizmetleri ekiplerinin (servicios sociales comunitarios) tespiti ve önerisiyle başlar; çocuk 18 yaşına gelince yardım sona erer. Bunun yanında acil durumlar için Ayudas de Emergencia Social vardır. Boşanma ya da ayrılık sırasında çocuğun anne-babasıyla görüşmesi güç oluyorsa ücretsiz ve geçici bir tarafsız mekân olan Punto de Encuentro Familiar kullanılabilir. Ailevi çatışmalar için Registro de Mediación Familiar'daki arabuluculardan yararlanılabilir; koşulları sağlayanlar için nöbetçi (turno de oficio) ücretsiz arabuluculuk vardır. | G20: aile yardımı, ayudas económicas familiares, servicios sociales, Punto de Encuentro Familiar, mediación familiar, Ayuda de Emergencia Social, Junta de Andalucía | H20: settled | I20: sevilla:kaynak:255;sevilla:kaynak:254 | J20: 46319 | K20: 911 | L20: Hayır | M20: Taslak | N20: sevilla:aile | O20: Çocuklarının temel ihtiyaçlarını karşılayamıyorsan oturduğun yerin toplum sosyal hizmetleri (servicios sociales comunitarios) merkezine git; ekonomik yardım süreci bu ekiplerin önerisiyle başlar. Acil ve olağanüstü bir ihtiyacın varsa aynı merkezde Ayuda de Emergencia Social'i sor. Ayrılık ya da boşanma sürecinde çocuğun diğer ebeveynle görüşmesi zorlaşıyorsa Punto de Encuentro Familiar hizmetini iste. Aile içi anlaşmazlıkta arabuluculuk istiyorsan Registro de Mediación Familiar'daki arabulucuları kullan; ücretsizlik koşulunu sağlıyorsan turno de oficio'yu sor. Genel sorular için Junta'nın 012 ya da 955 012 012 hattını ara. | R20: Punto de Encuentro Familiar hizmeti ücretsizdir. | S20: Ekonomik yardım koşullarla gelir: yardımı alan aile, sosyal hizmetlerin öngördüğü tamamlayıcı müdahaleyi kabul etmek zorundadır.
A21: sevilla:sevilla-egitim-delegasyonu-delegacion-territorial-adres-telefon | B21: sevilla | C21: sevilla-egitim-delegasyonu-delegacion-territorial-adres-telefon | D21: Sevilla'da Eğitim Bölge Müdürlüğü (Delegación Territorial de Educación) nerede, nasıl ulaşılır? | E21: Ronda de Tamarguillo adresi, doğrudan telefon ve okul kayıtları için ücretsiz bilgi hattı | F21: Junta de Andalucía'nın Sevilla ilindeki eğitim birimi Delegación Territorial de Educación en Sevilla'dır; Edificio Antiguo Matadero, Ronda de Tamarguillo s/n, Sevilla 41005 adresinde bulunur. Telefonu 955034200, e-postası informacion.dpse.ced@juntadeandalucia.es. Birimin servisleri arasında Servicio de Planificación y Escolarización (okullaşma planlaması), Servicio de Ordenación Educativa ve Servicio de Inspección Educativa vardır. Okullaşma sürecine dair soruları için Consejería'nın ayrı, ücretsiz bir hattı bulunur: 900 848 000, kesintisiz 8.00-19.00. | G21: Delegación de Educación Sevilla, eğitim müdürlüğü, Ronda de Tamarguillo, 955034200, 900 848 000, okullaşma | H21: planning;new;settled | I21: sevilla:kaynak:246;sevilla:kaynak:256 | J21: 46319 | K21: 912 | L21: Hayır | M21: Taslak | N21: sevilla:aile | O21: Yüz yüze gitmek istersen Ronda de Tamarguillo s/n adresindeki Edificio Antiguo Matadero'ya git. Telefonla ulaşmak için 955034200'ü ara; yazılı soru için informacion.dpse.ced@juntadeandalucia.es adresine yaz. Okul kaydı ve yerleştirme sorularında ücretsiz 900 848 000 hattını 8.00-19.00 arasında ara. Okullaşma konusunu sorarken Servicio de Planificación y Escolarización adını an. | Q21: 900 848 000 hattı 8.00-19.00 arasında kesintisiz. | R21: Bilgi hattı ücretsizdir.
A22: sevilla:sevilla-okul-basvurusu-ve-matrikul-online-secretaria-virtual-iande | B22: sevilla | C22: sevilla-okul-basvurusu-ve-matrikul-online-secretaria-virtual-iande | D22: Sevilla'da okul başvurusu ve matrikülü internetten nasıl yaparım: Secretaría Virtual, iANDE, iPASEN? | E22: Okula gitmeden başvuru ve matrikül; iANDE anahtarı iPASEN'de, ders ve yemek formları aynı işlemde | F22: Endülüs'te kamu ve devlet destekli okullara başvuru ve matrikül Secretaría Virtual üzerinden elektronik yapılabilir; böylece iş saatinde okula gitmek gerekmez. Kimlik doğrulaması için üç yol var: iANDE anahtarı, dijital sertifika ve Cl@ve. iANDE anahtarını iPASEN uygulamasındaki Administrador PASEN mesajında bulursun; her çocuk için ayrı anahtar verilir. Yeni anahtar gerekiyorsa herhangi bir okula yüz yüze gitmen gerekir. Online matrikülde ders seçimi yapılır, comedor escolar, aula matinal ve extraescolar formları doldurulur ve görüntü kullanım izni verilir. Matrikül istersen okulda yüz yüze de yapılabilir. Kamu okullarının ve concertado okulların concertada olan kademelerinin 3-5 yaş (Infantil ikinci kademe) kabul süreci tüm Endülüs için aynıdır; concertado okulların concertada olmayan kademeleri farklı olabilir, concertado olmayan özel okullar ise kendi tarih ve koşullarını belirler. Bunları o okuldan öğren. | G22: Secretaría Virtual, iANDE, iPASEN, Cl@ve, online okul kaydı, matrikül, iEscolariza, Endülüs okul başvurusu, escolarización | H22: planning;new | I22: sevilla:kaynak:256;sevilla:kaynak:257 | J22: 46319 | K22: 903 | L22: Hayır | M22: Taslak | N22: sevilla:aile | O22: iPASEN uygulamasını güncelle; mesajlarında Administrador PASEN'den gelen iANDE iletisini bul. İletide her çocuğun anahtarı yazılıdır. iANDE anahtarın yoksa ya da yenisi gerekiyorsa herhangi bir okula yüz yüze git ve iste; dijital sertifika ya da Cl@ve de kullanılabilir. Secretaría Virtual takviminde Solicitudes bölümünden ilgili işlemin bağlantısını aç; bağlantı yalnız ilgili dönem açıkken çalışır. Online matrikülde ders seçimini yap, comedor, aula matinal ve extraescolar formlarını doldur ve görüntü kullanım iznini ver. Okulda yüz yüze yapmak istersen Educación'ın yayımladığı matrikül formlarını indir ve okula götür. Okul ve adres puanı sorgulamak için iEscolariza uygulamasını kullan; kayıt sorularında 900 848 000 numarasını ara. | P22: iANDE anahtarı (iPASEN'den) ya da dijital sertifika ya da Cl@ve Yüz yüze matrikülde: Educación'ın matrikül formu | Q22: Hat 8.00-19.00 arasında kesintisiz; başvuru ve matrikül bağlantıları ilgili dönem açıkken çalışır. | S22: Concertado okulların concertada olmayan kademelerinde ve concertado olmayan özel okullarda başvuru tarihlerini ve koşullarını okulun kendisi belirler.
A23: sevilla:sevilla-okul-yeri-yetersizse-puanlama-ve-oncelik-kriterleri | B23: sevilla | C23: sevilla-okul-yeri-yetersizse-puanlama-ve-oncelik-kriterleri | D23: Sevilla'da okulda yer yetersizse başvurular nasıl puanlanır: kardeş, yakınlık, engel, gelir ve öncelik hakları? | E23: Endülüs kabul ölçütleri: kardeş 14 puan, engel 2-4 puan, gelir yalnız izin verirsen; bağlı okul ve zorunlu taşınma önceliklidir | F23: Bir okulda başvuru sayısı yer sayısını aşarsa kabul şu ölçütlerle sıralanır: okulda kayıtlı kardeş, evin ya da veli iş yerinin yakınlığı, çocukta/ebeveynde/kardeşte engel, ailenin kişi başı yıllık geliri, kalabalık (numerosa) ve tek ebeveynli aile, velilerin çalışması, birinci kademe Educación Infantil'e kayıtlı olma, tek kardeşi olma ve çoğul doğum; Bachillerato'da ayrıca not ortalaması da sayılır. Kardeşler farklı sınıflar için aynı okula başvurursa biri kabul edilince diğerlerine 14 puan verilir (birikmez); aynı sınıfa başvuru varsa biri kabul edilince diğerleri de kabul edilir. Çocukta %33 ile %66 arası engel 3 puan, %66 ve üstü 4 puandır; gelişim bozukluğu da 3 puan sayılır ama yalnız Infantil ikinci kademe (3-5 yaş) başvurularında; velide %33-66 arası 2, %66 ve üstü 3 puan; her engelli kardeş yarım puan (en çok 2). Bağlı (adscrito) okuldan gelenler, velisi o okulda haftada en az 10 saat çalışanlar ve zorunlu iş taşınması gibi nedenlerle gelen aileler öncelik alır. | G23: baremo, puanlama, okul kabul ölçütleri, kardeş puanı, familia numerosa, adscrito, prioridad, Decreto 21/2020, escolarización | H23: planning;new | I23: sevilla:kaynak:136 | J23: 46319 | K23: 904 | L23: Hayır | M23: Taslak | N23: sevilla:aile | O23: Kardeşin başvurduğun okulda kayıtlıysa bunu başvuruda belirt; farklı sınıf için 14 puan alırsın. Adresi mi yoksa velinin iş yerini mi esas alacağını başvuruda seç; çoğu bilgiyi idare kendi kayıtlarından alır, itiraz edersen belgeleri sen sunarsın. Gelir puanını istiyorsan Vergi İdaresi'nin (AEAT) gelir bilgisini vermesine yazılı izin ver; istemiyorsan izin vermeyebilirsin. Çalışma puanı için bakım sorumluluğu olan tüm velilerin, başvuru döneminin başlangıç tarihinden önceki en az altı ay kesintisiz ve haftada en az 20 saat çalışıyor olması gerekir. Kalabalık aile belgen (familia numerosa) süresi dolmuşsa yenileme başvurusunu yap ve kabul kararı çıkmadan önce belgeyi ilet. Başvuruda en çok dört yedek okul yaz; her okulun puanını kamu okulunda okul konseyi, concertado okulda okulun sahibi (titular) hesaplar. | P23: Gerekirse: yürürlükte familia numerosa belgesi Libro de familia (tek ebeveynli aile ya da çoğul doğum için onaylı kopya) Empadronamiento belgesi (adres bilgisi tutmuyorsa) | S23: Bu ölçütler yer yetersiz olduğunda sıralama içindir; yer yeterliyse başvuru doğrudan kabul edilir. Altı aylık çalışma koşulu ve 20 saat sınırı yalnız çalışma puanı içindir.
A24: sevilla:sevilla-okul-yemegi-sabah-bakimi-ve-etkinlikler-servicios-complementarios | B24: sevilla | C24: sevilla-okul-yemegi-sabah-bakimi-ve-etkinlikler-servicios-complementarios | D24: Sevilla'da okul yemeği, sabah bakımı ve etkinlikler (comedor, aula matinal, extraescolar) nasıl istenir, indirim ne zaman? | E24: Hizmetler matrikül döneminde istenir; ücretsizlik ya da indirim (bonificación) için ayrı kısa dönem Eylül'de | F24: Okul yemeği (comedor escolar), sabah bakımı (aula matinal) ve okul sonrası etkinlikler (actividades extraescolares) tamamlayıcı hizmet (servicios complementarios) sayılır. Bu hizmetler matrikül döneminde istenir. Kamu okullarında Infantil ikinci kademe, Primaria ve özel eğitim için matrikül 1-8 Haziran'dır; sık sorulan sorular sayfasının hizmetler bölümü ise aynı etaplar için hizmet isteği süresini 1-10 Haziran diye yazar. İki tarih tutmadığı için hizmet formlarını matrikülle birlikte 8 Haziran'a kadar vermek ikisine de uyar. ESO'daki institutos için matrikül ve hizmet isteği 1-10 Temmuz'dur. Hizmetlerin ücretsiz olması ya da indirimli olması (gratuidad/bonificación) için ayrı dönem 1-7 Eylül'dür; son gün 7 Eylül'dür. Okulların sunduğu hizmetlerin bilgisi okul ilan panosundadır. Hizmet istemek, kabul ölçütü olarak hiçbir puan getirmez. Kamu ve concertado okullar ücretsiz eğitim için aileden para isteyemez; bu hizmetler ve extraescolar etkinlikler ise gönüllüdür. | G24: comedor escolar, aula matinal, extraescolar, servicios complementarios, bonificación, okul yemeği, gratuidad, matrikül | H24: planning;new;settled | I24: sevilla:kaynak:136 | J24: 46319 | K24: 906 | L24: Hayır | M24: Taslak | N24: sevilla:aile | O24: Okulun ilan panosundan comedor, aula matinal ve extraescolar hizmetlerinin bilgisine bak. Hizmetleri matrikülle birlikte ve en geç 8 Haziran'a kadar iste: Infantil ikinci kademe, Primaria ve özel eğitim için matrikül 1-8 Haziran (hizmetler bölümü 1-10 Haziran yazar), ESO için 1-10 Temmuz (2026/27 dönemi). Online matrikülde ilgili formlar aynı işlemde bulunur. Ücretsizlik ya da indirim için 1-7 Eylül arasında ayrıca başvur. Okul eğitim için ücret isterse bunun yasal olmadığını hatırla; gönüllü olan yalnız hizmetler ve extraescolar etkinliklerdir. | P24: Okulun hizmet formları (online matrikülde Secretaría Virtual'da) | Q24: Hizmet isteme: matrikülle birlikte (matrikül 1-8 Haziran, hizmetler bölümü 1-10 Haziran yazar; ESO için 1-10 Temmuz); indirim: 1-7 Eylül. | S24: Ücretsizlik ya da indirim başvurusunun son günü 7 Eylül'dür.
A25: sevilla:sevilla-okul-yerlestirme-sonuclari-itiraz-ve-matrikul-takvimi | B25: sevilla | C25: sevilla-okul-yerlestirme-sonuclari-itiraz-ve-matrikul-takvimi | D25: Sevilla'da okul yerleştirme sonuçları ne zaman açıklanır, itiraz ve matrikül nasıl yürür? | E25: 2026/27 takvimi: puan listesi Nisan, sonuç 14 Mayıs, recurso de alzada 26 Mayıs-25 Haziran, matrikül Haziran-Temmuz | F25: Okul başvurusu verildikten sonra süreç sırasıyla şöyle ilerler. 2026/27 takvimine göre puanlı liste 17-20 Nisan'da yayımlandı, ardından 10 ders günü süren dinleme (audiencia) dönemi 21 Nisan'da başladı. Eşit puanlar 13 Mayıs'ta kurayla çözüldü, kabul kararı 14 Mayıs'ta yayımlandı, tercih ettiği okulda yer bulamayanlar 25 Mayıs'ta yeniden yerleştirildi (reubicación). Recurso de alzada ve itirazlar 26 Mayıs-25 Haziran arasında yapıldı. Matrikül: Infantil ikinci kademe, Primaria ve özel eğitim 1-8 Haziran, ESO, özel eğitim ve Bachillerato 1-10 Temmuz, ek sınavla sınıfa geçecek Bachillerato öğrencileri 1-8 Eylül. Başvuru dönemi için takvim sayfası 1 Mart-7 Nisan 2026'yı gösterir; sık sorulan sorular sayfası ise 1-31 Mart yazar; iki sayfa tutmadığı için başvuruyu 31 Mart'a kadar vermek ikisine de uyar. Matrikül yaptırmak, yer verilen okulda zorunludur. | G25: okul sonuçları, recurso de alzada, matrikül takvimi, sorteo, reubicación, audiencia, escolarización 2026/2027, itiraz | H25: planning;new | I25: sevilla:kaynak:247;sevilla:kaynak:136 | J25: 46319 | K25: 905 | L25: Hayır | M25: Taslak | N25: sevilla:aile | O25: Başvuruyu 31 Mart'a kadar ver: takvim sayfası 7 Nisan'a kadar gösterse de sık sorulan sorular sayfası 1-31 Mart yazar. Puanlı listeye bak ve dinleme (audiencia) döneminde itirazını okula yaz. Kabul kararını (2026/27'de 14 Mayıs) izle; tercih ettiğin okulda yer bulamadıysan yeniden yerleştirme sonucunu bekle (2026/27'de 25 Mayıs). Karara itiraz için recurso de alzada ver; bunun için önce okulda puan itirazı yapmış olman gerekmez. Yer verilen okulda matrikülü kendi etabının tarihinde yaptır: Infantil ikinci kademe ve Primaria 1-8 Haziran, ESO ve Bachillerato 1-10 Temmuz (2026/27). Bir öğrenci için yalnız tek başvuru ver; birden fazla ya da süre dışı başvuru önceliğini kaybettirir. | P25: Okul başvuru kopyası (okulun kaydettiği) | Q25: 2026/27: puanlı liste 17-20 Nisan, sorteo 13 Mayıs, karar 14 Mayıs, yeniden yerleştirme 25 Mayıs, recurso 26 Mayıs-25 Haziran, matrikül 1-8 Haziran / 1-10 Temmuz / 1-8 Eylül. | S25: Tarihler 2026/27 takvimidir; her yıl yeni takvim yayımlanır.
A26: sevilla:familia-numerosa-unvani-alma-yenileme-ve-sevilla-basvurusu | B26: sevilla | C26: familia-numerosa-unvani-alma-yenileme-ve-sevilla-basvurusu | D26: Çok çocuklu aile unvanı (título de familia numerosa) Endülüs'te nasıl alınır ve yenilenir, Sevilla'da nereye başvurulur? | E26: 3 ve üzeri çocuk: 5 çocuktan itibaren especial, 4 çocukta özel durumlarda da especial, diğerleri general; yenileme unvan bitmeden önceki 3 ay içinde | F26: Bir ya da iki ebeveyn ile üç veya daha fazla çocuğu olan aile (çocuklar ortak olmasa da) Endülüs'te título de familia numerosa için başvurabilir. Especial kategori; 5 ve üzeri çocuk, 4 çocuktan en az 3'ü çoklu doğum, çoklu evlat edinme veya çoklu sürekli ya da evlat edinme öncesi koruyucu aile kaynaklıysa ya da 4 çocuklu ailede kişi başı yıllık gelir IPREM'in %75'ini aşmıyorsa geçerlidir; geri kalan aileler general kategorisindedir. Başvuru, ikamet ettiğin ilin Delegación Territorial'ine yönelik Nº 003206/2 formuyla yapılır; Sevilla'daki delegasyon Luis Montoto 89'dadır (telefon 955 00 68 28). Başvuruyu ebeveynlerden biri ya da yasal ehliyeti olan başka bir aile üyesi yapabilir. | G26: familia numerosa, título de familia numerosa, çok çocuklu aile, aile unvanı, Endülüs aile, VEAJA, categoría especial, renovación | H26: new;settled | I26: sevilla:kaynak:447;sevilla:kaynak:448 | J26: 46320 | K26: 913 | L26: Hayır | M26: Taslak | N26: sevilla:aile | O26: Ailenin kapsama girip girmediğine bak: üç ya da daha fazla çocuk; çocuklar bekâr ve 21 yaşından küçük olmalı (üniversite, yüksek meslek okulu gibi eğitimdeyse ya da iş bulmaya yönelik eğitim görüyorsa 25 yaş dahil), seninle yaşamalı ve sana ekonomik olarak bağlı olmalı. %33'ün üstünde engelli ya da çalışamaz durumdaki çocukta yaş sınırı yoktur. Çocuğun yıllık geliri IPREM'i aşmıyorsa ekonomik bağımlılık sürer. Kategoriyi belirle: 5 ve üzeri çocuk ya da 4 çocuktan en az 3'ü çoklu doğum, çoklu evlat edinme veya çoklu sürekli ya da evlat edinme öncesi koruyucu aile kaynaklıysa especial; kişi başı yıllık geliri IPREM'in %75'ini aşmayan 4 çocuklu aile de especial; geri kalan aileler general. Resmî formu (Nº 003206/2) doldur ve imzala: ilk başvuruda EXPEDICIÓN, yenilemede renovación, değişiklikte modificación kutusunu işaretle; yenileme ve değişiklikte unvan numarasını yaz. Form ve belgeler İspanyolca olmalı, yabancı dildeki belge İspanyolcaya çevrilmiş ve legalize edilmiş olmalı. Belgeleri hazırla: kimlikler, Libro de Familia, empadronamiento belgeleri ve gerekiyorsa gelir beyanı (aşağıdaki belge listesine bak). İdare geçerli DNI'ı olanların kimlik bilgilerini ve Endülüs'teki bir belediyede kayıtlı olanların ikamet bilgilerini kendisi sorgulayabilir; yalnız sorgulanamayan kişiler için belge ekle. Formu ikamet ettiğin ilin Delegación Territorial'ine yönelterek ver; Sevilla'da bu delegasyon Luis Montoto 89'dadır. İnternetten VEAJA'dan (dijital sertifika veya Cl@ve gerekir) ya da Presentación Electrónica General'den, yüz yüze ise herhangi bir kamu kayıt bürosundan (oficina de asistencia en materia de registros) veya postaneden verebilirsin. Yenilemeyi unvanın bitmesinden önceki 3 ay içinde iste. VEAJA ile yenilersen idare işlemi sürdürürken geçici belge (certificado provisional) çıkabilir; yenilemede çocukların üniversite kaydı gibi belgeleri başvuruyla birlikte eklemen gerekmez, ancak idare isterse bu belgeleri sonradan vermeyi taahhüt edersin. Ailede değişiklik olursa 3 ay içinde bildir; 4 çocuklu ailenin especial kategorisi gelire dayanıyorsa ya da ekonomik bağımlılığı gelirle kanıtlıyorsan her yılın ilk üç ayında önceki yılın gelir beyanını ver; bu gelirler idarenin elinde zaten varsa tekrar vermen gerekmez. | P26: Başvuru formu Nº 003206/2 (Anexo I), imzalı Ailenin yasal olarak kimlik taşıması gereken üyelerinin geçerli DNI, NIE veya pasaport kopyası (geçerli DNI'ı olanların kimlik bilgilerini idare kendisi sorgulayabilir; yalnız sorgulanamayanlar için gerekir) Libro de Familia kopyası (üçüncü ülke vatandaşlarında benzeri belge); ilk başvuruda her durumda gerekir Her aile üyesi için bireysel empadronamiento belgesi ya da toplu empadronamiento belgesi; yalnız idare ikamet bilgisini sorgulayamıyorsa gerekir (idare yalnız Endülüs'teki belediyelerde kayıtlı kişileri sorgulayabilir); DNI'ı olmayan 14 yaş altı çocuklar için bunlardan biri şart Özel kategori ya da ekonomik bağımlılık için gelir gerekiyorsa: 16 yaş üstü tüm aile üyelerinin önceki yıl gelirine dair beyan (formun 4. bölümü) Aile üyelerinden birinin oturum kartı yenileme aşamasındaysa formun 5. bölümündeki beyan AB/AEA dışı başvuranda: ailenin tüm üyelerinin geçerli yabancı kimlik kartı (tarjeta de identidad de extranjero) İlk başvuruda 21 yaşından büyük öğrenci çocuk varsa öğrenim belgesi Özel durumlarda (boşanma, engel, koruyucu aile gibi) başvuru formunun talimatlarında sayılan ek belgeler | Q26: Yenileme: unvan bitmeden önceki 3 ay içinde. Değişiklik (aile üyeleri veya koşullar değişirse): değişimden sonraki 3 ay içinde. | S26: İki çocuklu aile de şu durumlarda aynı kapsama girer: çocuklardan en az biri %33 ve üzeri engelli ya da çalışamaz durumdaysa; eşi ölmüş ebeveynin iki çocuğu varsa; tek ebeveyn %65 ve üzeri engelliyse; iki ebeveynin ikisi de engelliyse, en az biri %65 ve üzeri engelliyse ya da çalışamaz durumdaysa. Ayrı yaşayan ya da boşanmış ebeveyn, nafaka yükümlülüğünü gösteren mahkeme kararını sunarsa ve çocuklar ekonomik olarak ona bağlıysa, 3 ve üzeri çocuk için de başvurabilir; çocuklarla aynı evde yaşaması şart değildir. %33'ün üstünde engelli ya da çalışamaz durumdaki çocuk kategori hesabında iki sayılır. Aile üyeleri İspanyol ya da AB/AEA vatandaşıysa İspanya'da ikamet etmeli; başka bir AB/AEA ülkesinde yaşıyorlarsa ebeveynlerden en az biri İspanya'da ücretli ya da serbest çalışmalı. Başka ülke vatandaşlarında hak veren tüm aile üyeleri İspanya'da ikamet etmeli. | T26: {"kind": "steps", "title": "Aile unvanı başvurusu", "note": "Şematik", "items": [{"key": "1", "title": "Kapsamı kontrol et", "text": "Ailenin kapsama girip girmediğine bak: üç ya da daha fazla çocuk; çocuklar bekâr ve 21 yaşından küçük olmalı (üniversite, yüksek meslek okulu gibi eğitimdeyse ya da iş bulmaya yönelik eğitim görüyorsa 25 yaş dahil), seninle yaşamalı ve sana ekonomik olarak bağlı olmalı. %33'ün üstünde engelli ya da çalışamaz durumdaki çocukta yaş sınırı yoktur. Çocuğun yıllık geliri IPREM'i aşmıyorsa ekonomik bağımlılık sürer."}, {"key": "2", "title": "Kategoriyi belirle", "text": "Kategoriyi belirle: 5 ve üzeri çocuk ya da 4 çocuktan en az 3'ü çoklu doğum, çoklu evlat edinme veya çoklu sürekli ya da evlat edinme öncesi koruyucu aile kaynaklıysa especial; kişi başı yıllık geliri IPREM'in %75'ini aşmayan 4 çocuklu aile de especial; geri kalan aileler general."}, {"key": "3", "title": "Formu doldur", "text": "Resmî formu (Nº 003206/2) doldur ve imzala: ilk başvuruda EXPEDICIÓN, yenilemede renovación, değişiklikte modificación kutusunu işaretle; yenileme ve değişiklikte unvan numarasını yaz. Form ve belgeler İspanyolca olmalı, yabancı dildeki belge İspanyolcaya çevrilmiş ve legalize edilmiş olmalı."}, {"key": "4", "title": "Belgeleri hazırla", "text": "Belgeleri hazırla: kimlikler, Libro de Familia, empadronamiento belgeleri ve gerekiyorsa gelir beyanı (aşağıdaki belge listesine bak). İdare geçerli DNI'ı olanların kimlik bilgilerini ve Endülüs'teki bir belediyede kayıtlı olanların ikamet bilgilerini kendisi sorgulayabilir; yalnız sorgulanamayan kişiler için belge ekle."}, {"key": "5", "title": "Başvuruyu ver", "text": "Formu ikamet ettiğin ilin Delegación Territorial'ine yönelterek ver; Sevilla'da bu delegasyon Luis Montoto 89'dadır. İnternetten VEAJA'dan (dijital sertifika veya Cl@ve gerekir) ya da Presentación Electrónica General'den, yüz yüze ise herhangi bir kamu kayıt bürosundan (oficina de asistencia en materia de registros) veya postaneden verebilirsin."}, {"key": "6", "title": "Yenilemeyi zamanında iste", "text": "Yenilemeyi unvanın bitmesinden önceki 3 ay içinde iste. VEAJA ile yenilersen idare işlemi sürdürürken geçici belge (certificado provisional) çıkabilir; yenilemede çocukların üniversite kaydı gibi belgeleri başvuruyla birlikte eklemen gerekmez, ancak idare isterse bu belgeleri sonradan vermeyi taahhüt edersin."}, {"key": "7", "title": "Değişiklikleri bildir", "text": "Ailede değişiklik olursa 3 ay içinde bildir; 4 çocuklu ailenin especial kategorisi gelire dayanıyorsa ya da ekonomik bağımlılığı gelirle kanıtlıyorsan her yılın ilk üç ayında önceki yılın gelir beyanını ver; bu gelirler idarenin elinde zaten varsa tekrar vermen gerekmez."}]}
A27: sevilla:kira-sozlesmesi-suresi-ve-uzama | B27: sevilla | C27: kira-sozlesmesi-suresi-ve-uzama | D27: İspanya'da konut kira sözleşmesi en az kaç yıl sürer ve nasıl uzar? | E27: Konut kirasında en az süre 5 yıl (kiraya veren tüzel kişiyse 7); sözleşme yıllık uzar, kiracı 30 gün önceden bildirerek uzamayı durdurabilir | F27: Konut kira sözleşmesinde en az süre kural olarak 5 yıldır (kiraya veren tüzel kişiyse 7 yıl): taraflar süreyi özgürce belirler, ancak süre bundan kısa yazılırsa vade gününde sözleşme, bu en az süreye ulaşana dek yıllık dönemlerle zorunlu olarak uzar. İstisnalar vardır. Kiraya veren gerçek kişiyse ve sözleşmeye baştan açıkça, kendisi ya da birinci derece (kan ya da evlat edinme yoluyla) yakınları için (kesinleşmiş ayrılık, boşanma ya da evlilik iptali kararı hâlinde eşi için de) evi kalıcı konut olarak ihtiyaç duyduğunu yazmışsa, ilk yıldan sonra nedenini belirterek en az 2 ay önceden bildirip evi geri isteyebilir; bu durumda zorunlu uzama işlemez (md. 9.3). Kiraya veren ya da yakınları evi çıkıştan sonraki 3 ay içinde kullanmazsa kiracı 30 gün içinde eve geri konulmayı ya da tazminat almayı seçebilir. Geçici konut sözleşmeleri (kiracının asıl evinden haklı ve belgelenebilir bir nedenle geçici olarak ayrı kaldığı dönemde konut ihtiyacını karşılayan kira) bu en az süre kurallarına tabi değildir; süreleri 31 günden uzun olmalı ve kural olarak 12 ayı aşmaz (md. 9 bis). Uzamasını istemiyorsan, en az süre dolana dek vade gününden en az 30 gün önce kiraya verene yenilemek istemediğini bildirirsin. Süre yazılmamışsa ya da belirsizse sözleşme bir yıllık sayılır ve yıllık uzatma hakkın yine geçerlidir. Geçici konut hükümleri 6 Ekim 2026 tarihli Real Decreto-ley 29/2026 ile geldi; kararname (Real Decreto-ley) olduğu için ileride değişebilir ve aynı hükmü getiren daha önceki Real Decreto-ley 26/2026 Meclis kararıyla kaldırılmıştı (2 Ekim 2026 tarihli Resolución). Kira yasası 2026'da değişiyor; bu kart 7 Ekim 2026 tarihli konsolide metne göre (yayım 7 Ekim, yürürlük 8 Ekim). | G27: kira sözleşmesi, alquiler, Ley de Arrendamientos Urbanos, LAU, kira süresi, prórroga, arrendamiento de vivienda | H27: planning;new | I27: sevilla:kaynak:090 | J27: 46319 | K27: 9066 | L27: Hayır | M27: Taslak | N27: sevilla:ev | O27: Sözleşmedeki süreye bak: taraflar süreyi özgürce belirler; süre 5 yıldan (kiraya veren tüzel kişiyse 7 yıldan) kısaysa vade gününde sözleşme en az süreye ulaşana dek yıllık dönemlerle zorunlu olarak uzar. Kiraya veren gerçek kişiyse, sözleşmede kendisi ya da birinci derece yakınları için evi kalıcı konut olarak isteme ihtiyacının baştan açıkça yazılıp yazılmadığına bak; yazılmışsa ilk yıldan sonra, nedeni belirtilerek en az 2 ay önceden yapılan bildirimle ev geri istenebilir ve zorunlu uzama işlemez. Sürenin sözleşme tarihinden ya da ev sana teslim edildiği tarihten (hangisi sonraysa) başladığını bil; teslim tarihini ispat etmek kiracıya düşer, bu yüzden teslim tarihini gösteren bir kayıt tut. En az süre dolmadan gelen bir vade gününde uzamak istemiyorsan, sözleşmenin bitiş tarihinden ya da yıllık uzamalardan birinin bitişinden en az 30 gün önce kiraya verene yenilemek istemediğini bildir. Sözleşmede süre yazmıyorsa ya da süre belirsizse, sözleşmenin bir yıllık yapıldığını bil; yıllık uzatma hakkın bu durumda da geçerlidir. Geçici konut sözleşmesi yapıyorsan en az süre kuralının işlemediğini bil: süre 31 günden uzun olmalı ve kural olarak 12 ayı aşmaz. | Q27: Kira yasası 2026'da değişiyor; bu kart 7 Ekim 2026 tarihli konsolide metne göre (yayım 7 Ekim, yürürlük 8 Ekim). Geçici konut hükümleri (md. 2.3, 9.4, 9 bis) 6 Ekim 2026 tarihli Real Decreto-ley 29/2026 ile geldi; kararname (Real Decreto-ley) olduğu için ileride değişebilir. En az süre 5 yıl (kiraya veren tüzel kişiyse 7 yıl); uzamayı durdurma bildirimi vade gününden en az 30 gün önce.
A28: sevilla:kira-depozitosu-fianza-ve-iade | B28: sevilla | C28: kira-depozitosu-fianza-ve-iade | D28: İspanya'da kira depozitosu (fianza) ne kadardır ve nasıl geri alınır? | E28: Konutta fianza bir aylık kiradır; bakiye anahtar tesliminden bir ay sonra iade edilmemişse yasal faiz işler; fianza dışında ek güvence de kararlaştırılabilir | F28: Konutta fianza bir aylık kiradır ve sözleşme yapılırken para olarak verilmesi zorunludur. Sözleşme bitince iade edilecek bakiye, anahtarların tesliminden bir ay sonra hâlâ iade edilmemişse yasal faiz işler. Sözleşme bitince taraflar evin durumunu imzalı yazılı bir belgeyle kaydeder; belge hiç imzalanmazsa ya da belgede hiçbir kusur yazılmazsa, aksi ispatlanmadıkça ev uygun durumda teslim edilmiş sayılır. İlk 5 yıl (kiraya veren tüzel kişiyse ilk 7 yıl) fianza güncellenmez; her uzamada kiraya veren artırılmasını, kiracı azaltılmasını isteyebilir. Fianza dışında taraflar ek bir güvence kararlaştırabilir: konut sözleşmelerinde 5 yıla kadar (kiraya veren tüzel kişiyse 7 yıla kadar) süreli sözleşmede bu ek güvence en çok iki aylık kira, geçici kiralamalarda en çok bir aylık kiradır; kiracıdan kira ödememe sigortası ya da benzeri bir sigorta kapsamı yaptırması istenemez. Özerk bölgeler, kiraya verenin fianza'yı faizsiz olarak bölge idaresine ya da belirlenen kuruma yatırma zorunluluğu koyabilir; bu zorunluluk bölgeye göre değişir. Ek güvence sınırı ve çıkış belgesi 6 Ekim 2026 tarihli Real Decreto-ley 29/2026 ile geldi; kararname (Real Decreto-ley) olduğu için ileride değişebilir. Kira yasası 2026'da değişiyor; bu kart 7 Ekim 2026 tarihli konsolide metne göre (yayım 7 Ekim, yürürlük 8 Ekim). | G28: fianza, kira depozitosu, depozito iadesi, depósito de fianzas, alquiler, yasal faiz, LAU | H28: new;settled | I28: sevilla:kaynak:090 | J28: 46319 | K28: 9067 | L28: Hayır | M28: Taslak | N28: sevilla:ev | O28: Sözleşmeyi imzalarken bir aylık kira tutarında fianza ver; konut kiralamada bu zorunludur. Fianza dışında bir ek güvence kararlaştırılıyorsa sınırı bil: konutta 5 yıla kadar (kiraya veren tüzel kişiyse 7 yıla kadar) süreli sözleşmede en çok iki aylık kira, geçici kiralamalarda en çok bir aylık kira; kira ödememe sigortası ya da benzeri bir sigorta kapsamı yaptırman senden istenemez. İlk 5 yıl (kiraya veren tüzel kişiyse ilk 7 yıl) fianza'nın güncellenmediğini bil; sözleşme uzadığında kiraya veren artırılmasını, sen azaltılmasını isteyebilirsin, tutar konutta bir aylık güncel kiraya eşitlenene dek. Evden çıkarken evin durumunu iki tarafın imzaladığı yazılı bir belgeyle kaydet; belge imzalanmazsa ya da belgede kusur yazılmazsa, aksi ispatlanmadıkça ev uygun durumda teslim edilmiş sayılır. Anahtarları teslim et ve teslim tarihini not et; iade edilecek fianza bakiyesi anahtar tesliminden bir ay sonra hâlâ ödenmemişse bu tutar yasal faiz işler. Bölgende fianza'nın idareye yatırılması zorunluysa bu yükümlülük kiraya verene aittir; idare, sözleşmenin bitiminden bir ay sonra yatırılan tutarı iade etmezse tutar yasal faiz işler. | Q28: Kira yasası 2026'da değişiyor; bu kart 7 Ekim 2026 tarihli konsolide metne göre (yayım 7 Ekim, yürürlük 8 Ekim). Ek güvence sınırı (md. 36.5) ve çıkış belgesi (md. 36.7) 6 Ekim 2026 tarihli Real Decreto-ley 29/2026 ile geldi; kararname (Real Decreto-ley) olduğu için ileride değişebilir. Faiz, anahtar tesliminden bir ay sonra başlar. | R28: Konutta fianza: bir aylık kira. Ek güvence (tarafların anlaşmasıyla): 5 yıla kadar (kiraya veren tüzel kişiyse 7 yıla kadar) süreli konut sözleşmesinde en çok iki aylık kira, geçici kiralamalarda en çok bir aylık kira.
A29: sevilla:kira-artisi-siniri-irav | B29: sevilla | C29: kira-artisi-siniri-irav | D29: İspanya'da ev sahibi kirayı yılda en çok ne kadar artırabilir? | E29: Artış son yayımlanmış IRAV değişimini aşamaz; yalnız sözleşmede açıkça yazılıysa ve yıldönümünde yapılır; IRAV her ay yayımlanır | F29: Güncelleme yapılsa bile kira artışı, güncelleme tarihinde yayımlanmış son IRAV endeksinin yüzde değişimini aşamaz. Kira yalnızca sözleşmenin her yıldönümünde ve sözleşmede kararlaştırılan biçimde güncellenebilir; sözleşmede açık bir güncelleme anlaşması yoksa güncelleme uygulanmaz. IRAV'ı INE hesaplar; INE'ye göre 26 Mayıs 2023'ten sonra imzalanan sözleşmeler IRAV'a göre güncellenir, bu kart bu sözleşmeler içindir. INE sayfasında IRAV için son veri Eylül 2026'dır (14/10/2026'da yayımlandı) ve yıllık değişim %2,54'tür; bu değer her ay değişir. Konut piyasası gergin ilan edilen bölgelerde kira için ayrıca kurallar vardır; böyle bir ilanın olup olmadığı bölgeye göre değişir. Kira yasası 2026'da değişiyor; bu kart 7 Ekim 2026 tarihli konsolide metne göre (yayım 7 Ekim, yürürlük 8 Ekim). Md. 18.1, 6 Ekim 2026 tarihli Real Decreto-ley 29/2026 (art. 3.11) ile değiştirilmiştir; aynı maddeyi değiştiren daha önceki Real Decreto-ley 26/2026 (29 Eylül 2026) ise Meclisin kararnameyi yürürlükten kaldırmasıyla (2 Ekim 2026 tarihli Resolución) geçersiz kılındı. Kararnameyle yapılan değişikliğin kalıcılığı bu nedenle kesin değildir. | G29: kira artışı, IRAV, kira güncelleme, actualización de la renta, INE, zona tensionada, alquiler | H29: settled | I29: sevilla:kaynak:090;sevilla:kaynak:091 | J29: 46319 | K29: 9068 | L29: Hayır | M29: Taslak | N29: sevilla:ev | O29: Sözleşmende kira güncelleme maddesi olup olmadığına bak; açık bir anlaşma yoksa kira güncellenmez. Güncelleme maddesi var ama endeks ya da yöntem yazmıyorsa kira IRAV'ın yıllık değişimine göre güncellenir; her durumda artış IRAV'ın yüzde değişimini aşamaz. Referans ay olarak, güncelleme tarihinde yayımlanmış son endeksin ayı alınır; güncelleme sözleşmenin yıldönümünde yapılabilir. Güncellenen kira, ilgili tarafın karşı tarafa yazılı bildirmesinden sonraki aydan itibaren istenebilir; kiracı isterse bildirime INE'nin uygun belgesi eklenir. Bildirim, önceki ayın kira makbuzuna yazılan bir notla da geçerli biçimde yapılabilir. | Q29: IRAV değeri her ay değişir: INE sayfasında son veri Eylül 2026 (14/10/2026'da yayımlandı), yıllık değişim %2,54. Kira yasası 2026'da değişiyor; bu kart 7 Ekim 2026 tarihli konsolide metne göre (yayım 7 Ekim, yürürlük 8 Ekim). Md. 18.1, 6 Ekim 2026 tarihli Real Decreto-ley 29/2026 ile değiştirilmiştir; daha önceki Real Decreto-ley 26/2026'nın aynı maddeye ilişkin değişikliği Meclis kararıyla kaldırıldı, bu yüzden kararnameyle yapılan değişikliğin kalıcılığı kesin değildir. | S29: Konut piyasası gergin ilan edilen bölgelerde kira için ayrıca kurallar vardır; ilanın olup olmadığı bölgeye göre değişir.
A30: sevilla:kirada-onarim-ve-hasar-sorumlulugu | B30: sevilla | C30: kirada-onarim-ve-hasar-sorumlulugu | D30: İspanya'da kirada onarım masrafını kim öder? | E30: Yaşanabilirlik için gerekli onarımlar ev sahibine; olağan kullanımdan doğan küçük onarımlar konut kirasında kiracıya, geçici konutta ev sahibine aittir | F30: Evi yaşanabilir durumda tutmak için gereken onarımları ev sahibi yapar; konut kira sözleşmesinde bunun için kirayı artıramaz. Olağan kullanımdan doğan aşınmanın gerektirdiği küçük onarımlar konut kira sözleşmesinde kiracıya aittir; geçici konut sözleşmesinde ise bu küçük onarımlar da ev sahibine aittir (md. 21 bis). Bozulma İspanyol Medeni Kanunu'nun (Código Civil) 1563 ve 1564. maddelerine göre kiracıya yüklenebiliyorsa, o onarım ev sahibinin yükümlülüğü dışında kalır. Konut kira sözleşmesinde kiracı onarım gerektiğini en kısa sürede ev sahibine bildirir; yakın bir zarar ya da ağır bir rahatsızlık varsa ev sahibine haber vererek acil onarımı kendisi yaptırıp tutarını hemen ev sahibinden isteyebilir. Geçici konutta kiracı onarımı yine en kısa sürede bildirir; ev sahibi en çok 5 iş günü içinde yanıt vermek zorundadır, yanıt gelmezse kiracı gerekli onarımları yaptırıp tutarını hemen ev sahibinden isteyebilir; ödenmezse gerekçesini bildirdikten sonra tutarı ertesi ayın kirasından düşebilir. Geçici konut hükümleri 6 Ekim 2026 tarihli Real Decreto-ley 29/2026 ile geldi; kararname (Real Decreto-ley) olduğu için ileride değişebilir. Kira yasası 2026'da değişiyor; bu kart 7 Ekim 2026 tarihli konsolide metne göre (yayım 7 Ekim, yürürlük 8 Ekim). | G30: kira onarım, hasar sorumluluğu, conservación de la vivienda, pequeñas reparaciones, ev sahibi, kiracı, habitabilidad | H30: settled | I30: sevilla:kaynak:090 | J30: 46319 | K30: 9069 | L30: Hayır | M30: Taslak | N30: sevilla:ev | O30: Onarım gerektiğini fark ettiğinde en kısa sürede ev sahibine bildir. Konut kira sözleşmesinde ev sahibinin kendisinin ya da görevlendirdiği teknisyenlerin evin durumunu doğrudan görmesine izin ver. Konut kira sözleşmesinde yaşanabilirlik için gereken onarımı ev sahibinden bekle; bunun için kira artırılamaz. Konut kira sözleşmesinde olağan kullanımdan doğan aşınmanın gerektirdiği küçük onarımları kendin üstlen; geçici konut sözleşmesinde bunlar da ev sahibine aittir. Konut kira sözleşmesinde yakın bir zarar ya da ağır bir rahatsızlığı önlemek için acil onarım gerekiyorsa, ev sahibine önceden haber vererek onarımı yaptır ve tutarını hemen ev sahibinden iste. Geçici konutta ev sahibi 5 iş günü içinde yanıt vermezse gerekli onarımları yaptırabilir, tutarı hemen ev sahibinden isteyebilirsin; ödemezse gerekçeni bildirip ertesi ayın kirasından düşebilirsin. | Q30: Kira yasası 2026'da değişiyor; bu kart 7 Ekim 2026 tarihli konsolide metne göre (yayım 7 Ekim, yürürlük 8 Ekim). Geçici konut hükümleri (md. 21 bis) 6 Ekim 2026 tarihli Real Decreto-ley 29/2026 ile geldi; kararname (Real Decreto-ley) olduğu için ileride değişebilir. | S30: Bozulma kiracıya yüklenebiliyorsa (İspanyol Código Civil md. 1563 ve 1564) ev sahibi o onarımı yapmak zorunda değildir.
A31: sevilla:kiralik-evden-cikis-ve-ihbar-suresi | B31: sevilla | C31: kiralik-evden-cikis-ve-ihbar-suresi | D31: İspanya'da kiracı sözleşme bitmeden evden çıkabilir mi? | E31: Evet: konut kiracısı en az altı ay geçtikten sonra, kiraya verene en az 30 gün önceden bildirerek çıkabilir (geçici konutta: bir ay sonra, 10 gün önceden) | F31: Evet. Konut kiracısı, en az altı ay geçtikten sonra kiraya verene en az 30 gün önceden bildirmek koşuluyla kira sözleşmesinden çıkabilir (desistimiento; md. 11.1). Geçici konut sözleşmesinde çıkış, sözleşmenin yapılmasından en az bir ay sonra ve kiraya verene en az 10 gün önceden bildirmekle yapılır; bu hüküm 6 Ekim 2026 tarihli Real Decreto-ley 29/2026 ile geldi, kararname (Real Decreto-ley) olduğu için ileride değişebilir. Sözleşmenin ilk 5 yılında (kiraya veren tüzel kişiyse ilk 7 yılında) bir vade gününde ayrılmak istiyorsan, uzamayı durdurmak için vade gününden en az 30 gün önce yenilemek istemediğini bildirirsin (md. 9.1). Bugünkü metne göre (8 Ekim 2026'dan beri yürürlükte) 5 yıl (kiraya veren tüzel kişiyse 7 yıl) dolduktan sonraki vadelerde md. 10.1 geçerlidir: yenilememe isteğini kiracı en az 2 ay önceden bildirir; sonraki yıllık uzamaların bitişinde bu süre 1 aydır. 15 Kasım 2026'dan itibaren ise md. 10.1, 6 Ekim 2026 tarihli Real Decreto-ley 28/2026 ile yeni bir metne bağlanıyor ve bugünkü metnin yerine geçiyor: 5 yıl (tüzel kişi kiraya verende 7 yıl) sonrasında yenilememe bildirimini kiraya veren en az 6 ay, kiracı en az 2 ay önceden yapar; bildirim yapılmazsa sözleşme yıllık değil, 5'er (tüzel kişi kiraya verende 7'şer) yıllık sürelerle kendiliğinden uzar. Kiraya veren yenilememeyi geçerli biçimde bildirirse, kanunda sayılan istisnalar dışında kiracıya tazminat ödemek zorundadır. Bu değişikliklerin kalıcılığı kesin değildir: md. 10 ve md. 11 için daha önce çıkan 26/2026 ve 27/2026 sayılı kararnamelerin değişiklikleri, Meclisin bu kararnameleri yürürlükten kaldırması üzerine 2 Ekim 2026 tarihli Resolución'larla geçersiz kılındı. Kiraya veren, çıkıştan sonra iade etmesi gereken fianza bakiyesini anahtar tesliminden itibaren bir ay içinde iade etmezse bakiye yasal faiz işler. Kira yasası 2026'da değişiyor; bu kart 7 Ekim 2026 tarihli konsolide metne göre (yayım 7 Ekim, yürürlük 8 Ekim). | G31: evden çıkış, erken çıkış, desistimiento, ihbar süresi, kira feshi, alquiler, anahtar teslimi | H31: settled | I31: sevilla:kaynak:090 | J31: 46319 | K31: 9070 | L31: Hayır | M31: Taslak | N31: sevilla:ev | O31: En az altı ay geçtiğinden emin ol; konut kira sözleşmesinde çıkış hakkı bu süre geçtikten sonra kullanılır (geçici konutta bir ay). Kiraya verene çıkmak istediğini, çıkış tarihinden en az 30 gün önce bildir (geçici konutta en az 10 gün önce). Sözleşmenin ilk 5 yılında (kiraya veren tüzel kişiyse ilk 7 yılında) bir vade gününde ayrılıyorsan, vade gününden en az 30 gün önce yenilemek istemediğini kiraya verene bildir; 5 yıl (7 yıl) dolduktan sonraki vadelerde bu bildirim kiracı için en az 2 ay önce yapılır. 15 Kasım 2026'dan sonra bu vadelerde sözleşme yıllık değil 5'er (tüzel kişi kiraya verende 7'şer) yıllık sürelerle kendiliğinden uzar; kiracının bildirimi yine en az 2 ay önce yapılır. Anahtarları teslim ederken teslim tarihini not et; fianza bakiyesi bir ay içinde iade edilmezse yasal faiz işler. | Q31: Kira yasası 2026'da değişiyor; bu kart 7 Ekim 2026 tarihli konsolide metne göre (yayım 7 Ekim, yürürlük 8 Ekim). Geçici konutta çıkış hükümü (md. 11.2) 6 Ekim 2026 tarihli Real Decreto-ley 29/2026 ile geldi; kararname (Real Decreto-ley) olduğu için ileride değişebilir; aynı konudaki önceki kararname (Real Decreto-ley 26/2026) Meclis kararıyla kaldırılmıştır. Md. 10.1'in yeni metni 15 Kasım 2026'da yürürlüğe girer (Real Decreto-ley 28/2026). Konutta çıkış bildirimi en az 30 gün önce; çıkış hakkı en az altı ay geçtikten sonra.
A32: sevilla:kiralik-ilan-dolandiriciligini-tanima | B32: sevilla | C32: kiralik-ilan-dolandiriciligini-tanima | D32: Ev ararken sahte kiralık ilan dolandırıcılığını nasıl tanırsın? | E32: Çok düşük fiyat, kopya fotoğraf, evi gösteremeyen yurtdışındaki ev sahibi, aracıyla anahtar teslimi ve acele anonim ödeme isteği uyarı işaretidir | F32: INCIBE'ye göre sahte kiralık ilanların başlıca işaretleri şunlardır: bölgedeki benzer evlere göre çok düşük fiyat, başka siteden kopyalanmış ya da başka ilanlarda da görülen fotoğraflar, yurtdışında oturduğu için evi şahsen gösteremeyen ev sahibi, anahtar ya da sözleşme teslimi için aracı önerilmesi ve acele ettirilme. MoneyGram ya da Western Union gibi anonim para gönderme hizmetiyle ödeme istenirse ya da ev sahibi görünen kişinin uyruğuyla aynı ülkeden olmayan bir bankaya havale istenirse süreci sürdürme. | G32: kiralık ilan dolandırıcılığı, estafa alquiler, sahte ilan, INCIBE, MoneyGram, Western Union, ev arama | H32: planning;new | I32: sevilla:kaynak:092;sevilla:kaynak:090 | J32: 46319 | K32: 9071 | L32: Hayır | M32: Taslak | N32: sevilla:ev | O32: Çok düşük fiyatlı ilanda dikkatli ol; ilgilendiğin yerin fiyatını bölgedeki diğer kiralarla karşılaştır. Fotoğraflarda başka bir siteden alındığını gösteren filigran var mı ya da aynı fotoğraflar başka ilanlarda da çıkıyor mu diye bak. Yurtdışında oturduğu için evi şahsen gösteremeyen ev sahibine güvenme. Anahtar ya da sözleşme teslimi için aracı önerilirse güvenme; Airbnb gibi şirketlerin adı süreçle ilgisi olmadan kullanılabiliyor. Aracı şirket adına gelen e-posta Outlook ya da Gmail gibi ücretsiz bir alan adından geliyorsa bu da uyarı işaretidir. Aceleye getirilmeye karşı dikkatli ol; dolandırıcılar anlaşmayı bir an önce kapatmak ister. MoneyGram ya da Western Union gibi anonim para gönderme hizmetiyle ödeme istenirse süreci sürdürme; ev sahibi görünen kişinin uyruğuyla aynı ülkeden olmayan bir bankaya havale istenirse de sürdürme. İlanın adresini Google'da ara; sonuçlarda dolandırıcılıkla ilgili haber ya da başka kullanıcıların yorumları çıkabilir. | S32: Bilgi olarak: İspanyol kira yasasına (LAU md. 17.3) göre kira ödemesi elektronik araçlarla yapılır; taraflardan birinin banka hesabı ya da elektronik ödeme erişimi yoksa ve onun talebi üzerine nakit ödeme kiralanan evde mümkündür. Bu bir dolandırıcılık ölçütü değildir; bu kartın ölçütleri INCIBE'nin saydığı işaretlerdir. Yasal bilgi 7 Ekim 2026 tarihli konsolide metne göre (yayım 7 Ekim, yürürlük 8 Ekim).
A33: sevilla:endulus-kira-depozitosu-fianza-avra-yatirma-zorunlulugu | B33: sevilla | C33: endulus-kira-depozitosu-fianza-avra-yatirma-zorunlulugu | D33: Endülüs'te kira depozitosu (fianza) AVRA'ya yatırılır mı: 24 Ocak 2026 öncesi ve sonrası sözleşmeler | E33: 24 Ocak 2026 ve sonrasındaki yeni sözleşmelerde yatırma zorunluluğu kalktı; 23 Ocak 2026 dahil öncesindeki sözleşmelerde sürüyor | F33: Sözleşme tarihine bağlıdır. 24 Ocak 2026 dahil bu tarihten sonra yapılan kira sözleşmelerinde depozitoyu Endülüs yönetimine (AVRA) yatırma zorunluluğu kaldırılmıştır. 23 Ocak 2026 dahil bu tarihe kadar yapılan sözleşmelerde depozitoyu yatırma zorunluluğu sürer. Kaldırma, 16 Aralık 2025 tarihli Ley 5/2025 (Endülüs Konut Yasası) ek hüküm altıdan (Disposición Adicional Sexta) gelir. | G33: fianza, kira depozitosu, AVRA, Ley 5/2025, Endülüs konut yasası, depozito iadesi, kira sözleşmesi | H33: new;settled | I33: sevilla:kaynak:133 | J33: 46319 | K33: 9099 | L33: Hayır | M33: Taslak | N33: sevilla:ev | O33: Kira sözleşmesinin tarihine bak: sözleşme 24 Ocak 2026 ya da sonrasındaysa depozito için AVRA'ya yatırma yükümlülüğü yoktur. Sözleşme 23 Ocak 2026 dahil öncesine aitse depozitonun yatırılması zorunluluğu devam eder. Eski rejimde yatırılmış bir depozitoyu geri almak için, sözleşme sona erince AVRA'ya iade talebinde bulun. | Q33: Eski rejimde yatırılmış depozitonun iadesi için yönetim, iade talebinden itibaren bir ay içinde öder. | S33: İki rejim: (1) Sözleşme tarihi 24 Ocak 2026 ya da sonrası: AVRA'ya yatırma zorunluluğu yok. (2) Sözleşme tarihi 23 Ocak 2026 dahil öncesi: yatırma zorunluluğu sürer. Yasaya göre Endülüs yönetimi, eski mevzuata göre yasal olarak yatırılmış depozitoları, sözleşmeler sona erdikçe ve ilgililerin talebi üzerine iade eder.
A34: sevilla:sevilla-korumali-konut-kayit-defteri-nedir | B34: sevilla | C34: sevilla-korumali-konut-kayit-defteri-nedir | D34: Sevilla'da korumalı konut (vivienda protegida) için neden Registro de Demandantes'e yazılman gerekir? | E34: Satılık ya da kiralık tüm korumalı konutlar belediyenin talep sahipleri kaydı üzerinden dağıtılır; kayıt için gelir sınırı yıllık IPREM'in 7 katıdır | F34: Sevilla'da kamu ya da özel girişimle yapılan bütün korumalı konutlar (satılık da kiralık da) belediyenin Registro Público Municipal de Demandantes de Vivienda Protegida (korumalı konut talep sahipleri kaydı) üzerinden dağıtılır. Bu konutlardan birine sahip olmak için önce kayda yazılmış olmak gerekir. Kayıt, ilgilinin şartları sağladığını bildirdiği bir beyanla (declaración responsable) yapılır. Genel şartlar: reşit olmak, tam mülkiyette ya da ömür boyu kullanım hakkıyla bir konutun sahibi olmamak ve başvuranın ya da hanenin gelirinin IPREM'in 7 katını aşmaması. Sevilla belediyesinde nüfus kaydı (empadronamiento) olmak (son 2 yıl ya da daha önce toplam 5 yıl) veya son 3 yıl Sevilla'da çalışmak kayıt şartı değil, konut dağıtımında seçim ölçütüdür. | G34: vivienda protegida, korumalı konut, Registro de Demandantes, EMVISESA, sosyal konut, IPREM, Sevilla | H34: planning;new;settled | I34: sevilla:kaynak:145;sevilla:kaynak:144 | J34: 46319 | K34: 400 | L34: Evet | M34: Taslak | N34: sevilla:ev | O34: Reşit olduğunu ve tam mülkiyette ya da ömür boyu kullanım hakkıyla bir konutun sahibi olmadığını kontrol et. Gelirini hane olarak topla: başvuranın ya da hanenin yıllık geliri IPREM'in 7 katını aşmamalı. Kayıt başvurusunu yap; kayıt, şartları sağladığını bildiren bir beyanla işlenir. Kayıt tamamlanınca korumalı konut dağıtımlarına katılabilirsin; Sevilla'da 2 yıllık ya da toplam 5 yıllık nüfus kaydı (empadronamiento) veya 3 yıllık çalışma seçimde ölçüt olur. | S34: Sevilla'da nüfus kaydı (empadronamiento) ya da çalışma bağı kayıt için şart değildir; yalnızca konut seçiminde ölçüttür.
A35: sevilla:sevilla-konut-kayit-basvurusu-randevu-ve-form | B35: sevilla | C35: sevilla-konut-kayit-basvurusu-randevu-ve-form | D35: Sevilla'da korumalı konut kaydı için başvuru nasıl yapılır: randevu, form ve imzalar | E35: Randevu 010 hattından ya da belediye web platformundan alınır; form hanedeki 18 yaş üstü herkesçe imzalanır; başvuru için süre sınırı yok | F35: Birlikte yaşayan aile ya da grup tek başvuru yapar. Formu EMVISESA'nın sitesinden indirebilir ya da ilçelerdeki vatandaş hizmet noktalarından (Puntos de Atención al Ciudadano) alabilirsin. Başvuru için randevu şarttır: Sevilla'dan 010'u, şehir dışından 955 010 010'u ara; belediye web platformunda doğru seçenek 'Emvisesa ve Registro de Demandantes'. Formu hanedeki reşit herkes imzalar; başvuruyu başkası adına yapıyorsan imzalı yetki belgesi ve iki kişinin DNI fotokopisi gerekir. Kayıt aracı güncellenirken e-başvuru, belediye elektronik şubesinde 'presentación general' başlatıp doldurduğun formu ekleyerek de yapılıyor; EMVISESA'nın 'Konut talep et' sayfası ayrıca 'Oficina Virtual del Registro' çevrim içi yolunu gösteriyor. Başvuru için son tarih yok. | G35: Registro de Demandantes, kayıt başvurusu, cita previa, 010, EMVISESA, Punto de Atención al Ciudadano | H35: planning;new;settled | I35: sevilla:kaynak:147;sevilla:kaynak:148 | J35: 46319 | K35: 401 | L35: Hayır | M35: Taslak | N35: sevilla:ev | O35: Formu EMVISESA sitesinden indir ya da ilçendeki vatandaş hizmet noktasından al. Randevu al: Sevilla'dan 010'u, şehir dışından 955 010 010'u ara ya da belediye web platformunda 'Emvisesa ve Registro de Demandantes' seçeneğini kullan. Formu hanedeki reşit tüm üyelere imzalat; başkası adına başvuruyorsan imzalı yetki belgesi ve iki tarafın DNI fotokopisini hazırla. Formu randevuda teslim et ya da kayıt aracı güncellenirken geçerli olan yolla belediye elektronik şubesinde 'presentación general' başlatıp formu ekle. | P35: Doldurulmuş ve hanedeki reşit tüm üyelerce imzalanmış başvuru formu Başka biri adına başvuruda: imzalı yetki belgesi ve iki tarafın DNI fotokopisi | Q35: Başvuru için süre sınırı yok. | S35: Birden fazla kişi aynı hanedeyse tek başvuru yapılır. Başvuru sayfası yalnız imzalı formu istiyor; EMVISESA'nın 'Konut talep et' sayfası ise şartları gösteren belgelerin hazır olmasından söz ediyor. Ek belge gerekip gerekmediğini 010 ya da 955 476 180 üzerinden sorabilirsin.
A36: sevilla:korumali-konut-oncelik-gruplari-ve-kontenjanlar | B36: sevilla | C36: korumali-konut-oncelik-gruplari-ve-kontenjanlar | D36: Sevilla korumalı konutlarında kimler öncelikli: gençler, büyük aileler, tek ebeveynliler ve diğer gruplar | E36: Konutlar kontenjanlara göre dağıtılır; genel kontenjanda 40 yaş altına en az %60 ayrılır | F36: Konutlar sırayla şu kontenjanlara dağıtılır: engelli uyumlu konutlar, büyük aile kontenjanı, özel durum kontenjanı (en az %10), toplumsal cinsiyete dayalı şiddet (violencia de género) mağdurları (en az %10) ve genel kontenjan. Genel kontenjanda 40 yaşından küçükler en az %60 alır; sonra 65 yaş üstü, sonra 40-64 yaş arası gelir. Özel koruma gruplarına örnek: 40 yaşını doldurmamış gençler, 65 yaş ve üstü, büyük aileler, tek ebeveynli aileler, bakmakla yükümlü çocuğu olan haneler, engelliler, evsizler, ipotek ya da kira borcu yüzünden son 2 yılda evini kaybedenler. Sevilla bağı (Sevilla'da 2 yıllık nüfus kaydı, daha önce toplam 5 yıl nüfus kaydı ya da son 3 yıl Sevilla'da çalışma) seçimde öncelik sağlar ama kayıt şartı değildir; toplumsal cinsiyete dayalı şiddet ve terör mağdurları ile İspanya'ya dönen göçmenler (emigrante retornado, belgeyle) bu ölçütten muaftır. | G36: kontenjan, cupo, büyük aile, genç, tek ebeveyn, grupos de especial protección, Registro de Demandantes, vinculación | H36: planning;new;settled | I36: sevilla:kaynak:146;sevilla:kaynak:147 | J36: 46319 | K36: 402 | L36: Hayır | M36: Taslak | N36: sevilla:ev | O36: Hangi gruba girdiğini belirle: 40 yaş altı genç, 65 yaş üstü, büyük aile, tek ebeveynli aile gibi. Gençlik için yaş şartının hanenin gelirinin tamamını ya da çoğunu getiren kişi tarafından sağlanması gerektiğini bil. Sevilla'daki nüfus kaydı (empadronamiento) süreni ya da Sevilla'daki çalışma süreni formda 'bağ var' olarak işaretleyebileceğin ölçütlerle karşılaştır. Grubunu resmî belgeyle kanıtlaman gerekir (büyük aile, engellilik, mağdurluk vb.); belgeni elinin altında tut. | S36: Kayıt formu için ek belge istenmez; gruplar (büyük aile, engellilik, mağdurluk vb.) ise resmî belgeyle kanıtlanır.
A37: sevilla:korumali-konut-cekilis-gecerlilik-ve-vazgecme | B37: sevilla | C37: korumali-konut-cekilis-gecerlilik-ve-vazgecme | D37: Korumalı konut kaydı: çekiliş nasıl yapılır, kayıt ne kadar geçerli, konutu reddedersen ne olur? | E37: Kayıt son güncellemeden itibaren 3 yıl geçerli; değişiklikler 3 ay içinde bildirilir; kiralık konutu reddetmek kaydı düşürür | F37: Yeni bir konut grubu çıktığında yapımcı iki yoldan birini seçer: kayıtlı talep sahiplerinin sıralandığı çekiliş listesi ya da kamuya açık çağrı; başvuranlar konuttan fazlaysa çağrı noter ya da yetkili kamu görevlisi önünde çekilişle biter. Kayıt, sunulduğu ya da son güncellendiği tarihten itibaren 3 yıl geçerlidir. Durumunda (örneğin aile bileşiminde) değişiklik olursa değişikliği olaydan itibaren 3 ay içinde kayda bildirmelisin. Kiralık konutu reddedersen kaydın silinir; yeni başvuru yapmana bir engel ya da bekleme süresi yoktur. Satılık konutta gönüllü olarak iki kez vazgeçersen kaydın iptal edilir. Çekilişten sonra da kayıt olabilirsin; bir sonraki çekilişe kadar sıra, önceki katılımcıların arkasından numara sırasıyla verilir. EMVISESA'nın sayfasına göre son çekiliş 20 Aralık 2022'de yapıldı. | G37: sorteo, çekiliş, kayıt geçerlilik, renuncia, Registro de Demandantes, vivienda protegida, adjudicación | H37: planning;new;settled | I37: sevilla:kaynak:146 | J37: 46319 | K37: 403 | L37: Hayır | M37: Taslak | N37: sevilla:ev | O37: Kaydının geçerlilik tarihini takip et: kayıt, sunulduğu ya da son güncellendiği tarihten itibaren 3 yıl geçerli. Aile bileşimi, gelir gibi bilgilerin değişirse olaydan sonraki 3 ay içinde kayda bildir. Çekilişte ya da çağrıda seçilirsen Registro seni bilgilendirir; teklif edilen konutun kaydındaki özelliklere uyup uymadığına bak. Kiralık konutu reddedersen kaydın silinir; yeniden başvurabilirsin, bekleme süresi yok. | Q37: Kayıt 3 yıl geçerli; değişiklik bildirimi için süre olaydan itibaren 3 ay. | S37: En fazla üç belediyenin talep sahipleri kaydına yazılabilirsin; tercih ettiğin belediyeyi belirtirsin.
A38: sevilla:sevilla-kira-referans-fiyat-haritasi-ipra | B38: sevilla | C38: sevilla-kira-referans-fiyat-haritasi-ipra | D38: Sevilla'da mahalle mahalle kira fiyatına nereden bakarsın: IPRA kira referans haritası | E38: Belediye konut şirketi EMVISESA, şehrin 107 yerleşim mahallesi için interaktif kira referans endeksi yayınlıyor | F38: EMVISESA'nın IPRA (Índice de Precio de Referencia de Alquiler) uygulaması, Sevilla'nın 107 yerleşim mahallesinin kira referans endeksini interaktif haritada gösterir. Haritada mahalleni seçince iki kart açılır: birincisi mahalledeki konut turizmi baskısını ve geçmişini, ikincisi IPRA ve POA değerlerinin geçmiş grafiğini verir. IPRA, kiracının fiilen ödediği kiraya dayanır (veri olarak AVRA'ya yatırılması gereken depozito, fianza, esas alınır); POA ise ev sahiplerinin ilanda istediği kiradır. İki değer arasındaki farka bakarak ilanın mahalle ortalamasının altında mı üstünde mi olduğunu görebilirsin. Endeksin güncellemesi 25 Kasım 2022'de Sevilla Şehri Yönetim Kurulu kararıyla onaylandı. Endülüs'te fianzayı AVRA'ya yatırma zorunluluğu 24 Ocak 2026'dan itibaren yapılan sözleşmelerde kalktı. Rakamlar uygulamada mahalle seçilince görünür. | G38: IPRA, kira fiyatı, mahalle, EMVISESA, POA, kira endeksi, alquiler Sevilla | H38: before;planning;new | I38: sevilla:kaynak:150;sevilla:kaynak:133 | J38: 46319 | K38: 404 | L38: Hayır | M38: Taslak | N38: sevilla:ev | O38: EMVISESA'nın IPRA haritasını aç. Haritada ilgilendiğin mahalleyi bul ve üzerine tıkla. İlk kartta konut turizmi baskısına, ikinci kartta IPRA ve POA grafiğine bak. İlandaki kirayı mahallenin IPRA değeriyle karşılaştır. | S38: IPRA kiracıların gerçekten ödediği kirayı, POA ev sahiplerinin istediği kirayı gösterir; ikisini karıştırma.
A39: sevilla:bono-alquiler-joven-endulus-2026 | B39: sevilla | C39: bono-alquiler-joven-endulus-2026 | D39: Endülüs'te 35 yaş ve altına kira yardımı (Bono Alquiler Joven): kimlere verilir, 2026'da durum ne? | E39: Aylık en fazla 250 euro, en çok 24 ay; 2026 başvuruları 22 Haziran 2026'da 15.000 başvuruya ulaşılınca kapandı | F39: Bono Alquiler Joven, Endülüs Junta'sının gençlere verdiği kira yardımıdır: aylık en fazla 250 euro, en çok 24 tam ve ardışık ay için. Başvuran reşit ve en fazla 35 yaşında (35 dahil) olmalı; İspanyol, AB/AEA ülkesi ya da İsviçre vatandaşı olmalı, AB dışından olanlar İspanya'da düzenli kalış ya da ikamet durumunda olmalı. Yardım için kira sözleşmen (ya da sözleşme taahhüdün) ve düzenli bir gelirin olmalı; önceki vergi yılı gelirin tek kişi için IPREM'in 3 katını (14 maaşla 25.200 euro), birden fazla kişilik hane için 4 katını (33.600 euro) aşmamalı. Başvuran ya da konutta oturan hane üyelerinden hiçbiri İspanya'da bir konutun maliki ya da intifa hakkı sahibi olmamalı (istisnalar var). Kiraladığın konut asıl ve sürekli ikametgâhın olmalı; nüfus kaydın (padrón) yardım döneminin başından itibaren geçerli olmalı. Junta'nın sayfasına göre 2026 başvuru dönemi 13 Ocak 2026'da yeniden açıldı ve 22 Haziran 2026'da 15.000 başvuruya ulaşılınca kapandı. | G39: Bono Alquiler Joven, kira yardımı, genç, 35 yaş, Junta de Andalucía, 250 euro, IPREM | H39: planning;new;settled | I39: sevilla:kaynak:154 | J39: 46319 | K39: 405 | L39: Hayır | M39: Taslak | N39: sevilla:ev | O39: Yaşını kontrol et: başvuru anında en fazla 35 yaşında olmalısın (35 dahil). Uyrukluk ve oturum durumunu kontrol et: AB dışındansan İspanya'da düzenli kalış ya da ikamet gerekir. Geliri hesapla: önceki vergi yılı için tek kişide IPREM'in 3 katı, birden fazla kişilik hanede 4 katı üst sınırdır. Konut maliki ya da intifa hakkı sahibi olmadığını (hane üyeleri dahil) ve nüfus kaydının yardım döneminin başından itibaren kiralık adreste geçerli olduğunu kontrol et. Kira sözleşmenin (ya da sözleşme taahhüdünün) ve düzenli gelir belgelerinin hazır olduğundan emin ol; 2026 başvuru dönemi 22 Haziran 2026'da kapandı, başvuru yalnız Junta'nın elektronik ofisi (VEAJA) üzerinden yapılıyordu. | P39: Kira sözleşmesi ya da sözleşme taahhüdü Düzenli gelir belgeleri Kişisel dijital sertifika ve Autofirma uygulaması (elektronik başvuru için) | Q39: 2026 başvuru dönemi 13 Ocak 2026'da açıldı, 22 Haziran 2026'da kapandı. | R39: Yardım: aylık en fazla 250 euro, en çok 24 ay. | S39: Yardım kiracının asıl ve sürekli konutu için verilir (nüfus kaydı yardım döneminin başından itibaren geçerli olmalı); kiraya verenle birinci ya da ikinci derece akrabalık varsa yardım verilmez.
A40: sevilla:bono-alquiler-joven-kira-tavani-sozlesme-turleri | B40: sevilla | C40: bono-alquiler-joven-kira-tavani-sozlesme-turleri | D40: Bono Alquiler Joven: kira üst sınırı, sözleşme türleri ve kira ödemesini kanıtlama | E40: Konutta aylık 900 ya da 600 euro, odada 380 ya da 300 euro kira sınırı; başvuru yalnızca elektronik | F40: 2026 başvuru dönemi 22 Haziran 2026'da kapandı. Yardım için kira tutarının bir üst sınırı var. Konut sözleşmelerinde (tür 1, 2, 3) sınır, Plan Vive Ek V'teki 1, 2 ve 3. grup belediyelerde aylık 900 euro, diğer Endülüs belediyelerinde 600 euro'dur. Birbiriyle aile olmayan kişilerin ortak kiraladığı sözleşmelerde (tür 4) konut sınırına ek olarak kişi başı 380 ya da 300 euro, oda kirasında (tür 5) 380 ya da 300 euro uygulanır. Garaj, depo ya da ortak gider sözleşmede ayrı yazılmamışsa kiradan yüzde 5 ile 15 arasında kesinti yapılır. Başvuru yalnızca elektronik yapılır; FNMT'nin verdiği kişisel dijital sertifika ve Autofirma gerekir. Yardım aldığın süre boyunca kira ödemesini makbuz ya da banka dekontuyla kanıtlarsın; şartları etkileyen bir değişikliği 15 gün içinde bildirirsin. | G40: Bono Alquiler Joven, kira tavanı, oda kirası, Autofirma, VEAJA, Plan Vive, habitación | H40: planning;new;settled | I40: sevilla:kaynak:154 | J40: 46319 | K40: 406 | L40: Hayır | M40: Taslak | N40: sevilla:ev | O40: Sözleşme türünü belirle: tek kiracılı konut, aile olarak birlikte kiralanan konut, aile olmayan kişilerle ortak sözleşme ya da yalnızca oda kirası. Kirayı sınırla karşılaştır: konutta 900 ya da 600 euro, kişi başı payda ve odada 380 ya da 300 euro. Garaj, depo ya da ortak gider sözleşmede ayrı yazılı değilse kiradan yüzde 5, 10 ya da 15 düşüleceğini hesaba kat. Dijital sertifikanı ve Autofirma uygulamasını hazırla; başvuru Junta'nın elektronik ofisi (VEAJA) üzerinden yapılır, 2026 dönemi 22 Haziran 2026'da kapandı. Kira ödemelerini makbuz, dekont ya da banka kaydıyla belgele. | P40: FNMT kişisel dijital sertifikası Autofirma uygulaması Kira ödeme makbuzu ya da banka dekontu | Q40: Şartları etkileyen değişiklik 15 gün içinde bildirilir. | R40: Kira sınırı: konutta 900 euro (1-3. grup belediyeler) ya da 600 euro (diğerleri), aylık; oda ve kişi başı pay 380 ya da 300 euro. | S40: Sınırın hangi gruba göre uygulanacağı, belediyenin Plan Vive Ek V'teki grubuna bağlıdır.
A41: sevilla:emvisesa-ppr-2026-kira-yardimi | B41: sevilla | C41: emvisesa-ppr-2026-kira-yardimi | D41: EMVISESA kiracısıysan: düşük gelirli aileler için PPR kira yardımı (2026) şartları ve evrakı | E41: Yalnızca EMVISESA konutlarının kiracıları; sosyal hizmetler kullanıcısı olmak şart; 2026 başvuru süresi 15 Eylül 2026'da doldu | F41: PPR (Protocolo de Protección a Familias con Pocos Recursos), EMVISESA'nın ya da EMVISESA'nın yönettiği konutların kiracısı ve yasal kullanıcısı olan, risk altındaki ya da dışlanmış ailelere verilen kira yardımıdır; Sevilla Belediyesi Sosyal Refah ve İstihdam Delegasyonu bütçesinden karşılanır. Şartlar: konutta yasal olarak asıl ve sürekli ikamet etmek, su, elektrik ya da gaz aboneliklerinin yasal olması, tüm hane üyelerinin o adreste nüfus kaydının olması, apartman aidatlarını ödemiş olmak, EMVISESA'nın Protocolo de Convivencia dosyalarında konutu kullanmama ya da çok ağır ihlal nedeniyle yaptırım almamış olmak, önceki yıllarda PPR başvurusu yaptıysan asgari kirayı (renta mínima exigible) ödemiş olmak ve Belediye Sosyal Hizmetleri'nin kullanıcısı olmak. Şartları Konut Hakkı Belediye Ofisi (OMDV) kontrol eder. 2026 için başvuru süresi 15 Eylül 2026'da sona erdi. Başvuru, OMDV'de randevuyla yüz yüze yapılır. | G41: PPR, EMVISESA kiracı, kira yardımı, OMDV, düşük gelir, ayudas al alquiler, Servicios Sociales | H41: settled | I41: sevilla:kaynak:149 | J41: 46319 | K41: 407 | L41: Hayır | M41: Taslak | N41: sevilla:ev | O41: Şartları kontrol et: konutta asıl ikametgâh, yasal abonelikler, hanenin tamamı o adreste nüfus kayıtlı, aidat borcu yok, EMVISESA yaptırımı yok, önceki yıllarda PPR aldıysan asgari kira ödenmiş, Belediye Sosyal Hizmetleri kullanıcısı olmak. OMDV'den randevu al: 955 476 054, 955 476 004 ya da 955 476 050. Başvuru formunu ve ekleri (yetki, Anexo 0, I, III, V) kira sözleşmesinin tüm sahiplerine imzalat. Evrakı Avenida de San Jerónimo 5'teki OMDV ofisine eksiksiz teslim et; damgalı kopyanı al. | P41: PPR başvuru formu ve Anexo 0, I, III, V ekleri Son üç ışık ve su faturası Aidatın ödendiğini gösteren yönetici ya da apartman başkanı belgesi (aidat tutarı yazılı) 14 yaşını geçen hane üyelerinin DNI fotokopisi; AB vatandaşları için AB kayıt belgesi ve pasaport ya da kimlik, AB dışı için geçerli yabancı kimlik kartı fotokopisi Aile cüzdanı fotokopisi, toplu ikametgâh belgesi, 16 yaş üstü herkesin gelir belgesi ve iş geçmişi dökümü Sosyal Güvenlik entegre yardım belgesi (Ingreso Mínimo Vital alıp almadığını gösterir) Varsa: boşanma sözleşmesi ya da kararı, SEPE veya Sosyal Güvenlik'ten başka yardım için başvuru belgesi, bağımlılık ya da engellilik kararı, ödenmeyen nafaka için şikâyet ya da dava belgesi | Q41: 2026 başvuru süresi 15 Eylül 2026'da sona erdi. | S41: Eksik evrak ya da hatalı doldurulmuş form başvuruyu geçersiz kılar.
A42: sevilla:sevilla-konut-isleri-adresler-emvisesa-registro-omdv | B42: sevilla | C42: sevilla-konut-isleri-adresler-emvisesa-registro-omdv | D42: Sevilla'da konut işleri için adresler ve telefonlar: EMVISESA merkezi, Registro ofisi ve Konut Hakkı Ofisi (OMDV) | E42: Registro ofisi ve OMDV aynı adreste, Avda. San Jerónimo 5'te; EMVISESA merkezi Parque Empresarial Arte Sacro'da | F42: Korumalı konut kaydı (Registro) ofisi Avda. San Jerónimo 5, ACC. B, 41015 Sevilla adresindedir; hafta içi 8:30-14:30 arası çalışır, cumartesi kapalıdır. Randevu için 010'u (şehir dışından 955 010 010) ya da danışma hattı 955 476 180'i ara; 3 ve 10 numaralı otobüslerin durakları ofisin yakınındadır. Konut Hakkı Belediye Ofisi (OMDV) de Avenida de San Jerónimo 5'tedir; EMVISESA kiracılarının PPR kira yardımı başvurusu için randevu telefonları 955 476 054, 955 476 004 ve 955 476 050. EMVISESA'nın merkezi Avenida de la Ingeniería 9, Parque Empresarial Arte Sacro, Edificio 9, 41015 Sevilla adresindedir; telefon 955 476 000, yalnızca randevuyla hizmet verir, hafta içi 8:30-14:30 arası açıktır, salı günleri ayrıca 16:00-18:30 arası randevuyla çalışır. | G42: EMVISESA adres, Registro de Demandantes ofisi, OMDV, San Jerónimo 5, Arte Sacro, 010, konut ofisi | H42: planning;new;settled | I42: sevilla:kaynak:145;sevilla:kaynak:149 | J42: 46319 | K42: 408 | L42: Evet | M42: Taslak | N42: sevilla:ev | O42: Registro işi için 010'u (şehir dışından 955 010 010) ya da 955 476 180'i arayıp randevu al. EMVISESA kiracısıysan PPR kira yardımı başvurusu için Konut Hakkı Ofisi'nden (OMDV) 955 476 054, 955 476 004 ya da 955 476 050 numaralarından randevu al. Randevu günü Avda. San Jerónimo 5'e git; 3 ya da 10 numaralı otobüs yakında durur. EMVISESA merkezindeki bir iş için 955 476 000'den randevu al. | Q42: Registro ofisi: hafta içi 8:30-14:30, cumartesi kapalı. EMVISESA merkezi: hafta içi 8:30-14:30, salı 16:00-18:30 randevuyla. | S42: OMDV ve Registro ofisi aynı adreste olsa da randevu telefonları farklıdır.
A43: sevilla:endulus-kiraci-haklari-satis-ev-giris-faturalar | B43: sevilla | C43: endulus-kiraci-haklari-satis-ev-giris-faturalar | D43: Endülüs'te kiracı olarak haklarını bil: ev satılırsa, ev sahibi eve girmek isterse, vergi ve faturalar kimde? | E43: Junta de Andalucía'nın kiracı ve ev sahibi hak-yükümlülük listesinden Sevilla'da işine yarayanlar | F43: Ev satılırsa kiracı olarak önalım (tanteo) hakkın var: ev sahibi satma kararını sana yazılı bildirmeli. Evi alan kişi mevcut kira sözleşmesine uymak zorundadır. Evi ancak kısmen ve ev sahibinin önceden yazılı iznine bağlı olarak alt kiraya verebilirsin; tadilat da ev sahibinin açık ve yazılı rızasıyla yapılır. Anahtar tesliminden sonra ev sahibi, sen izin vermedikçe ya da mahkeme izni olmadıkça eve giremez. Ev sahibinin enerji verimliliği sertifikası olması gerekir. Küçük, olağan kullanımdan doğan onarımlar kiracıya düşer. Sayaçlı faturalar (elektrik, su, gaz, telefon) kiracıya aittir; IBI (emlak vergisi) ve çöp harcı ise ev sahibine düşer; kiracı yalnızca sözleşmede kararlaştırılan yük ve vergileri öder. Aksi kararlaştırılmadıkça kira ayın ilk yedi günü içinde ödenir. | G43: kiracı hakları, derechos inquilino, tanteo, subarriendo, IBI, çöp harcı, Junta de Andalucía | H43: new;settled | I43: sevilla:kaynak:153 | J43: 46319 | K43: 409 | L43: Hayır | M43: Taslak | N43: sevilla:ev | O43: Sözleşmeyi oku: kira günü, hangi giderlerin kime ait olduğu ve alt kiralama ya da tadilat izni yazılı mı bak. Ev satış kararı alınırsa ev sahibinden yazılı bildirim iste ve önalım hakkını kullanıp kullanmayacağına karar ver. Tadilat ya da alt kiralama yapacaksan ev sahibinden önceden yazılı izin al. Sayaçlı hizmetlerin (elektrik, su, gaz, telefon) faturalarını kendi adına öde. IBI ve çöp harcı ev sahibine düşer; sözleşmede bunları sana yükleyen bir madde var mı, imzalamadan önce bak. | Q43: Kira, aksi kararlaştırılmadıkça ayın ilk 7 günü içinde ödenir.
A44: sevilla:kira-ve-konut-hizmeti-sikayeti-hoja-de-reclamaciones-012 | B44: sevilla | C44: kira-ve-konut-hizmeti-sikayeti-hoja-de-reclamaciones-012 | D44: Endülüs'te işletmelerden şikâyet formu (hoja de reclamaciones) nasıl istenir? Kira hakları için 012 hattı | E44: Şikâyet formu ücretsiz ve hemen verilir; dijital sertifikanla tamamen internetten, yoksa yazdırıp Junta kayıt servisine verilir | F44: Mal satan ya da hizmet veren işletme ve profesyoneller, şikâyet formu (hoja de quejas y reclamaciones) bulundurmak zorundadır. İstediğinde form hemen ve ücretsiz verilir; vermezse yetkili tüketici otoritesinin görevlilerinden yardım isteyebilirsin. Şikâyet (queja) yalnızca memnuniyetsizliği bildirir; talep (reclamación) ise iade, onarım ya da tazminat ister. Dijital sertifikan varsa süreç tamamen internetten yürür; yoksa formu yazdırıp doldurur ve Junta de Andalucía'nın herhangi bir biriminin kayıt (registro) servisine verirsin. Bu form, bir işletmeden mal ya da hizmet aldığında kullanılır. Ev sahibiyle kira sözleşmesinden doğan hak ve yükümlülükler hakkında bilgi için 012 ya da 955 012 012'yi arayabilirsin; Junta bu ayrıntıları Consumo Responde sitesinde de yayınlıyor. | G44: hoja de reclamaciones, şikâyet formu, Consumo Responde, 012, tüketici şikâyeti, kira hakları, Junta de Andalucía | H44: new;settled | I44: sevilla:kaynak:155;sevilla:kaynak:153 | J44: 46319 | K44: 410 | L44: Hayır | M44: Taslak | N44: sevilla:ev | O44: İşletmeden ya da hizmet verenden şikâyet formunu (hoja de reclamaciones) iste; hemen ve ücretsiz vermek zorunda. Form verilmezse yetkili tüketici otoritesinin görevlilerinden yardım iste. Formu açık ve kısa doldur; ne talep ettiğini (iade, onarım ya da tazminat) yaz. Dijital sertifikan varsa şikâyeti internetten ilet; yoksa yazdırıp Junta'nın bir biriminin kayıt servisine ver. Kira hak ve yükümlülükleri hakkında bilgi için 012 ya da 955 012 012'yi ara. | P44: Doldurulmuş şikâyet formu (hoja de reclamaciones) | R44: Form ücretsizdir.
A45: sevilla:avra-eski-fianza-iade-basvurusu-model-810 | B45: sevilla | C45: avra-eski-fianza-iade-basvurusu-model-810 | D45: Eski kira depozitosunu (fianza) AVRA'dan geri almak: Model 810 formu, belgeler ve bir aylık süre | E45: 23 Ocak 2026'ya kadar yapılan sözleşmelerde yatırılan fianza, başvuruyu yapan kiraya verene bir ay içinde iade edilir | F45: Endülüs'te 23 Ocak 2026'ya (dahil) kadar yapılan kira sözleşmelerinde depozito (fianza) AVRA'ya (Endülüs Konut ve Yenileme Ajansı) yatırılıyordu. Bu depozitonun iadesini sözleşme sona erdikçe, kiraya veren (ya da yasal temsilcisi) 810 numaralı formla ister; başvuru randevuyla yüz yüze ya da elektronik yapılabilir. Formla birlikte taşınmazın katastro referansı gerekir; iade için ayrıca banka hesabının GIRO sistemine kayıtlı olması zorunludur. Dijital sertifikası olan kişi hesabı Oficina Virtual'dan kaydedebilir; olmayan kişi üçüncü kişi hesap bakım formunu doldurur. AVRA, talepten itibaren bir ay içinde depozitoyu iade eder. 24 Ocak 2026'dan itibaren yapılan sözleşmelerde AVRA'ya yatırma zorunluluğu kalkmıştır. | G45: fianza, AVRA, Model 810, depozito iadesi, GIRO, katastro referansı, kiraya veren | H45: settled | I45: sevilla:kaynak:152;sevilla:kaynak:133 | J45: 46319 | K45: 411 | L45: Hayır | M45: Taslak | N45: sevilla:ev | O45: Sözleşmenin 23 Ocak 2026 ya da öncesinde yapılıp yapılmadığına bak; 24 Ocak 2026'dan itibaren yapılan sözleşmelerde fianzayı AVRA'ya yatırma zorunluluğu kalktı. Kiraya verenden 810 numaralı iade formunu doldurmasını iste: dijital sertifikayla internetten ya da AVRA'dan randevu alıp kâğıt üzerinde. Katastro referansını forma ekle ve kiraya verenin banka hesabının GIRO sisteminde kayıtlı olduğundan emin ol. Başvuruyu ilet; AVRA depozitoyu başvurudan itibaren bir ay içinde iade eder. | P45: Model 810 iade formu Taşınmazın katastro referansı GIRO sisteminde kayıtlı banka hesabı | Q45: AVRA iadeyi talepten itibaren bir ay içinde yapar. | S45: İadeyi kiraya veren ister; kiracı olarak ev sahibine sözleşmenin AVRA kapsamında olup olmadığını sorabilirsin.
A46: sevilla:elektrik-aboneligi-serbest-piyasa-pvpc | B46: sevilla | C46: elektrik-aboneligi-serbest-piyasa-pvpc | D46: Elektrik aboneliği nasıl yapılır; serbest piyasa ile PVPC arasındaki fark nedir? | E46: Serbest piyasa herkese açık; regüle fiyat PVPC yalnız 10 kW ve altı gerçek kişi ve mikro işletmelere | F46: Elektrik için iki yol var: serbest piyasada fiyat ve koşulları tedarikçiyle serbestçe kararlaştırırsın; regüle piyasada ise yalnız PVPC (küçük tüketici gönüllü fiyatı) sözleşmesi yaparsın. Serbest piyasa herkese açıktır; PVPC'ye yalnız sözleşmeli gücü 10 kW ve altı olan gerçek kişiler ile mikro işletmeler girebilir ve PVPC yalnız "comercializadora de referencia" (referans tedarikçi) ile yapılır. PVPC'de güç ve enerji için ayrı fiyatlar vardır; enerji fiyatı günün saatine göre değişir. Elektrik almak için hem şebeke erişim sözleşmesi (ATR) hem enerji sözleşmesi gerekir; çoğu kişi ikisini de tedarikçi üzerinden yapar. | G46: elektrik aboneliği, PVPC, serbest piyasa, mercado libre, comercializadora, CUPS, contrato de luz | H46: new | I46: sevilla:kaynak:067;sevilla:kaynak:068 | J46: 46319 | K46: 9050 | L46: Hayır | M46: Taslak | N46: sevilla:fatura | O46: Serbest piyasa mı PVPC mi istediğine karar ver; sözleşmeli gücün 10 kW'ın üzerindeyse ya da gerçek kişi veya mikro işletme değilsen PVPC'ye giremezsin. Aboneliği kendi adına yap: kiracıysan da elektrik noktasının abonesi (sözleşme sahibi) sen olmalısın; evin sahibi kim olursa olsun fark etmez. Seçtiğin tedarikçiye CUPS kodunu, sözleşme sahibinin adını ve DNI'sini (kimlik numarası), yeni abonelik adresini, Certificado de Instalación ya da Boletín Eléctrico'yu, istediğin gücü ve faturaların çekileceği hesabın IBAN kodunu ver. Elektrik noktası yeniyse bunlara ek olarak ilk iskân ya da işyeri açma ruhsatını, oturulabilirlik belgesini ve mülkiyet senedi ya da kira sözleşmesini ver. Sözleşmeyi imzalamadan önce tedarikçinin sözleşmeden ayrı gönderdiği özet belgeyi oku; ana koşullar orada sade dille yazılıdır. | P46: CUPS kodu (her elektrik faturasında yazar) Sözleşme sahibinin adı ve DNI (kimlik numarası) Yeni abonelik adresi Certificado de Instalación ya da Boletín Eléctrico Başlatmak istediğin güç Faturaların çekileceği hesabın IBAN kodu Elektrik noktası yeniyse: licencia de primera ocupación ya da licencia de apertura Elektrik noktası yeniyse: cédula de habitabilidad ya da cédula de calificación definitiva Elektrik noktası yeniyse: mülkiyet senedi ya da kira sözleşmesi | Q46: CNMC'ye göre elektriğin açılması için yasal azami süre 5 ile 7 iş günüdür; bu süre tedarikçiden bağımsızdır. | S46: Sözleşme genelde bir yıllıktır ve aynı sürelerle kendiliğinden uzar. CNMC'ye göre sözleşmede taahhüt (permanencia) şartı varsa tedarikçi, bir yıl dolmadan feshe ceza uygulayabilir; bu ceza düşük gerilimde sözleşmenin kalan enerji maliyetinin %5'ini aşamaz. PVPC'yi seçersen enerjin için başka bir sözleşme biçimine başvuramazsın ve birden fazla tedarikçiyle çalışamazsın. PVPC ile serbest piyasa arasındaki geçişin kendisi, sözleşmenin teknik koşulları aynı kaldıkça ek ücret doğurmaz.
A47: sevilla:elektrik-faturasi-nasil-okunur | B47: sevilla | C47: elektrik-faturasi-nasil-okunur | D47: Elektrik faturası nasıl okunur: potencia, enerji ve vergiler neyi gösterir? | E47: Sabit güç bedeli, tüketime bağlı enerji bedeli, şebeke giderleri ve vergiler faturada ayrı kalemlerdir | F47: Elektrik faturası enerji maliyetinden, düzenlenmiş giderlerden (şebeke, yenilenebilir enerji teşviki gibi), tedarikçinin marjından ve vergilerden (elektrik özel vergisi ile IVA) oluşur; sayaç kirası ve ek hizmetler varsa ayrıca eklenir. Tedarikçiler bu maliyetleri genelde iki terimle yansıtır: sabit güç terimi (sözleşmeli güce bağlıdır, hiç elektrik tüketmesen de ödenir) ve değişken enerji terimi (ne kadar ve hangi saatte tükettiğine bağlıdır; serbest piyasada tedarikçiyle sabit fiyat formülü sözleşmediysen). Düzenlenmiş maliyetler şebeke erişim bedelleri (peajes) ve cargos yoluyla yansıtılır; ikisi faturada ayrı gösterilmek zorundadır. PVPC'de vergiler PVPC fiyatının içinde değil, üstüne eklenir. | G47: elektrik faturası, factura de la luz, potencia, término de energía, peajes, cargos, IVA, Entiende tu factura | H47: new;settled | I47: sevilla:kaynak:068;sevilla:kaynak:069 | J47: 46319 | K47: 9051 | L47: Hayır | M47: Taslak | N47: sevilla:fatura | O47: Faturada sözleşme sahibini, sözleşme ve fatura numarasını, CUPS kodunu ve fatura dönemini kontrol et; CNMC'ye göre bunlar faturada yazılı olmak zorundadır. Potencia (güç) satırına bak: bu tutar sözleşmeli güce bağlıdır ve hiç elektrik tüketmesen de ödenir. Enerji satırına bak: serbest piyasada tedarikçiyle sabit fiyat formülü sözleşmediysen tutar ne kadar ve hangi saatte tükettiğine bağlıdır. Peajes ve cargos kalemlerinin ayrı satırda gösterildiğini kontrol et; vergileri (elektrik özel vergisi ve IVA) de faturada bul. PVPC'deysen vergiler PVPC fiyatının üstüne uygulanır. Sayaç kirası ve bakım ya da sigorta gibi ek hizmetleri ayrı satırda ara; ek hizmetlerin bedeli faturada ayrı yazılmak zorundadır. Anlamadığın bir kalem olursa CNMC'nin "Entiende tu factura" aracını kullan; tedarikçin kim olursa olsun faturanı anlamana yardım eder. | S47: PVPC'deki, bono social'deki ve geçici olarak serbest piyasa sözleşmesi olmayan tüketicilerin faturalarının biçimi ve içeriği düzenlenmiştir. Diğer tüketicilerde tedarikçi fatura tasarımını serbestçe belirler, ama sayılan kalemleri içermek zorundadır.
A48: sevilla:sozlesmeli-elektrik-gucu-nasil-secilir | B48: sevilla | C48: sozlesmeli-elektrik-gucu-nasil-secilir | D48: Sözleşmeli elektrik gücü (potencia contratada) nasıl seçilir ve değiştirilir? | E48: Güç bedeli tüketmesen de ödenir; gücü ihtiyacına göre tut, değişikliği tedarikçi üzerinden iste | F48: Sözleşmeli gücü (potencia contratada) fiilen ihtiyacın kadar tut: güç terimi sabittir ve hiç elektrik tüketmesen de ödenir. Aynı anda çalışan cihazları azaltmak daha düşük bir güç seçmene imkân verir. Gücü tedarikçi üzerinden değiştirirsin; 12 ayda en az bir kez güç değişikliği yapma hakkın vardır. Güç artırımı ücretli olabilir; diğer sözleşme değişiklikleri genelde ücretsizdir. | G48: potencia contratada, elektrik gücü, kW, güç artırma, güç azaltma, comercializadora, contador | H48: new;settled | I48: sevilla:kaynak:068;sevilla:kaynak:067 | J48: 46319 | K48: 9052 | L48: Hayır | M48: Taslak | N48: sevilla:fatura | O48: Dağıtım şirketinin internet sitesinden maksimum güç ve tüketim verilerine bak; dağıtım şirketini seçemezsin, CNMC bütün dağıtım şirketlerinin tüketici portalı sitelerini yayımlar. Aynı anda çalıştırdığın cihazları gözden geçir; birlikte kullanımı azaltırsan daha düşük bir güç yeter. Güç değişikliği talebini tedarikçine ilet; tedarikçi dağıtım şirketiyle gereken işlemleri senin adına yapar. Gücü seçerken şunu hesaba kat: güç değişikliği hakkın 12 ayda en az bir kez tanınır. | Q48: 12 ayda en az bir kez güç değişikliği yapma hakkın vardır. | R48: Sözleşme değişiklikleri genelde ücretsizdir; güç artırımı ücretli olabilir. | S48: Sözleşmeli gücü 15 kW'ın altında olan ve saatlik ayrım ile uzaktan okuma yapabilen sayaca sahip tüketici gücü 0,1 kW'ın katları olarak seçebilir.
A49: sevilla:dogalgaz-aboneligi-tur-ve-fatura | B49: sevilla | C49: dogalgaz-aboneligi-tur-ve-fatura | D49: Doğalgaz aboneliği nasıl yapılır; TUR (regüle tarife) ile serbest piyasa arasındaki fark ve fatura kalemleri nelerdir? | E49: Yılda 50.000 kWh'a kadar tüketenler regüle TUR tarifesine girebilir; tedarikçi değişimi ücretsizdir | F49: Doğalgazda iki yol var: serbest piyasada fiyatı tedarikçiyle serbestçe kararlaştırırsın; TUR'da (tarifa de último recurso) ise fiyatı idare belirler ve fiyat üç ayda bir belirlenir. CNMC'nin güncel rehberine göre TUR'a yıllık tüketimi 50.000 kWh'a kadar olanlar (en çok 4 bar basınçta) girebilir ve TUR yalnız son çare tedarikçileriyle (comercializador de último recurso) yapılır. Sözleşme için konutuna atanmış CUPS kodu gerekir. Gazı henüz açılmamış konutta tedarikçi sözleşmesinden sonra aboneliği dağıtım şirketi açar. Tedarikçi değiştirmek ücretsizdir ve en geç 3 hafta içinde yapılır. | G49: doğalgaz, gas natural, TUR, tarifa de último recurso, mercado libre, CUPS, factura del gas | H49: new;settled | I49: sevilla:kaynak:070 | J49: 46319 | K49: 9053 | L49: Hayır | M49: Taslak | N49: sevilla:fatura | O49: Yıllık tüketimini kWh olarak belirle; TUR kademesini yıllık tüketim belirler: TUR.1 yılda 5.000 kWh'ın altı (örneğin gaz ocağı ve/veya şofben olan konut), TUR.2 5.000 ile 15.000 kWh arası (örneğin doğalgaz kaloriferli konut), TUR.3 15.000 ile 50.000 kWh arası (örneğin kalorifer ve yüksek tüketimli konut ya da soğuk bölge). Serbest piyasa ile TUR'u karşılaştır; TUR'u yalnız son çare tedarikçilerinden biriyle yapabilirsin ve koşulları hepsinde aynıdır. Gazı henüz açılmamış bir konutta bireysel gaz tesisatı yapılmışsa ve yetkili kurulumcunun verdiği tesisat sertifikan varsa tedarikçini seç; tedarikçi abonelik ve hizmete alma talebini senin adına dağıtım şirketine iletir. Dağıtım şirketi talebi en çok 6 iş günü içinde doğrular, kontroller olumluysa başka en çok 6 iş günü içinde aboneliği açar. Yeni abonelikte dağıtım şirketine abonelik hakkı (derechos de alta) ve bağlantı (enganche) bedellerini, ayrıca tesisat doğrulaması bedelini ödersin; ancak tesisat için yetkili gaz kurulumcusunun boletín'inin sunulması gerekiyorsa ya da tesisatın yapımında proje ve nihai iş sertifikası sunulması gerekmişse doğrulama bedeli ödenmez. Binanın gaz şebekesine bağlantısı yoksa dağıtım şirketinden bağlantı hattı (acometida) istemen gerekir. Sözleşmeyi tedarikçinin satış ofisinde, telefonla ya da internetten yap; evde satış yasaktır. Telefonla arandıysan ve sözleşme yapmaktan emin değilsen satıcıya banka hesap numaranı verme. Konutuna atanmış CUPS kodunu hazırla; kod bütün gaz faturalarında yazar. Sözleşmeyi imzalayınca yeni tedarikçi geçişi dağıtım şirketiyle yürütür; geçiş ücretsizdir ve en geç 3 hafta içinde yapılır, istersen daha uzun bir süre isteyebilirsin. Telefon ya da internetten sözleşme yaptıysan 14 gün içinde sözleşmeden cayabilirsin; cayarsan önceki tedarikçine dönersin. | P49: CUPS kodu (gaz faturalarında yazar) | Q49: Tedarikçi değişimi en geç 3 hafta sürer. Gazı henüz açılmamış konutta dağıtım şirketi talebi doğrulamak için en çok 6, aboneliği açmak için başka en çok 6 iş günü kullanır. TUR'un değişken terimi Ocak, Nisan, Temmuz ve Ekim ayının 1'inde güncellenebilir; her yıl Ekim ayında tüketiciler son yıl tüketimine uygun TUR kademesine yeniden yerleştirilir. | S49: Gaz faturası şu kalemleri içerir: sabit terim (yıllık ücret, fatura dönemindeki gün sayısına göre uygulanır), değişken terim (tüketilen kWh ile sözleşmedeki fiyatın çarpımı), hidrokarbür vergisi, tedarikçiden aldığın ek hizmetler (ayrı yazılmalıdır) ve IVA. Dağıtım şirketi sayaç tüketiciye ait değilse sayaç kirası, 5 yılda bir yapılan tesisat denetimi, ortak tesisat kirası (canon IRC) ve yeni bağlantıda bağlantı hakları gibi hizmetleri de faturalayabilir. Faturada sayaçtaki m3 okuması (gerçek mi tahmini mi olduğuyla birlikte) ve m3'ü kWh'a çeviren faktör yazılmalıdır. Konut amaçlı apartman yönetimleri (comunidad de propietarios) tüketimlerinden bağımsız olarak TUR'a girebilir; bunun için iki şartı taşımaları gerekir: bireysel kalorifer sayacı ya da maliyet paylaştırıcısı olması (teknik olarak imkânsızsa muaftır) ve enerji verimliliği denetimini süresi içinde olumlu sonuçlandırmış olması.
A50: sevilla:bono-social-elektrik-kimler-alir | B50: sevilla | C50: bono-social-elektrik-kimler-alir | D50: Bono social eléctrico (elektrik faturası indirimi) kimlere verilir? | E50: Oturduğun konutta PVPC sözleşmen olmalı; gelir, aile ya da emeklilik durumun resmî ölçütlerden birine uymalı | F50: Bono social (elektrik faturası indirimi) için oturduğun asıl konutta PVPC sözleşmen olmalı ve gelir ya da aile durumun MITECO'nun sıraladığı ölçütlerden birine uymalı. MITECO'nun 2026 sayfasına göre 31 Aralık 2026'ya kadar indirim savunmasız tüketicide %42,5, ağır savunmasız tüketicide %57,5'tir; olağan oranlar ise %35 ve %50'dir. İndirim enerji terimi üzerine ve yıllık kWh sınırları dahilinde uygulanır. Savunmasız sayılmak için şunlardan biri yeter: birlikte yaşayanların yıllık toplam geliri IPREM'in 1,5 katını aşmamak (sayfada 14 maaşlı 1 IPREM = 8.400 euro), büyük aile (familia numerosa) belgesi, gelir sahibi bütün hane üyelerinin Sosyal Güvenlik emeklisi olup asgari emekli maaşı alması ve başka yıllık gelirlerinin toplamda 500 euroyu aşmaması ya da hanede birinin Ingreso Mínimo Vital yararlanıcısı olması. Birlikte yaşayan her ek yetişkin için gelir çarpanı 0,3, her çocuk için 0,5 artar. | G50: bono social, bono social eléctrico, elektrik indirimi, consumidor vulnerable, IPREM, PVPC, familia numerosa | H50: new;settled | I50: sevilla:kaynak:071;sevilla:kaynak:072 | J50: 46319 | K50: 9054 | L50: Hayır | M50: Taslak | N50: sevilla:fatura | O50: Elektrik sözleşmenin oturduğun asıl konutta (vivienda habitual) ve PVPC üzerinde olduğunu kontrol et. Savunmasız tüketici ölçütlerinden birine uyup uymadığına bak: birlikte yaşayanların toplam yıllık geliri en çok IPREM'in 1,5 katı (sayfada 14 maaşlı 1 IPREM = 8.400 euro olarak verilir; her ek yetişkin için +0,3, her çocuk için +0,5), büyük aile belgesi, gelir sahibi bütün hane üyelerinin Sosyal Güvenlik emeklisi (yaşlılık ya da kalıcı iş göremezlik) olup ilgili emeklilik türünün asgari tutarını alması ve başka yıllık gelirlerinin toplamda 500 euroyu aşmaması ya da hanede birinin Ingreso Mínimo Vital yararlanıcısı olması. Hanende biri en az yüzde 33 oranında tanınmış engelli, cinsiyete dayalı şiddet mağduru, terör mağduru ya da II. veya III. derece bakım bağımlılığı durumundaysa, ya da tek ebeveyn ve en az bir çocuktan oluşan bir aileysen gelir sınırları 1 IPREM puanı (sayfada 8.400 euro daha) artar. Ağır savunmasız tüketici için gelirin savunmasız eşiklerinin yarısını aşmaması gerekir; büyük ailede sınır 2 IPREM (sayfada 16.800 euro), gelir sahibi bütün üyeleri asgari emekli maaşı alan ve başka yıllık geliri toplamda 500 euroyu aşmayan hanede 1 IPREM'dir (sayfada 8.400 euro). Ağır savunmasız ölçütlerini karşılıyorsan ve bir kamu idaresinin (özerk bölge ya da yerel) sosyal hizmetleri seni izleyip PVPC faturanın en az yüzde 50'sini finanse ediyorsa sosyal dışlanma riski altındaki tüketici sayılırsın; geçici ödeme güçlüğünde elektriğin kesilmesi yasaktır. İndirim enerji terimi üzerine ve yıllık kWh sınırları dahilinde uygulanır. Yıllık sınırlar (Real Decreto 897/2017 Anexo I tablosu, hane bileşimine göre): bireysel talep ya da iki kişilik hane 1.587 kWh; üç kişilik hane, asgari emekli maaşı alan emekliler ya da iki kişilik ve biri çocuk olan hane 2.222 kWh; dört kişilik hane ya da üç kişilik ve ikisi çocuk olan hane 2.698 kWh; beş ve daha fazla kişilik hane, dört kişilik ve üçü çocuk olan hane ya da büyük aile 4.761 kWh. | Q50: MITECO'nun 2026 sayfasına göre %42,5 ve %57,5 oranları 31 Aralık 2026'ya kadar geçerlidir. | S50: IPREM, Indicador Público de Renta de Efectos Múltiples'in kısaltmasıdır; gelir sınırları bu göstergenin katları olarak verilir. MITECO sayfasında 1 IPREM (14 maaşlı) 8.400 euro, 2 IPREM 16.800 euro olarak yazılıdır.
A51: sevilla:internet-mobil-hat-sozlesmesi-taahhut-cayma | B51: sevilla | C51: internet-mobil-hat-sozlesmesi-taahhut-cayma | D51: İnternet ve mobil hat sözleşmesi: taahhüt süresi, süre dolmadan fesih ve 14 günlük cayma hakkı nasıl işler? | E51: Sözleşme en çok 24 ay sürer; 14 günlük cayma yalnız uzaktan ve işyeri dışı sözleşmelerde vardır ve istisnaları vardır | F51: Bireysel tüketici için internet ve mobil hat sözleşmesi en çok 24 ay sürebilir; yalnız fiziksel hat (örneğin fiber) kurulumunu ayrı bir sözleşmeyle taksitle ödediysen bu üst sınır o taksit sözleşmesine uygulanmaz. 14 günlük cayma hakkı yalnız uzaktan (telefon, internet, posta gibi) ve işyeri dışında yapılan sözleşmelerde geçerlidir; operatörün dükkânında imzaladığın sözleşmeye otomatik uygulanmaz. Cayma hakkının istisnaları vardır: hizmet tamamen verilmişse cayamazsın; ödemeli hizmette bu, hizmetin başlamasına önceden açık onay verdiğin ve tamamlanınca cayma hakkını yitireceğini bildiğin durumda geçerlidir; hizmetin cayma süresi içinde başlamasını açıkça istediysen cayarken o ana kadar verilen hizmetin orantılı bedelini ödersin. Süre dolunca sözleşme aynı süre kadar kendiliğinden uzar; bundan sonra en çok bir ay önceden haber vererek, haber süresindeki hizmet bedeli dışında maliyetsiz her an feshedebilirsin. Süre dolmadan, fesih hakkın doğmadan kendi isteğinle bitirirsen maliyet ve cezalar olabilir; operatör bunları sözleşme özetinde yazmak zorundadır. | G51: internet sözleşmesi, mobil hat, taahhüt, permanencia, cayma hakkı, desistimiento, 24 ay, operatör | H51: new;settled | I51: sevilla:kaynak:073;sevilla:kaynak:074 | J51: 46319 | K51: 9055 | L51: Hayır | M51: Taslak | N51: sevilla:fatura | O51: Sözleşmeyi nasıl yaptığını netleştir: telefon, internet ya da posta gibi uzaktan veya işyeri dışında yaptıysan 14 takvim günü içinde gerekçe göstermeden cayabilirsin; bu hakkın istisnası ve olası bir bedeli vardır (sonraki adım). Hizmet tamamen verilmişse cayma hakkı uygulanmaz; ödemeli hizmette bu, hizmetin başlamasına önceden açık onay verdiğin ve tamamlanınca cayma hakkını yitireceğini bildiğin durumda geçerlidir. Hizmetin cayma süresi içinde başlamasını açıkça istediysen, cayarken o ana kadar verilen hizmetin orantılı bedelini ödersin. Cayma hakkını kullandığın için ceza koyan sözleşme hükümleri tamamen geçersizdir. Evine istenmeden gelen satıcıyla ya da operatörün satış amaçlı düzenlediği bir gezide imzaladıysan cayma süresi 30 takvim günüdür. Dükkânda yüz yüze imzaladıysan yasal 14 günlük cayma hakkın yoktur; ancak işyeri dışında seninle kişisel görüşme yapıldıktan hemen sonra dükkânda ya da uzaktan imzalanan sözleşmeler de bu kuralların kapsamındadır. Sözleşme süresini kontrol et: bireysel tüketici sözleşmesi 24 aydan uzun olamaz (yalnız fiziksel hat kurulumu için ayrı yapılan taksit sözleşmesi hariç). Otomatik uzatmadan önce operatörün gönderdiği bildirimi oku: taahhüdün bittiğini, nasıl fesih edeceğini ve en iyi tarifelerini içermek zorundadır. Süre dolmadan kendi isteğinle çıkmak istiyorsan sözleşme özetindeki fesih maliyetleri ve olası cezalar bölümüne bak. Operatör koşulları değiştireceğini bildirirse bildirimden itibaren bir ay içinde ek maliyet ödemeden sözleşmeyi feshedebilirsin; değişiklik yalnız senin lehine, tamamen idari nitelikte ve sana olumsuz etkisi olmayan ya da mevzuatın zorunlu kıldığı bir değişiklikse bu hak doğmaz. | Q51: Sözleşme en çok 24 ay sürer. Cayma süresi 14 takvim günüdür; evde istenmeyen ziyaretlerde 30 takvim günüdür. Süre dolup sözleşme uzadıktan sonra fesih için en çok bir ay önceden haber verilir. | S51: Fesih hakkının kanundan doğduğu durumlarda (örneğin operatör sözleşme koşullarını değiştirdiğinde), sübvansiyonlu cihazı (terminal) elinde tutmadıkça tazminat ödemezsin. Cihazı tutarsan tazminat, cihazın orantılı değerini ya da sözleşme sonuna kalan hizmet bedelini aşamaz (hangisi daha düşükse). Hakkın doğmadan erken bitirirsen sözleşmedeki maliyet ve cezalar uygulanabilir. Dayanak: Ley 11/2022 madde 67 (BOE'de 27/12/2025 tarihli güncel metin) ve RDL 1/2007 madde 92 ile 102 ile 108 (BOE'de 28/02/2026 tarihli güncel metin).
A52: sevilla:cnmc-teklif-karsilastirma-araci | B52: sevilla | C52: cnmc-teklif-karsilastirma-araci | D52: CNMC karşılaştırma aracı elektrik ve doğalgaz tekliflerini nasıl karşılaştırır? | E52: Araç yalnız bilgi verir; teklifi sözleşmeye çevirmez, sözleşmeyi seçtiğin tedarikçiyle yaparsın | F52: CNMC'nin enerji teklifleri karşılaştırma aracı, kendi tüketimini piyasadaki tekliflerle karşılaştırıp profiline en uygun olanı seçmene yardım eder. Araçta regüle fiyatlı teklifler (elektrikte PVPC, gazda TUR) ile serbest fiyatlı teklifler birlikte görünür. Araç yalnızca bilgilendirir ve teklifi doğrudan sözleşmeye çevirmez; sözleşme için seçtiğin tedarikçiye ayrıca başvurursun. Elektrik ve gaz tedarikçileri tekliflerini CNMC'ye bildirmek zorundadır. | G52: CNMC karşılaştırıcı, comparador de ofertas, elektrik teklifleri, gaz teklifleri, PVPC simülatörü, tedarikçi değiştirme | H52: new;settled | I52: sevilla:kaynak:075;sevilla:kaynak:070 | J52: 46319 | K52: 9056 | L52: Hayır | M52: Taslak | N52: sevilla:fatura | O52: https://comparador.cnmc.gob.es/ adresindeki karşılaştırma aracını aç; gaz faturanda QR kod varsa aracı o kodla da açabilirsin. Kendi tüketimini araca gir ve piyasadaki tekliflerle karşılaştır. Regüle fiyatlı teklifleri (elektrikte PVPC, gazda TUR) ve serbest fiyatlı teklifleri birlikte incele. Fiyatın yanında taahhüt (permanencia) şartlarına ve teklife dahil ek hizmetlere de bak. Seçtiğin teklif için sözleşmeyi araç üzerinden yapamazsın; sözleşme için seçtiğin tedarikçiye başvur. PVPC'de, 10 kW ve altı güçte ve referans tedarikçideysen, faturanı CNMC'nin PVPC fatura simülatörüyle simüle et; serbest piyasa sözleşmen varsa ya da gücün 10 kW'ın üzerindeyse simülatör işine yaramaz. | S52: Elektrik ya da gazda tedarikçi değişiminin kendisi ücretsizdir (mevcut sözleşmendeki taahhüt şartları ayrıdır); CNMC'ye göre değişim için azami süre 21 gündür ve bütün işlemleri yeni tedarikçi yürütür.
A53: sevilla:elektrik-ve-telekom-sikayet-yollari | B53: sevilla | C53: elektrik-ve-telekom-sikayet-yollari | D53: Elektrikte şebeke kesintisi, elektrik faturası sorunu veya telekom şikâyetinde hangi yol izlenir? | E53: Önce şirkete şikâyet et: elektrikte 15 iş günü, telekomda bir ay bekle; sonra tahkim, özerk bölge ya da OAUT | F53: Elektrikte önce sorunun muhatabı şirkete şikâyet edersin: fatura ve sözleşme için tedarikçiye (comercializadora), şebekenin kalitesi ve sürekliliği için dağıtım şirketine (distribuidora). Şirket 15 iş günü içinde yanıt vermek zorundadır; memnun kalmazsan Defensor del cliente'ye, tahkim kurullarına (Juntas Arbitrales de Consumo), akredite bir alternatif çözüm kuruluşuna ya da özerk bölgenin tüketici organına gidebilirsin. Telekomda da önce operatöre şikâyet edersin; bir ay içinde yanıt alamazsan ya da yanıt yetmezse telekomünikasyon kullanıcı bürosuna (OAUT) başvurursun. Gerçek kişiysen telekomda hakem kurullarına (Juntas Arbitrales de Consumo) da gidebilirsin; bu yol operatörün hakem sistemine katılmasına bağlıdır ve operatör reddederse OAUT'a başvuru süresi yeniden açılır. | G53: şikâyet, reclamación, kesinti, distribuidora, comercializadora, OAUT, Juntas Arbitrales de Consumo, Defensor del cliente | H53: new;settled | I53: sevilla:kaynak:076;sevilla:kaynak:077 | J53: 46319 | K53: 9057 | L53: Hayır | M53: Taslak | N53: sevilla:fatura | O53: Elektrikte şikâyetini önce ilgili şirketin tüketici hizmetine ilet: fatura ve sözleşme konusunda tedarikçiye, şebekenin kalitesi ve sürekliliği konusunda dağıtım şirketine. Şikâyette referans numarası al; telefonla yaptıysan başvurunu ve içeriğini kanıtlayan bir belge isteme hakkın var. Elektrikte 15 iş günü içinde memnun edici yanıt alamazsan Defensor del cliente'ye, Juntas Arbitrales de Consumo'ya, akredite bir alternatif çözüm kuruluşuna ya da özerk bölgenin tüketici organına başvur. Defensor del cliente şikâyeti en çok 2 ayda sonuçlandırır ve kararı şirketi bağlar; şirketler bu birimi gönüllü kurduğu için hepsinde bulunmaz. Telekomda şikâyeti önce operatöre telefonla, internetten, postayla ya da ticari ofisinde yap; operatör telefonla şikâyeti kabul etmek zorundadır ve sana referans numarası verir. Operatörden bir ay içinde yanıt alamazsan ya da yanıt seni tatmin etmezse OAUT'a başvur; başvuruyu elektronik sertifika ya da Cl@ve ile internetten yapabilir ya da formu imzalayıp idarenin herhangi bir kayıt biriminden ya da postayla verebilirsin. Gerçek kişiysen telekom uyuşmazlığı için Juntas Arbitrales de Consumo (tüketici hakem kurulları) yolunu da kullanabilirsin; operatörün bu hakem sistemine katılıp katılmadığını Tüketim Bakanlığı'nın internet sitesinden öğrenebilirsin. OAUT'a başvuru süresi içinde hakeme gittiysen ve operatör hakeme katılmayı reddederse, OAUT'a başvuru için 3 aylık süre yeniden açılır. | Q53: Elektrikte şirketin yanıt süresi en çok 15 iş günüdür. Telekomda operatörün yanıt süresi bir aydır; OAUT'a başvuru süresi operatörün yanıtından ya da yanıt süresinin bitişinden itibaren 3 aydır ve OAUT şikâyeti başvurudan itibaren 6 ay içinde sonuçlandırır. Gerçek kişi OAUT süresi içinde hakeme gidip operatör katılmayı reddederse OAUT için 3 aylık süre yeniden açılır. | S53: OAUT kararı idari yolu kapatır; karara karşı alındığı tarihten itibaren bir ay içinde itiraz (recurso de reposición) ya da iki ay içinde idari yargıya dava (recurso contencioso-administrativo) yoluna gidilebilir.
A54: sevilla:apartman-yonetimi-comunidad-de-vecinos | B54: sevilla | C54: apartman-yonetimi-comunidad-de-vecinos | D54: Daire sahibi için apartman yönetimi (comunidad de propietarios): ortak giderler, kurul ve yedek fon (Katalonya dışı genel kural) | E54: Katalonya dışı genel kural (Ley 49/1960): daire sahibi payı oranında ortak giderlere katılır, kurul yılda en az bir kez toplanır | F54: Aşağıdaki bilgiler Katalonya dışındaki genel kural olan Ley de Propiedad Horizontal'a (Ley 49/1960) göre, daire sahibi açısından yazılmıştır; Katalonya'da kat mülkiyeti kendi medeni kanununun 5. kitabıyla (Código Civil de Cataluña, Ley 5/2006) düzenlenir. Ley 49/1960'a göre daire ya da işyeri (local) sahibi, ortak giderlere senette (título) belirlenen ya da özel olarak kararlaştırılan katılım payına (cuota de participación) göre katılmak zorundadır. Topluluğun organları Junta de propietarios (mülk sahipleri kurulu), başkan (presidente), varsa başkan yardımcıları, sekreter ve yöneticidir (administrador); sekreter ve yönetici görevlerini, tüzük ya da kurul ayrı atamadıkça başkan yürütür. Kurul en az yılda bir kez bütçeyi ve hesapları onaylamak için toplanır. Yedek fon (fondo de reserva) Ley 49/1960'a göre son olağan bütçenin en az %10'u kadar olmalıdır; Katalonya'da ise bütçede ortak giderlerin en az %5'i yedek fon için ayrılır (Código Civil de Cataluña md. 553-6). | G54: comunidad de vecinos, propiedad horizontal, apartman yönetimi, junta de propietarios, presidente, fondo de reserva, cuota | H54: new;settled | I54: sevilla:kaynak:078;sevilla:kaynak:079 | J54: 46319 | K54: 9058 | L54: Hayır | M54: Taslak | N54: sevilla:fatura | O54: Binanın bakımı, hizmetleri ve yükleri için bireysel olarak ayrılamayan genel giderlere, senette (título) belirlenen ya da özel olarak kararlaştırılan katılım payına (cuota de participación) göre katıl. Yedek fona (fondo de reserva) da katılım payına göre katıl. Sekretere İspanya'daki bildirim adresini, iletimini kanıtlayan bir yolla yazılı bildir; bildirmezsen çağrılar ve bildirimler topluluktaki dairene yapılır (dairedeki kişiye teslim edilen bildirim de tam geçerlidir), ulaşılamazsa ilan panosuna asılır ve üç takvim günü sonra geçerli olur. Kurulun gündemine konu eklemek istiyorsan başkana yazılı olarak konuyu açıkça belirt; başkan konuyu bir sonraki toplantının gündemine koyar. Kurul toplantısına kendin ya da imzalı yazılı yetkiyle bir temsilci aracılığıyla katıl; vadesi gelmiş borcun varsa (ve borca mahkemede itiraz etmediysen ya da tutarı mahkeme veya noter aracılığıyla bırakmadıysan) görüşebilirsin ama oy kullanamazsın. Dairenin sahibi değişirse sekretere yazılı bildir; bildirmezsen (yönetim organları değişikliği başka bir yolla öğrenmediyse) devirden sonraki borçlardan yeni malikle birlikte müteselsil sorumlu kalırsın. Başkan seçilirsen: görev zorunludur, ama göreve geldikten sonraki bir ay içinde hakimden görevden alınmanı isteyebilirsin. | Q54: Kurul en az yılda bir kez toplanır; Ley 49/1960'a göre (Katalonya dışı) olağan yıllık toplantının çağrısı en az 6 gün önceden yapılır; Katalonya'da çağrı, davet ve bildirimler en az 8 takvim günü önceden gönderilir (Código Civil de Cataluña md. 553-21.2). Tüzük aksini söylemedikçe yönetim organları bir yıl için seçilir. | R54: Ley 49/1960'a göre yedek fon, topluluğun son olağan bütçesinin en az %10'u kadar olmalıdır. Katalonya'da bütçede ortak giderlerin en az %5'i yedek fon için ayrılır (Código Civil de Cataluña md. 553-6). | S54: Bu bilgiler daire sahiplerinin yükümlülüklerine dairdir ve Ley 49/1960'ın BOE'deki 03/10/2026 tarihli güncel metnine göre yazılmıştır; Katalonya için yalnız aşağıda ayrıca etiketlenen değerler verilmiştir (Ley 5/2006'nın BOE'deki 03/07/2026 tarihli güncel metni). Ley 49/1960 (Katalonya dışı): Daire alırsan, satın alınan daire önceki sahiplerin ortak gider borçlarından devrin yapıldığı yılın vadesi gelmiş kısmı ile önceki üç takvim yılı kadarıyla sorumludur. Satıcı, devir belgesinde borç durumunu beyan etmeli ve sekreterin verdiği borç sertifikasını sunmalıdır (alıcı onu açıkça muaf tutmadıkça); sertifika talepten itibaren en çok 7 takvim günü içinde verilir. Katalonya (Código Civil de Cataluña): Özel bölümler, ortak giderler ve yedek fon için cari yılın vadesi gelmiş kısmından ve hemen önceki dört yıldan doğan tutarlardan sorumludur (md. 553-5.1). Toplantı çağrıları, davetler ve bildirimler, tüzük açıkça başka bir şey söylemedikçe en az 8 takvim günü önceden gönderilir (md. 553-21.2).
A55: sevilla:su-aboneligi-emasesa-ilk-kez | B55: sevilla | C55: su-aboneligi-emasesa-ilk-kez | D55: Sevilla'da su aboneliği (EMASESA) nasıl açılır, hangi belgeler istenir? | E55: Online ya da randevuyla; evde yaşayanları gösteren padrón belgesi tarifeyi belirler | F55: Sevilla'da su sözleşmesini EMASESA ile yaparsın. Başvuruyu Oficina Online'dan evden verebilir ya da Puntos de Atención Ciudadana'da cita previa (randevu) alarak yüz yüze yapabilirsin. Başvuru formuna kimlik, evi kullanma hakkını gösteren belge ve iç tesisat belgesi eklenir. Konut için evde yaşayanları gösteren certificado de empadronamiento colectivo (toplu ikamet kaydı belgesi) özellikle önemlidir, çünkü tarife evdeki kişi sayısına göre uygulanır. Ücret ödenip şartlar tamamlanınca EMASESA suyu en geç 15 iş günü içinde açmakla yükümlüdür; işler için gereken izin ya da ruhsatlar gecikirse bu süre durur. | G55: su aboneliği, EMASESA, agua Sevilla, contratar agua, empadronamiento colectivo, cita previa, alta de suministro | H55: new | I55: sevilla:kaynak:156;sevilla:kaynak:158 | J55: 46320 | K55: 500 | L55: Evet | M55: Taslak | N55: sevilla:fatura | O55: Oficina Online'dan başvur ya da Puntos de Atención Ciudadana için cita previa al; yüz yüze gidiyorsan doldurulmuş ve çıktısı alınmış başvuru formunu götür (Solicitud para la Instalación de Suministro y/o Alcantarillado, CO015). Kimlik belgeni ekle: NIF, NIE veya pasaport. Evi kullanma hakkını gösteren belgeyi ekle (tapu ya da kira sözleşmesi gibi); belgede evin catastral referansı (kadastro numarası) yazmalı. Belediyeden evde yaşayan herkesin göründüğü güncel certificado de empadronamiento colectivo'yu al ve ekle. Yeni ya da yenilenmiş konutsa Licencia Municipal de Primera Ocupación'u (ilk iskân ruhsatı) de ekle. Kurulum firmasından Certificado de Instalación Interior (iç tesisat belgesi) iste; EMASESA'nın kodlu basılı formu önerilir. | P55: Başvuru formu CO015 (Solicitud para la Instalación de Suministro y/o Alcantarillado) NIF, NIE veya pasaport Evi kullanma hakkını gösteren belge (tapu, kira sözleşmesi) ve catastral referans Certificado de empadronamiento colectivo Licencia Municipal de Primera Ocupación (yeni ya da yenilenmiş konutta) Certificado de Instalación Interior | Q55: Ücret ödenip şartlar tamamlandıktan sonra en geç 15 iş günü; gerekli izin ya da ruhsat gecikirse süre durur | S55: Padrón belgesini sözleşmeden sonra verirsen etkisi yalnız verdiğin günden başlar, geriye dönük işlemez.
A56: sevilla:su-sozlesmesi-devir-cambio-titularidad-ve-baja | B56: sevilla | C56: su-sozlesmesi-devir-cambio-titularidad-ve-baja | D56: Evde su sözleşmesi başkasının adınaysa: devir (cambio de titularidad) ve taşınırken kapatma (baja) | E56: Devir ücretsiz ama teminat (fianza) istenir; sözleşmeyi kapatmak abonenin yükümlülüğü | F56: Taşındığın evde su sözleşmesi başka birinin adınaysa yeni abonelik değil, EMASESA'dan devir (transferencia ya da cambio de titularidad) istersin. Evi satın almak ya da kiralamak devir nedenlerinden biridir. Devir ücretsizdir; yalnız olası borçlar için EMASESA kasasına bir teminat (fianza) yatırılır. Evden ayrılırken sözleşmeyi kapatmayı (baja) abone bildirmek zorundadır. Kapatmada ya da devirde bir kapanış faturası (factura de liquidación) çıkar; bunu kapatmayı isteyen abone ya da devirde önceki abone öder. | G56: su sözleşmesi devri, cambio de titularidad, baja, EMASESA, fianza, factura de liquidación, kiracı su | H56: new;settled | I56: sevilla:kaynak:157;sevilla:kaynak:158 | J56: 46319 | K56: 501 | L56: Hayır | M56: Taslak | N56: sevilla:fatura | O56: Devri Oficina Online'dan iste ya da Puntos de Atención Ciudadana için cita previa al; yüz yüze gidiyorsan doldurulmuş ve çıktısı alınmış Solicitud de cambio de titularidad formunu götür. Kimlik belgeni (NIF, NIE veya pasaport) ve evi kullanma hakkını gösteren belgeyi ekle. Evde yaşayanları gösteren güncel certificado de empadronamiento colectivo'yu ekle. Sayacın endeksinin açık okunduğu bir fotoğrafını ekle. Teminatı (fianza) EMASESA kasasına yatır. Evden çıkarken sözleşmeyi kapatmak için baja bildir; bunu yapmak abonenin yükümlülüğüdür. | P56: Solicitud de cambio de titularidad de un contrato NIF, NIE veya pasaport Evi kullanma hakkını gösteren belge Certificado de empadronamiento colectivo Sayacın endeksinin okunduğu fotoğraf | R56: Devir ücretsiz; teminat (fianza) yatırılır | S56: Boşanmada konutu kullanma hakkı mahkemece onaylı convenio regulador ile sana verildiyse devir isteyebilirsin; süre olay tarihinden itibaren iki yıldır. Ölümde eş, kayıtlı partner, çocuklar, evlat edinilmiş çocuklar, anne-baba ve kardeşler sözleşmeyi devralabilir.
A57: sevilla:su-fiyati-kisi-sayisina-gore-emasesa-tarifesi | B57: sevilla | C57: su-fiyati-kisi-sayisina-gore-emasesa-tarifesi | D57: Sevilla'da su ne kadar tutar: evdeki kişi sayısına göre blok tarife ve örnek m³ fiyatları | E57: Konut tüketimi evde kayıtlı kişi sayısına göre faturalanır; 2025 yılı 3 kişilik örnekte m³ başına 2,369 ile 4,089 euro (KDV hariç) | F57: EMASESA konut tüketimini evde kayıtlı (padrón ile kanıtlanmış) kişi sayısına göre faturalar; tarife kişi başına tüketim bloklarından oluşur. Bu yüzden evde yaşayan herkesin o adreste kayıtlı olması fiyatı doğrudan etkiler. EMASESA'nın 2025 yılı için yayımladığı 3 kişilik örnekte aylık 7 m³ tüketimde m³ başına 2,369 euro, 15 m³'te 3,084 euro, 30 m³'te 4,089 euro çıkıyor. Bu tutarlara KDV ve Junta de Andalucía'nın altyapı katkı payı (canon) dahil değil. EMASESA 18 Şubat 2026 tarihli BOP 33/2026 yönetmeliğiyle yeni tarifeler yayımladı; bu tutarlar 2025 tarifelerinden hesaplandığı için 2026'da ödeyeceğin m³ fiyatı bu örnekten farklı olabilir. | G57: su tarifesi, EMASESA tarifa, agua precio Sevilla, bloque, m3 fiyatı, padrón, empadronados | H57: planning;new | I57: sevilla:kaynak:160;sevilla:kaynak:161 | J57: 46320 | K57: 502 | L57: Hayır | M57: Taslak | N57: sevilla:fatura | O57: Evde yaşayan herkesin o adreste padrón kaydı olduğundan emin ol; EMASESA kişi sayısını bu kayda göre alır. Faturadaki sözleşme bölümünde yazan kişi sayısının doğru olup olmadığına bak. Kendi tüketimin için Oficina Online'daki ya da Mi Emasesa uygulamasındaki fatura simülatörünü kullan. 2026 tarifelerini EMASESA'nın tarife sayfasındaki 'Nuevas Tarifas' belgesinden incele. | R57: 3 kişilik örnek, KDV ve canon hariç, EMASESA'nın 2025 örneği: aylık 7 m³ için 2,369 euro/m³; 15 m³ için 3,084 euro/m³; 30 m³ için 4,089 euro/m³
A58: sevilla:emasesa-su-faturasi-nasil-okunur-kalemler | B58: sevilla | C58: emasesa-su-faturasi-nasil-okunur-kalemler | D58: EMASESA su faturası nasıl okunur: sabit ücret, tüketim, canon ve KDV | E58: Fatura içme suyu, atık su, kurum canonları ve KDV'den oluşur; sabit ücret sayaç çapına bağlı | F58: EMASESA faturası içme suyu (abastecimiento) ve atık su (saneamiento) hizmetini ve diğer kurumlar adına toplanan canonları kapsar. Her hizmette sabit (cuota fija) ve değişken (cuota variable) bölüm vardır. Sabit ücret hizmeti kullansan da kullanmasan da ödenir ve sayacın çapına (calibre) göre belirlenir; değişken ücret tüketime göre artan bloklarla hesaplanır. Canonlar Consorcio Provincial de Aguas ve Junta de Andalucía adınadır. KDV su ile ilgili kalemlerde %10, diğer kalemlerde %21'dir. Bazı belediyelerde çöp tasası (tasa de basuras) da su faturasından toplanır; öyleyse faturanın döküm bölümünde ayrıca yazar. | G58: su faturası, EMASESA factura, cuota fija, cuota variable, canon, calibre, tasa de basuras | H58: new;settled | I58: sevilla:kaynak:161;sevilla:kaynak:167 | J58: 46319 | K58: 503 | L58: Hayır | M58: Taslak | N58: sevilla:fatura | O58: Fatura başında fatura numarasına, son ödeme tarihine, faturalama dönemine ve ödenecek tutara bak. Sözleşme bölümünde evde kayıtlı kişi sayısının doğru olduğundan emin ol; su fiyatı buna göre hesaplanır. Okuma özetinde sayaç numarasına, sayaç çapına, önceki ve şimdiki endekse ve yöntemin gerçek mi tahmin mi olduğuna bak. Döküm bölümünde abastecimiento, saneamiento, canonlar ve KDV satırlarını tek tek oku. Tüketim geçmişi bölümünden son 5 dönemin litre/gün tüketimini kendi dönemlerinle karşılaştır. | Q58: Faturalama en çok 3 ayda bir yapılır | S58: EMASESA'ya göre bir kişinin verimli su tüketimi ayda 3 m³'ü aşmamalı.
A59: sevilla:emasesa-sosyal-tarife-kimler-yararlanir | B59: sevilla | C59: emasesa-sosyal-tarife-kimler-yararlanir | D59: EMASESA sosyal su tarifesi (tarifa social): kimler yararlanır, indirim yüzde kaç? | E59: Kişi başı günde 110 litreye kadar %25 ile %100 arası indirim; ölçüt evde kayıtlı kişilerin geliri | F59: Tarifa social, kişi başı günde 110 litreye kadar tüketime indirim getirir; bu miktarı aşan tüketim indirimsiz ödenir. Aynı evde kayıtlı kişilerin toplam brüt gelirine göre dört düzey var: %25 (Tip 1), %50 (Tip 2), %75 (Tip 3) ve %100 (ağır kırılganlık ya da sosyal dışlanma riski). Gelir sınırı IPREM'in (çoklu etki göstergesi) katı olarak verilir ve kayıtlı kişi sayısıyla artar; hesaba 16 yaşın üstündeki kayıtlı kişilerin geliri girer. Sabit ücretler, sözleşme ve yeniden bağlanma ücretleri de indirimli olur. | G59: tarifa social, sosyal tarife, su indirimi, EMASESA, IPREM, vulnerabilidad, bonificación agua | H59: new;settled | I59: sevilla:kaynak:159;sevilla:kaynak:158 | J59: 46320 | K59: 504 | L59: Evet | M59: Taslak | N59: sevilla:fatura | O59: Evde kayıtlı 16 yaş üstü herkesin brüt gelirini topla ve aşağıdaki IPREM katı tablosuyla karşılaştır. Su sözleşmesinin evde kayıtlı kişilerden birinin adına olduğundan emin ol; değilse devir iste. Adresinde padrón kaydının olduğundan emin ol; indirim kişi sayısı padrón belgesiyle hesaplanır. Bekleyen borcun varsa önce öde ya da borç tanıma (reconocimiento de deuda) imzala. | R59: Gelir sınırı (IPREM katı; Tip 1 / Tip 2 / Tip 3 / ağır kırılganlık): 1 kişi 1,30 / 1,15 / 1,05 / 0,95; 2 kişi 1,60 / 1,40 / 1,30 / 1,20; 3 kişi 1,90 / 1,70 / 1,55 / 1,45; 4 kişi 2,10 / 1,95 / 1,85 / 1,75; 5 kişi 2,30 / 2,15 / 2,10 / 2,00; 6 ve üzeri 2,45 / 2,25 / 2,15 / 2,05 | S59: %33 ve üzeri engeli olanlar ile evde bakılan III. derece bağımlılar iki kişi sayılır. Başka bir kamu kurumundan ya da özel kuruluştan aynı amaçla yardım alan hane yararlanamaz. Suyu açık konutta indirim süresince fiilen su kullanman gerekir; EMASESA'nın sık sorulan sorular sayfası bunu ayda ortalama en az 333 litre diye yazıyor, tarife sayfası ise haklı bir nedenle tüketim olmazsa indirimin sabit ücretlere uygulanabileceğini belirtiyor. Ekonomik ölçüt olarak EMASESA'nın Şubat 2026 yönetmeliğini tanıtan tarife sayfası yalnız IPREM'i gösteriyor; sık sorulan sorular sayfası ise ek olarak 16 yaş üstü kayıtlı kişilerin konut dışı mülkleri için kadastro değeri sınırı yazıyor (tek yetişkin için 16.917,60 euro). Bu ek sınırın yürürlükte olup olmadığını başvuru öncesi tarifasocial@emasesa.com adresine sorabilirsin.
A60: sevilla:emasesa-sosyal-tarife-basvuru-belgeler-yenileme | B60: sevilla | C60: emasesa-sosyal-tarife-basvuru-belgeler-yenileme | D60: EMASESA sosyal tarifesine başvuru: nereden, hangi belgelerle, ne kadar süre geçerli, nasıl yenilenir? | E60: Online, e-posta ya da randevuyla başvurulur; indirim yıl boyunca uygulanır, bitişinden önceki 3 ay içinde yenileme istenir | F60: Sosyal tarife başvurusunu Oficina Online'dan, tarifasocial@emasesa.com adresine e-postayla ya da Puntos de Atención Ciudadana'da cita previa alarak yaparsın; imzalı başvuru formu ve gerekli belgeler birlikte verilir. Eksik olan bir şey varsa EMASESA süre tanıyan bir bildirim gönderir; süre içinde cevap vermezsen başvurudan vazgeçmiş sayılırsın ve yeni form vermen gerekir. EMASESA'nın tarife sayfasına göre onaylanan indirim, iki aylık faturalama düzenine uyarlanarak yıl boyunca uygulanır; sık sorulan sorular sayfası ise başvuru tarihinden sonraki 4 üç aylık ya da 12 aylık faturadan söz ediyor. Aynı durumdaysan bitiminden önceki 3 ay içinde yenileme istersin. | G60: sosyal tarife başvurusu, tarifa social solicitud, EMASESA, bonificación, padrón, yenileme | H60: new;settled | I60: sevilla:kaynak:159;sevilla:kaynak:158 | J60: 46320 | K60: 505 | L60: Hayır | M60: Taslak | N60: sevilla:fatura | O60: Sözleşmenin senin adına olduğundan emin ol; değilse devir iste. Devir sürerken de başvurabilirsin, değerlendirme devir tamamlanana kadar bekler. Henüz sözleşmen yoksa su aboneliği başvurusuyla birlikte verebilirsin. Solicitud tarifa social formunu EMASESA sayfasından indir ya da bir müşteri noktasından al; doldurup imzala. Aşağıdaki belgeleri hazırla; veri sorgulama izinleri evde kayıtlı 16 yaş üstü herkesin imzasını ister. Formu ve belgeleri Oficina Online'dan, tarifasocial@emasesa.com adresine e-postayla ya da cita previa ile bir müşteri noktasında teslim et. EMASESA eksik belge bildirirse verilen süre içinde tamamla; tamamlamazsan başvuru geçersiz sayılır. Onaydan sonra indirimin bitişinden önceki 3 ay içinde yenileme iste. | P60: Certificado de empadronamiento colectivo (ya da EMASESA'nın padrón verisine bakması için izin) 16 yaş üstü herkesin kimliği: İspanyol vatandaşları için DNI, yabancılar için NIE veya pasaport Agencia Tributaria verilerinin sorgulanması için 16 yaş üstü herkesin imzalı izni (izin vermeyenler son gelir beyanı ya da resmî gelir sertifikasını sunar) Engellilik ya da bağımlılık durumu varsa ilgili belge | Q60: İndirim yıl boyunca uygulanır (iki aylık faturalamaya uyarlanmış); sık sorulan sorular sayfası başvurudan sonraki 4 üç aylık ya da 12 aylık fatura diyor | S60: Toplu sayaçlı binada her daire için ayrı başvuru formu ve her daire için toplu padrón belgesi gerekir; başvuruyu yönetici ya da yöneticinin açıkça yetki verdiği kişi yapar. EMASESA'nın sık sorulan sorular sayfasındaki belge listesinde, 16 yaş üstü herkesin Catastro verilerinin sorgulanmasına imzalı izni (vermeyenler Catastro sertifikası sunar) da yer alıyor; Şubat 2026 yönetmeliğini tanıtan sayfa ise ölçütü yalnız IPREM'e bağlıyor. Bu belgenin hâlâ istenip istenmediğini tarifasocial@emasesa.com adresine sorabilirsin.
A61: sevilla:emasesa-su-faturasi-odeme-yollari | B61: sevilla | C61: emasesa-su-faturasi-odeme-yollari | D61: EMASESA su faturası nasıl ödenir: kart, Bizum, banka ve otomatik ödeme | E61: Faturadaki QR kodla kart ya da Bizum; otomatik ödeme (domiciliación) her bankada tanımlanabilir | F61: EMASESA faturasını kartla (Pago Rápido, Oficina Online, Mi Emasesa uygulaması ya da telefon), Bizum ile, bankalarda ya da merkez ve müşteri noktalarında ödeyebilirsin. Faturadaki QR kodu okutunca doğrudan hızlı ödeme sayfasına gidersin; orada kart bilgilerini girer ya da telefon numaranı yazıp Bizum işlemini telefonundan onaylarsın. Otomatik ödeme (domiciliación) herhangi bir bankada tanımlanabilir. Anlaşmalı bankalarda (Cajasur, Banco Santander, BBVA, Caja Rural, La Caixa, Unicaja) nakit, kart ya da hesaptan ödeme yapılır. Süresi geçmiş faturada EMASESA sana yeni bir ödeme belgesi gönderir. | G61: su faturası ödeme, EMASESA pago, Bizum, domiciliación, QR, Pago Rápido, Mi Emasesa | H61: new;settled | I61: sevilla:kaynak:162;sevilla:kaynak:158 | J61: 46319 | K61: 506 | L61: Hayır | M61: Taslak | N61: sevilla:fatura | O61: Faturadaki QR kodu okut; kart bilgilerini gir ya da Bizum'u seç, telefon numaranı yaz ve işlemi telefonundan onayla. Dilersen Oficina Online'dan, Mi Emasesa uygulamasından ya da telefonla (955 00 32 00 veya 900 82 20 10) kartla öde. Otomatik ödeme için Oficina Online'dan, uygulamadan, telefondan ya da müşteri noktalarından domiciliación tanımla; banka hesabını değiştirmek için de aynı kanallar var. Faturanın süresi geçtiyse EMASESA'dan SMS ya da e-postayla yeni ödeme belgesi iste; onu bir bankada, Correos şubesinde ya da banka uygulamasında öde. Müşteri noktasında ödeyeceksen önce cita previa al; merkezde kart, nakit ve çek, müşteri noktalarında kart ve çek kabul edilir. | S61: Bankan faturayı iade ederse otomatik ödeme sona erer ve sonraki faturalar hesabına yansımaz; yeniden tanımlamak için EMASESA'yı ara. İade edilen faturayı Calle Escuelas Pías 1'deki merkez ofiste (pazartesi-cuma 8:00-14:15) ya da anlaşmalı bankalarda ödeyebilirsin.
A62: sevilla:su-faturasi-odenmezse-kesinti-mektubu-ve-yeniden-baglanma | B62: sevilla | C62: su-faturasi-odenmezse-kesinti-mektubu-ve-yeniden-baglanma | D62: Su faturasını zamanında ödeyemezsen ne olur: kesinti mektubu, 90 gün ve yeniden bağlanma | E62: Kesinti öncesi mektup gelir; sosyal acil durumu belgelenen konut abonesinin suyu kesilmez | F62: Fatura gönüllü ödeme süresinde ödenmezse EMASESA sözleşmeye göre suyu kesebilir. Kesintiden önce gelen mektup, gönüllü ödeme döneminin bittiğini ve hangi tarihten sonra kesme yetkisi doğduğunu bildirir; borcu mektuptaki tarihten önce EMASESA'nın bir müşteri noktasında ödemen gerekir. Kesinti tarihinden sonra 90 gün içinde borç ödenmezse sözleşme sona erer. Suyu yeniden açtırmak için tüm bekleyen faturaları ve yeniden bağlanma (reconexión) faturasını ödersin; sayaç sökülüp abonelik kapandıysa yeni abonelik gerekir. Belediye sosyal hizmetlerinin geçerli biçimde belgelediği sosyal acil durumdaki kişilerin konut suyu kesilmez. | G62: su kesintisi, EMASESA corte de suministro, reconexión, deuda, sosyal acil durum, carta de corte | H62: settled | I62: sevilla:kaynak:158;sevilla:kaynak:167 | J62: 46319 | K62: 507 | L62: Hayır | M62: Taslak | N62: sevilla:fatura | O62: Kesinti mektubundaki tarihi oku; mektup gönüllü ödeme döneminin bittiğini ve kesme yetkisinin hangi tarihte başladığını bildirir. Borcu o tarihten önce EMASESA'nın herhangi bir müşteri noktasında öde. Su kesildiyse bekleyen tüm faturaları ve yeniden bağlanma faturasını öde. Sayaç sökülmüş ve abonelik kapanmışsa yeni abonelik (alta) için başvur. Geliri sosyal tarife sınırının altındaysa tarifa social için başvur; başvuruyla birlikte borç tanıma ve ödeme planı imzalanır. | Q62: Kesinti tarihinden sonra 90 gün içinde borç ödenmezse sözleşme sona erer | S62: Sözleşme yapmadan suyu kullanıyorsan EMASESA 'uso fraudulento' mektubu gönderir; durumu düzeltmek için cita previa alıp sözleşmeni düzenlersin.
A63: sevilla:su-sayaci-tahmini-okuma-kacak-kontrolu-yuksek-fatura | B63: sevilla | C63: su-sayaci-tahmini-okuma-kacak-kontrolu-yuksek-fatura | D63: Su sayacı, tahmini fatura ve kaçak kontrolü: EMASESA'dan beklenmedik yüksek fatura gelirse | E63: Okumayı kendin bildirebilirsin; sayaç kapalı musluklarda dönüyorsa iç tesisatta kaçak olabilir | F63: EMASESA sayaçtan gerçek okuma alamazsa (sayaç arızası, evde kimsenin bulunmaması gibi nedenlerle) faturayı tahmini tüketimle keser; sayaç arızası dışındaki durumlarda tahmin sonradan gerçek okumaya göre düzeltilir. Okumayı kendin de bildirebilirsin ve EMASESA bunu kontrol eder. Kaçak testi basit: su kullanan her şeyi kapat, iç anahtarı açık bırak ve sayaca bak; sayaç tüketim kaydediyorsa iç tesisatta kaçak olabilir. Gizli iç tesisat kaçağı yüzünden olağandışı yüksek tüketim çıkarsa EMASESA'dan faturanın düzenlenmesini (regularización) isteyebilirsin; şartlar yönetmelikte. | G63: su sayacı, lectura estimada, fuga, kaçak, yüksek fatura, EMASESA, contador, regularización | H63: settled | I63: sevilla:kaynak:158;sevilla:kaynak:167 | J63: 46319 | K63: 508 | L63: Hayır | M63: Taslak | N63: sevilla:fatura | O63: Okumayı Oficina Online'dan (emasesaonline.com), 955 010 010 ya da 900 822 010 numaralarından veya Sevilla'daysan 010 Línea Sevilla'dan bildir; EMASESA okumayı kontrol eder. Kaçak testi: tüm musluk ve su kullanan cihazları kapat, iç anahtarı açık bırak ve sayaca bak; sayaç tüketim gösteriyorsa kaçak olabilir. Akıllı (NB-IoT) sayacın varsa Mi Emasesa uygulamasından saatlik ya da günlük tüketimi izle; kullanmadığın saatlerde sürekli tüketim kaçağa işaret eder. Yüksek tüketim mektubu geldiyse okumanın doğru olduğunu ve alışkanlıklarının değişmediğini düşünüyorsan iç tesisatı gözden geçir. Gizli iç tesisat kaçağı kaynaklı anormal yüksek faturada EMASESA'dan regularización iste. | S63: Sayaç en çok 12 yıl takılı kalabilir ve süre dolunca değiştirilir. Sayaç işçileri hiçbir durumda para istemez ve istendiğinde şirket kimlik kartını göstermek zorundadır; kuşkun varsa 955 010 010 veya 900 822 010'u ara.
A64: sevilla:emasesa-sevilla-distrito-sur-ve-este-musteri-noktalari | B64: sevilla | C64: emasesa-sevilla-distrito-sur-ve-este-musteri-noktalari | D64: Sevilla'da EMASESA müşteri noktaları: Distrito Sur ve Distrito Este adresleri, saatleri ve telefon | E64: İki nokta da hafta içi öğleye kadar, hafta içi dört gün öğleden sonra açık; randevu şart | F64: Su işlerini yüz yüze halletmek için EMASESA'nın Puntos de Atención Ciudadana noktalarından ikisi şunlardır: Distrito Sur (C/ Jorge Guillén, s/n, 41013) ve Distrito Este (C/ Cueva de Menga, s/n, Urb. Los Minaretes, 41020). İkisi de pazartesi-cuma 08:30-14:30 arası, ayrıca pazartesi-perşembe 17:00-19:00 arası açıktır. İkisinde de cita previa (randevu) olmadan hizmet alınmaz. Telefon numaraları 955 003 200 ve 900 822 010. | G64: EMASESA müşteri noktası, Punto de Atención Ciudadana, Distrito Sur, Distrito Este, Sevilla su ofisi, cita previa | H64: new;settled | I64: sevilla:kaynak:164;sevilla:kaynak:165 | J64: 46320 | K64: 509 | L64: Hayır | M64: Taslak | N64: sevilla:fatura | O64: Gideceğin noktadan önce cita previa al; bu iki noktada randevusuz hizmet verilmez. Sana yakın noktayı seç: Distrito Sur C/ Jorge Guillén, s/n, 41013; Distrito Este C/ Cueva de Menga, s/n, Urb. Los Minaretes, 41020. Hafta içi 08:30-14:30 ya da pazartesi-perşembe 17:00-19:00 arasında randevu saatine git. Telefon numaraları: 955 003 200 ve 900 822 010. | Q64: Pazartesi-cuma 08:30-14:30; pazartesi-perşembe 17:00-19:00
A65: sevilla:resmi-tatiller-2027 | B65: sevilla | C65: resmi-tatiller-2027 | D65: İspanya'da 2027'de resmî tatil günleri hangileri, hangileri bölgeye göre değişir? | E65: BOE'de 13 Ekim 2026'da yayımlandı: sekiz ulusal gün ve 6 Ocak 2027'de hiçbir bölgede değişmedi, kalanı bölgeye göre değişir; yerel tatiller belediyeye bağlıdır | F65: 2027'de her bölgede tatil olan günler: bölgelerin değiştiremediği 1 Ocak (Año Nuevo), 26 Mart (Viernes Santo), 1 Mayıs (Fiesta del Trabajo), 12 Ekim (Fiesta Nacional de España), 1 Kasım (Todos los Santos), 6 Aralık (Día de la Constitución), 8 Aralık (Inmaculada Concepción) ve 25 Aralık (Natividad del Señor); bir de 6 Ocak (Epifanía del Señor), çünkü kararın tablosunda hiçbir bölge 2027 için bu günün yerine başka gün koymamıştır. Liste, BOE'de 13 Ekim 2026'da yayımlanan (8 Ekim 2026 tarihli) Dirección General de Trabajo kararındadır. Bunların dışındaki günler bölgeye göre değişir: bazı ulusal günlerin yerine bölgeler kendi geleneksel günlerini koyabilir, ayrıca bazı bölgeler kendi bölge gününü ekler (2027 tablosunda bazı bölgelerin, örneğin başkent bölgesinin sütununda bölge günü işareti yoktur; Canarias için ada günleri tablonun altındaki 1 numaralı notta verilir). Karar 17 özerk bölgenin ve Ceuta ile Melilla'nın gönderdiği listelere dayanır. Yerel tatiller belediyeye göredir ve bu kararda yer almaz. | G65: resmi tatiller 2027, fiestas laborales 2027, BOE tatil takvimi, ulusal tatil, bölge tatili, fiestas locales, Viernes Santo, Jueves Santo | H65: planning;new;settled | I65: sevilla:kaynak:121 | J65: 46319 | K65: 9091 | L65: Hayır | M65: Taslak | N65: sevilla:gunluk | O65: 1 Ocak, 6 Ocak, 26 Mart, 1 Mayıs, 12 Ekim, 1 Kasım, 6 Aralık, 8 Aralık ve 25 Aralık'ı her yerde tatil olarak planla. 19 Mart (San José), 25 Mart (Jueves Santo) ve 16 Ağustos (Asunción'dan sonraki pazartesi) için kararın ekindeki tabloda kendi bölgenin sütununa bak: bölge bu günlerin yerine başka gün koyabilir. 29 Mart (Lunes de Pascua) gibi *** işaretli günleri bölge günü olarak oku; bunlar yalnız tabloda işaretli bölgelerde tatildir. Belediyene özgü yerel tatilleri bölgenin ya da ilin resmî gazetesinde yayımlanan listeden öğren; belediye başına yılda en çok iki gün olabilir. | Q65: 2027 takvim yılı | S65: Bazı bölgelerde adaya ya da yöreye özgü ek veya değişik tatil günleri vardır; kararın açıklama notlarında örnekleri verilir.
A66: sevilla:magaza-acilis-saatleri-cercevesi | B66: sevilla | C66: magaza-acilis-saatleri-cercevesi | D66: İspanya'da mağazaların açılış saatlerini kim belirler, yasal alt sınırlar neler? | E66: Ley 1/2004 ulusal çerçeveyi çizer; saat düzenlemesi özerk bölgelerdedir, haftalık ve pazar/tatil alt sınırları kanunda yazılıdır | F66: Saat düzenlemesi özerk bölgelerin yetkisindedir; Ley 1/2004 (Horarios Comerciales) ise ortak çerçeveyi ve alt sınırları koyar (konsolide metin, 17/10/2014 sürümü; metin bilgilendirme amaçlıdır, hukuki değeri yoktur). Bu çerçevede her işletmeci açılış ve kapanış saatini, hangi tatil günlerinde açık olacağını ve günlük ya da haftalık saatini kendisi belirler. Bölge, iş günlerinde haftalık toplam açık kalma süresini 90 saatin altına indiremez. Pazar ve tatil günlerinde yıllık ulusal asgari açık kalma sayısı 16'dır; bölge bu sayıyı artırabilir ya da azaltabilir, ama 10'un altına indiremez ve hangi pazar ve tatillerde açık olunacağını bölge belirler. Bu yüzden saat ve açık pazar günleri bölgene göre değişir. | G66: mağaza saatleri, horarios comerciales, Ley 1/2004, pazar günü açık, domingos y festivos, tiendas de conveniencia, çalışma saatleri | H66: new;settled | I66: sevilla:kaynak:122 | J66: 46319 | K66: 9092 | L66: Hayır | M66: Taslak | N66: sevilla:gunluk | O66: İşletmenin türüne bak: asıl işi pastane ve pasta, ekmek, hazır yemek, gazete, akaryakıt, çiçek ve bitki satmak olan mağazalar ile tiendas de conveniencia (500 m²'ye kadar, günde en az 18 saat açık, kitap, gazete, gıda, plak, video, oyuncak ve hediye gibi karışık ürün satan mağaza) tüm ülkede gün ve saatini serbestçe belirler. Sınır noktalarındaki, istasyon ve ulaşım araçlarındaki ve turistik yoğunluk bölgelerindeki mağazalar da serbesttir; bu bölgeleri özerk bölge belirler ve belediyenin önerisine göre ilan edilen alan ya da dönem kısıtlı olabilir. Kullanım alanı 300 metrekarenin altındaki küçük mağazalarda da gün ve saat serbesttir; KOBİ sayılmayan şirket ve gruplara ait olanlar bunun dışındadır. Eczane ve estanko (tütün bayii) kendi özel mevzuatına tabidir. Yukarıdakilerin dışındaki mağazalarda bölge, iş günlerindeki haftalık toplam açık kalma süresini 90 saatin altına indiremez; açılış ve kapanış saatini işletmeci seçer. Pazar ve tatilde açık olabilecek gün sayısı ulusal çerçevede yılda en az 16'dır; bölgen bunu artırabilir ya da 10'a kadar indirebilir. Hangi günlerin açık olacağını bölge belirler. | S66: Bölgeler halka saatleri bildirme yükümlülükleri de koyabilir. Yukarıdaki sayılar ulusal çerçevedir; bölgenin kendi düzenlemesi bunların üzerine çıkabilir.
A67: sevilla:ab-disi-paket-gumruk-iva | B67: sevilla | C67: ab-disi-paket-gumruk-iva | D67: AB dışından internetten alınan 150 euroya kadarlık paket için İspanya'da IVA ve gümrük vergisi ödenir mi? | E67: IVA ödenir; 1 Temmuz 2026'dan beri 150 euroya kadar siparişte kategori başına 3 euro arancel, 1 Kasım 2026'dan itibaren ayrıca 2 euro işlem ücreti | F67: Evet, 150 euroya kadar siparişlerde. AEAT'a göre AB dışından internetten alışverişte IVA ödenir: satıcı IOSS sistemine katılıyorsa fiyata IVA dahildir, katılmıyorsa paketi İspanya'ya sokan taşıyıcı IVA'yı tahsil eder ve teslimden önce malın fiyatının %21'ini isteyebilir. 1 Temmuz 2026'dan itibaren toplam tutarı en çok 150 euro olan siparişlerde IVA'ya ek olarak her ürün kategorisi için 3 euro sabit arancel (gümrük vergisi) ödenir; kaynak AB dışı örnek olarak Çin, ABD ve Birleşik Krallık'ı verir. 1 Kasım 2026'dan önce arancel olarak yalnız bu 3 euro vardır (taşıyıcı ayrıca bazı yönetim giderleri isteyebilir); 1 Kasım 2026'dan itibaren her kategori için 2 euro işlem ücreti de arancelle birlikte ödenir. AB dışı kaynaklı paketler Correos'ta gümrük kontrolüne girer; bu tutarlar önceden ödenmemişse alıcı onları ödemeden paketi alamaz. | G67: gümrük, IVA, arancel, AB dışı paket, 150 euro, Correos, AEAT, IOSS, internetten alışveriş, aduana | H67: new;settled | I67: sevilla:kaynak:123;sevilla:kaynak:124 | J67: 46319 | K67: 9093 | L67: Hayır | M67: Taslak | N67: sevilla:gunluk | O67: Siparişten önce satıcının koşullarında fiyatın IVA ve gümrük vergisini içerip içermediğine bak. Malın sipariş anında nereden gönderildiğine bak: gümrük vergisi için belirleyici olan, ürünün sipariş sonrası gönderildiği yerdir; ürün İspanya'da ya da başka bir AB ülkesindeyse gümrük vergisi yoktur. Fiyata dahil değilse taşıyıcının istediği IVA ve arancel tutarını öde; teslim buna bağlı olabilir. Correos'ta bu tutarları alıcı öder. İade edeceksen arancelin iade edilmediğini bil; arancel yalnız mal kusurluysa ya da sözleşmeye uymuyorsa geri verilir. IVA iadesi ise ayrı işler. | Q67: 1 Temmuz 2026'dan itibaren; işlem ücreti 1 Kasım 2026'dan itibaren | R67: Arancel: kategori başına 3 euro (150 euroya kadar siparişlerde, 1 Temmuz 2026'dan itibaren). İşlem ücreti: kategori başına 2 euro (1 Kasım 2026'dan itibaren) | S67: AEAT gümrük vergisini tüketiciden talep etmez; yalnız satıcı ya da platformun gümrük beyanı için görevlendirdiği kişiden ister. Tüketici gümrük işlemlerini kendi adına yapıyorsa kaynak bu güvenceyi vermez. Kontrol iki yönde işler: İspanya anakarasına (Península ve Baleares) AB dışından, Canarias, Ceuta ya da Melilla'dan gelen paketler ve Canarias, Ceuta ya da Melilla'ya başka bir bölgeden giren paketler Correos'ta gümrük kontrolüne tabidir. %21 oranı kaynak sayfada bölge ayrımı yapılmadan verilir; Canarias, Ceuta ve Melilla'daki IVA uygulaması bu kartın kapsamı dışındadır. Bazı ürünler kısıtlı ya da yasak olabilir; ithalatı yapan kişi şartları öğrenmekten ve gerekli belgeleri vermekten sorumludur.
A68: sevilla:diger-resmi-yardim-hatlari | B68: sevilla | C68: diger-resmi-yardim-hatlari | D68: İspanya'da 112 dışında hangi resmî yardım hatları var (016, 021, 028, 024)? | E68: Ministerio de Igualdad'ın 016, 021, 028, ATENPRO ve 900 19 10 10 hatları ile Ministerio de Sanidad'ın 024 intihar önleme hattı | F68: Evet, 112 dışında konuya özel resmî hatlar var: 016, 021, 028, ATENPRO, 900 19 10 10 ve 024. Ministerio de Igualdad'ın hatları: kadına yönelik şiddet için 016 (bilgi, hukuki danışmanlık ve psikososyal destek), ırksal ya da etnik ayrımcılık mağdurları için 021, LGTBI hakları ve nefret suçları için 028. Kadına şiddet mağdurları için 24 saat telefonla bakım ve koruma hizmeti ATENPRO'nun numarası 900 22 22 92, kadın haklarına dair bilgi ve danışmanlık hattı ise 900 19 10 10'dur. Ministerio de Sanidad'ın 024 hattı intihar düşüncesi ya da riski taşıyanlara ve yakınlarına yöneliktir; ülke genelinde ücretsiz, gizli ve günün 24 saati, yılın 365 günü açıktır. | G68: 016, 021, 028, 024, yardım hattı, kadına şiddet, ayrımcılık, LGTBI, intihar önleme, ATENPRO | H68: new;settled | I68: sevilla:kaynak:125;sevilla:kaynak:126 | J68: 46319 | K68: 9094 | L68: Hayır | M68: Taslak | N68: sevilla:gunluk | O68: Kadına yönelik şiddet için 016'yı ara; 600 000 016 numarasına ya da 016-online@igualdad.gob.es adresine de ulaşabilirsin. Irksal ya da etnik ayrımcılık için 021'i ara; 028 hattı LGTBI hakları ve nefret suçları içindir, chat ile de ulaşılır. ATENPRO (şiddet mağdurları için 24 saat telefon bakım ve koruma hizmeti) 900 22 22 92 numaralı telefondur; kadın haklarına dair bilgi ve danışmanlık için 900 19 10 10'u ara. İntihar düşüncesi ya da riski için 024'ü ara; hat sohbet ve işaret dili video çevirisiyle de açıktır. Yaşamı hemen tehdit eden acil bir durumda doğrudan 112'yi ara. | Q68: 024 hattı günün 24 saati, yılın 365 günü | S68: 024 hattı yüz yüze bir sağlık uzmanıyla görüşmenin yerini almak için değildir; duruma göre sağlık sistemine yönlendirir ya da 112'ye aktarır.
A69: sevilla:bahsis-ve-odeme-aliskanliklari | B69: sevilla | C69: bahsis-ve-odeme-aliskanliklari | D69: İspanya'da bahşiş vermek zorunlu mu, nakit ve kartla ödeme nasıl işler? | E69: Bahşiş zorunlu değil, servis fiyata dahildir; bar, restoran, otel ve taksilerde yaygındır, genelde toplamın yüzde beş ile on arasıdır (spain.info) | F69: Hayır, bahşiş zorunlu değil: spain.info'ya göre işletmelerin tamamı hizmet bedelini fiyata dahil eder. Yine de bar ve restoranlarda, otellerde ve taksilerde bahşiş vermek yaygındır; tutar hesap tutarına bağlıdır ve genelde toplam tutarın yüzde beşi ile yüzde onu arasındadır. Ödemede hemen her yerde nakit geçer ve genelde yalnız euro kabul edilir; makineyle ödemede bazen kartla ödemek zorunlu olabilir. Kredi ve banka kartları yaygındır, çoğunlukla Visa ve Mastercard; kartla ödeme için yaklaşık 10 € asgari tutar istenebilir ve kartının koşullarına göre komisyon doğabilir. Etiketteki fiyatta pazarlık kabul edilmez. | G69: bahşiş, propinas, ödeme, nakit, kart, Visa, Mastercard, pazarlık, euro | H69: before;new;settled | I69: sevilla:kaynak:127 | J69: 46319 | K69: 9095 | L69: Hayır | M69: Taslak | N69: sevilla:gunluk | O69: Servis bedeli fiyata dahil olduğu için bahşişi isteğe göre ver; bar, restoran, otel ve taksilerde yaygındır. Verecekse hesap tutarının yüzde beşi ile yüzde onu arasında bir tutar belirle. Yanında nakit euro bulundur; makineyle ödemede kart gerekebilir. Kartla küçük tutar ödeyeceksen yaklaşık 10 € asgari tutar istenebileceğini ve kartının komisyon koşullarını hesaba kat. | S69: Kartla ödemede komisyon, kartının koşullarına bağlıdır.
A70: sevilla:endulus-2027-resmi-tatilleri | B70: sevilla | C70: endulus-2027-resmi-tatilleri | D70: Endülüs'te 2027'de resmî tatil günleri hangileri, Día de Andalucía ve 15 Ağustos neden kayıyor? | E70: Decreto 84/2026: Día de Andalucía 1 Mart'a, 15 Ağustos 16 Ağustos'a kayar; belediye başına iki yerel tatil ayrıca gelir | F70: Decreto 84/2026'ya göre Endülüs'te 2027'nin ücretli, telafisiz bölge tatilleri şunlardır: 1 Ocak (Cuma), 6 Ocak (Çarşamba), 1 Mart (Pazartesi, Día de Andalucía), 25 Mart Jueves Santo, 26 Mart Viernes Santo, 1 Mayıs (Cumartesi), 16 Ağustos (Pazartesi), 12 Ekim (Salı), 1 Kasım (Pazartesi), 6 Aralık (Pazartesi), 8 Aralık (Çarşamba) ve 25 Aralık (Cumartesi). Día de Andalucía (28 Şubat) ve Asunción (15 Ağustos) 2027'de Pazar'a denk geldiği için ertesi Pazartesi'ye, yani 1 Mart ve 16 Ağustos'a kaydırıldı. Bunlara ek olarak her belediyede iki yerel tatil vardır; hangi günler olduğu belediyene göre değişir. | G70: Endülüs resmî tatil 2027, fiestas laborales, Día de Andalucía, Jueves Santo, Viernes Santo, fiestas locales, Decreto 84/2026 | H70: planning;new;settled | I70: sevilla:kaynak:140 | J70: 46319 | K70: 9103 | L70: Hayır | M70: Taslak | N70: sevilla:gunluk | O70: Aşağıdaki listeyi 2027 iş planına işle. 1 Mart ve 16 Ağustos'un kaydırılmış tarihler olduğunu hesaba kat. Belediyenin iki yerel tatil günü ayrıca belirlenir; bunları listeye ekle. | Q70: 2027 takvim yılı için geçerli. | S70: Yıllık sınır on dört gündür; ikisi yerel tatildir. Her belediyenin en çok iki yerel tatil önerisi Consejería'ya bildirilir.
A71: sevilla:endulus-112-nasil-calisir | B71: sevilla | C71: endulus-112-nasil-calisir | D71: Sevilla'da 112'yi arayınca ne olur, hangi dillerde cevap verirler? | E71: Endülüs 112 hattı ücretsiz ve kesintisiz; İspanyolca, İngilizce, Fransızca, Almanca ve Arapça yanıt veriliyor | F71: Endülüs'te (Sevilla dahil) 112, sağlık, yangın söndürme ve kurtarma, kamu güvenliği ve sivil korumayı tek numarada toplayan ücretsiz bir hattır; cep, sabit telefon ya da ankesörlüden aranabilir. Operatörler İspanyolca, İngilizce, Fransızca, Almanca ve Arapça cevap veriyor. Açılışta "Emergencias 112 Andalucía, ¿dígame?" der; sonra ne olduğunu, nerede olduğunu ve telefon numaranı sorar. Telefonuna ücretsiz 112 Andalucía uygulamasını kurarsan 112 düğmesine basınca, konum açıksa, tam koordinatların merkeze gider. | G71: 112, Emergencias 112 Andalucía, acil durum, acil numara, 112 uygulaması, WhatsApp konum, yabancı dil | H71: planning;new;settled | I71: sevilla:kaynak:191;sevilla:kaynak:193 | J71: 46319 | K71: 1100 | L71: Evet | M71: Taslak | N71: sevilla:gunluk | O71: Tehlikeyi görünce sakin kal ve 112'yi ara; hat cep, sabit telefon ve ankesörlüden çalışır. Operatörün sorularına sırayla cevap ver: ne oluyor, nerede ve hangi numaradan arıyorsun. Yerini bilmiyorsan 112 Andalucía uygulamasındaki 112 düğmesine bas; konum özelliği açıksa koordinatların merkeze gider. Konumun hâlâ belirsizse operatör sana WhatsApp ya da Line üzerinden konum göndermen için ihtiyacın olan dilde talimat yollayabilir; ihbarın kendisi yine telefon aramasıyla yapılır. Görüşme "Avisamos a los servicios operativos" (ilgili birimleri uyarıyoruz) cümlesiyle biter. | Q71: Kesintisiz hizmet | R71: Ücretsiz | S71: Şehirdeysen sokak, meydan ya da cadde adını, yakında tanınmış bir anıt ya da dükkân varsa onu söyle.
A72: sevilla:061-ya-da-saglik-merkezi-acil-ayrimi | B72: sevilla | C72: 061-ya-da-saglik-merkezi-acil-ayrimi | D72: Sevilla'da sağlık sorunu acil mi, acele mi? 061'i ne zaman ararsın, sağlık merkezine ne zaman gidersin? | E72: Endülüs Hükûmeti ateş, ağrı, kusmayı "urgencia", bilinç kaybı ve kalp krizini "emergencia" sayıyor | F72: Junta de Andalucía iki durumu ayırıyor. Ateş, ağrı, kusma gibi hayatı tehlikeye sokmayan ama en kısa sürede sağlık hizmeti gereken durumlar "urgencia"dır; bilinç kaybı, kalp krizi ya da kalp durması, çok kan kaybı gibi hayati riskli durumlar "emergencia"dır. Emergencia'da 061'i ara ya da hemen en yakın acil servise git. Acil hizmeti Endülüs'te hem hastanelerde hem sağlık merkezlerinde verilir. Diğer sağlık hizmetleri hakkında bilgi için Salud Responde'yi (955 545 060) arayabilirsin. | G72: 061, urgencias, acil servis, centro de salud, emergencia sanitaria, Salud Responde, Sevilla acil | H72: new;settled | I72: sevilla:kaynak:191;sevilla:kaynak:192 | J72: 46319 | K72: 1101 | L72: Hayır | M72: Taslak | N72: sevilla:gunluk | O72: Durum hayati tehlike taşıyorsa (bilinç kaybı, kalp krizi, çok kan kaybı) 061'i ara ya da hemen en yakın acil servise git. 061 sana şunları sorar: nereden arıyorsun, ne oldu, kaç kişi etkilendi; cevapları hazır tut. Hayati risk yoksa ama hızlı bakım gerekiyorsa: acil hizmeti Endülüs'te hem sağlık merkezlerinde hem hastanelerde verilir; acil birimi olan bir sağlık merkezine ya da hastanenin acil servisine gidebilirsin. Başka sağlık hizmetleri için bilgi gerekirse Salud Responde'yi 955 545 060'tan ara. | R72: 061 araması, "tarifa plana" (sabit paket) kullanıcıları için ücretsiz | S72: 061 ekibi ağır durumdaki hastayı stabilize eder ve referans hastaneye götürür.
A73: sevilla:endulus-bilgi-hatlari-salud-consumo-012 | B73: sevilla | C73: endulus-bilgi-hatlari-salud-consumo-012 | D73: Endülüs'te sağlık, tüketici ve genel bilgi için hangi hatlar aranır (Salud Responde, Consumo Responde, 012)? | E73: Junta de Andalucía'nın sağlık, tüketici ve vatandaş bilgi hatları ile üç uzman bilgi numarası | F73: Sağlık hizmetleri hakkında bilgi için Salud Responde 955 545 060, tüketici sorunları için Consumo Responde 900 215 080, Junta de Andalucía hizmetleri için genel vatandaş bilgi hattı 012 (ya da 955 012 012) var. Ayrıca kanser bilgisi için Infocáncer (900 100 036), toksikoloji bilgisi için Servicio Médico de Información Toxicológica (915 620 420) ve cinsel ve üreme sağlığı bilgisi için 900 850 100 numaraları Junta'nın sayfasında listeleniyor. Bunlar bilgi hatlarıdır; hayati tehlikede 112 ya da 061'i ara. | G73: Salud Responde, Consumo Responde, 012, Junta de Andalucía telefon, Infocáncer, toksikoloji, bilgi hattı | H73: new;settled | I73: sevilla:kaynak:192;sevilla:kaynak:191 | J73: 46319 | K73: 1102 | L73: Hayır | M73: Taslak | N73: sevilla:gunluk | O73: Sağlık hizmetleri için bilgi almak istiyorsan Salud Responde'yi 955 545 060'tan ara. Tüketici hakkı sorunun için Consumo Responde'yi 900 215 080'den ara. Junta de Andalucía hizmetleri hakkında genel soru için 012 ya da 955 012 012'yi ara. Hayati tehlike varsa bu hatları değil 112'yi ya da 061'i ara. | S73: Bunlar bilgi hatlarıdır; hayati tehlikede 112 ya da 061'i ara.
A74: sevilla:konteyner-renkleri-sevilla | B74: sevilla | C74: konteyner-renkleri-sevilla | D74: Sevilla'da çöp hangi konteynere atılır? Konteyner renkleri ve neyin nereye gittiği | E74: Organik atık kahverengi, ambalaj sarı, kâğıt ve karton mavi, cam yeşil konteynere gider | F74: Sevilla'nın turizm kurumu şehirde seçici atık toplama sistemi olduğunu ve dört tür konteyner kullanıldığını yazıyor. Organik atık (yemek artıkları ve diğer organik atıklar) kahverengi, ambalaj atığı (plastik, teneke ve briks) sarı, kâğıt ve karton mavi, cam yeşil konteynere atılır. Kurum, atığı doğru konteynere ve belirlenen toplama saatlerine uyarak bırakmanı istiyor. | G74: çöp, geri dönüşüm, konteyner renkleri, reciclaje, orgánico, envases, vidrio, Sevilla çöp | H74: new;settled | I74: sevilla:kaynak:204;sevilla:kaynak:195 | J74: 46319 | K74: 1103 | L74: Evet | M74: Taslak | N74: sevilla:gunluk | O74: Yemek artıklarını ve organik atıkları kahverengi (organik) konteynere at. Plastik, teneke ve briks ambalajı sarı konteynere at. Kâğıt ve kartonu mavi konteynere at. Cam şişe ve kavanozu yeşil konteynere at. Çöpü yalnız belirlenen saatlerde konteynere bırak.
A75: sevilla:cam-sise-kavanoz-geri-donusum-kurallari | B75: sevilla | C75: cam-sise-kavanoz-geri-donusum-kurallari | D75: Sevilla'da cam şişe ve kavanoz geri dönüşümü: konteynere ne girer, ne girmez? | E75: Boş, durulanmış, kapaksız şişe ve kavanoz; ayna, ampul, seramik ve ilaç ambalajı camla atılmaz | F75: Cam konteynerine yalnız boş ve durulanmış cam ambalaj (şişe, kavanoz, küçük şişe) atılır; kapak, mantar ve tıpalar çıkarılır. Atığı poşetle birlikte atma ve hiçbir şeyi konteynerin dışında bırakma. Ayna, ampul, cam sofra takımı, düz cam ve pencere camı, seramik, porselen, tuğla, taş, çanak çömlek ve vazo cam konteynerine girmez. İlaç ambalajı eczaneye götürülür. Sevilla'nın şehir rehberinde cam konteyneri yeşildir. | G75: cam geri dönüşüm, vidrio, cam konteyneri, şişe kavanoz atığı, ilaç ambalajı, geri dönüşüm kuralları | H75: new;settled | I75: sevilla:kaynak:196;sevilla:kaynak:204 | J75: 46319 | K75: 1104 | L75: Hayır | M75: Taslak | N75: sevilla:gunluk | O75: Şişe ve kavanozu boşalt, durula; kapak, mantar ve tıpayı çıkar. Cam atığını poşete koymadan yeşil cam konteynerine at; konteynerin dışına hiçbir şey bırakma. Kapak ve tıpaları sarı konteynere at; doğal mantarları organik atığa ver. İlaç ambalajlarını eczaneye götür. | S75: Cam konteynerine ayna, ampul, düz cam, seramik ve porselen atma.
A76: sevilla:organik-atik-ayri-toplama-zorunlulugu | B76: sevilla | C76: organik-atik-ayri-toplama-zorunlulugu | D76: Yemek artıkları (organik atık) için ayrı toplama zorunlu mu, Sevilla'da nasıl ayırırsın? | E76: 7/2022 sayılı yasa, tüm yerel yönetimlere 31 Aralık 2023'ten beri organik atığı ayrı toplamayı zorunlu kılıyor | F76: İspanya'nın 7/2022 sayılı atık yasası (8 Nisan 2022) organik atığın (biorresiduos) kaynağında ayrılmasını ve başka atıkla karıştırılmamasını şart koşar; ayrı toplama tüm yerel yönetimler için 31 Aralık 2023'ten beri zorunludur. Sistemi belediye seçer: kahverengi konteyner, kapı kapı toplama ya da puntos limpios (gönüllü getirme tesisleri) olabilir. Sevilla'nın şehir rehberi de organik atığı (yemek artıkları) ayrı bir konteyner olarak listeler. | G76: biorresiduos, organik atık, kahverengi konteyner, ayrı toplama, compostaje, punto limpio, Ley 7/2022 | H76: new;settled | I76: sevilla:kaynak:197;sevilla:kaynak:204 | J76: 46319 | K76: 1105 | L76: Hayır | M76: Taslak | N76: sevilla:gunluk | O76: Yemek artıklarını diğer çöpten ayır ve organik atık konteynerine at. Mahallende kahverengi konteyner yerine kapı kapı toplama varsa, o sistemin saat ve yerine uy. Evden toplanmayan seçili atıklar için puntos limpios'a (gönüllü getirme tesisi) götür. Organik atık bazı yerlerde evde ya da mahallede kompostlanarak da işleniyor. | Q76: 31 Aralık 2023'ten beri zorunlu
A77: sevilla:idi-sevilla-universitesi-ispanyolca-kursu | B77: sevilla | C77: idi-sevilla-universitesi-ispanyolca-kursu | D77: Sevilla Üniversitesi Dil Enstitüsü'nde (IDI) yabancılar için İspanyolca kursu: öğrenci olmadan katılabilir misin? | E77: IDI'nin İspanyolca kursları dört aylık dönemlerle işliyor; üniversite öğrencisi olmak şart değil | F77: Instituto de Idiomas (IDI), Sevilla Üniversitesi'nin dil enstitüsüdür ve ana dili İspanyolca olmayanlar için İspanyolca kursu açar. Kurslar dört aylık dönemlerle (cuatrimestral) işlediği için şehre dönem ortasında gelsen de uygun seviyeden başlayabilirsin. Enstitüyü üniversite öğrencisi olmayanlar da kullanabilir. Bir kursu geçersen o seviyen otomatik olarak belgelenmiş olur; seviyeni zaten biliyorsan akreditasyon sınavlarıyla (ACLES gibi) resmî olarak belgeletebilirsin. | G77: IDI, Instituto de Idiomas, Sevilla Üniversitesi, İspanyolca kursu, español como lengua extranjera, ACLES | H77: planning;new;settled | I77: sevilla:kaynak:198 | J77: 46319 | K77: 1106 | L77: Hayır | M77: Taslak | N77: sevilla:gunluk | O77: IDI sayfasındaki kurs listesinden ("Oferta de cursos") İspanyolca kurslarını incele. Dönem ortasında gelsen bile seviyene uygun gruptan başlayabilirsin; kurslar dört aylıktır. Seviyeni belgelemek istiyorsan IDI'nin akreditasyon sınavlarına (ACLES ve harici sınavlar) bak. | Q77: Kurslar dört aylık dönemlerle (cuatrimestral) | S77: Kurs ücretleri enstitünün "Precios públicos" (kamu fiyatları) bölümünde yer alıyor.
A78: sevilla:eoi-resmi-dil-okullari-sevilla-endulus | B78: sevilla | C78: eoi-resmi-dil-okullari-sevilla-endulus | D78: Sevilla'da resmî dil okulu (EOI) ile dil öğrenmek ve resmî dil sertifikası almak mümkün mü? | E78: Endülüs'te resmî dil eğitiminin ana yapısı EOI; sertifika sınavları her yıl açılır (2025/2026'da Mayıs-Haziran ve Eylül) | F78: Escuelas Oficiales de Idiomas (EOI), Endülüs'te resmî dil eğitiminin ana yapısıdır; temelden ileriye kadar seviyeler, yüz yüze, yarı yüz yüze ya da uzaktan eğitim sunar. Resmî sertifika sınavları her yıl yapılır, Endülüs genelinde aynı anda, bütün EOI'lerde gerçekleşir; sınava kayıtlı öğrenci olarak ya da serbest (régimen libre) girebilirsin. Sertifika sınavı dilleri arasında İspanyolca (ikinci dil olarak) da sayılır. 2025/2026 dönemi için olağan sınavlar Mayıs ve Haziran'da, olağanüstü sınav Eylül'de yapıldı. Kayıt ve kabul Eğitim Bakanlığı'nın (Consejería de Educación) prosedürüyle yürür. | G78: EOI, Escuela Oficial de Idiomas, resmî dil sertifikası, régimen libre, B2 sınavı, español segunda lengua, Endülüs dil okulu | H78: planning;new;settled | I78: sevilla:kaynak:199 | J78: 46319 | K78: 1107 | L78: Hayır | M78: Taslak | N78: sevilla:gunluk | O78: Junta'nın dil sayfasından EOI'lerin dil ve seviye listesine bak. Kayıt ve kabul için Consejería de Educación'ın EOI kabul ve kayıt prosedürünü kullan. Sınava sadece girmek istiyorsan serbest (régimen libre) başvuru seçeneğini kullan. Sorun olursa Junta de Andalucía bilgi hattını 012 ya da 955 012 012'den ara. | Q78: Olağan sınav Mayıs-Haziran, olağanüstü sınav Eylül (2025/2026 dönemi) | S78: Sevilla'daki EOI'lerin adresleri ve ücretleri bu sayfada yer almıyor.
A79: sevilla:halk-kutuphanesi-uyelik-karti-endulus | B79: sevilla | C79: halk-kutuphanesi-uyelik-karti-endulus | D79: Andalucía halk kütüphaneleri üyelik kartı (tarjeta de usuario) nasıl çıkarılır, ücretli mi? | E79: Kart ücretsiz, beş yıl geçerli ve ağdaki bütün kütüphanelerde kullanılıyor | F79: Andalucía Halk Kütüphaneleri Ağı'nın (Red de Bibliotecas Públicas de Andalucía) üyelik kartı ücretsizdir ve ödünç kitap almak için şarttır. Yetişkinler için yüz yüze başvuruda kayıt formunu doldurmak yeterlidir; kütüphane başvuru sırasında DNI, pasaport, yabancı kimlik numarası (NIE) ya da aile cüzdanı gösterilmesini isteyebilir. Elektronik imza sertifikan varsa başvuruyu internetten de yapabilirsin. Kart beş yıl sonra sona erer ve ağın bütün kütüphanelerinde geçerlidir. | G79: kütüphane kartı, tarjeta de usuario, Red de Bibliotecas Públicas de Andalucía, kütüphane üyeliği, carné, ödünç kitap | H79: new;settled | I79: sevilla:kaynak:200;sevilla:kaynak:201 | J79: 46319 | K79: 1108 | L79: Hayır | M79: Taslak | N79: sevilla:gunluk | O79: Yüz yüze başvuracaksan kayıt formunu doldur ve Andalucía içindeki posta adresini yaz. Başvuru sırasında DNI, pasaport, NIE ya da aile cüzdanını yanında bulundur. Elektronik imza sertifikan varsa formu internet üzerinden doldurabilirsin. Kartı kaybedersen kütüphaneye hemen haber ver. | P79: DNI, pasaport, yabancı kimlik numarası (NIE) ya da aile cüzdanı Kayıt (inscripción) formu | Q79: Kart verildiği tarihten beş yıl sonra sona erer | R79: Ücretsiz | S79: 14 yaşından küçükler için formu anne, baba ya da velayet sahibi doldurur. Kart kişiye özeldir ve başkasına devredilemez; yalnız tam gerekçeli durumlar bunun dışındadır.
A80: sevilla:infanta-elena-kutuphanesi-sevilla | B80: sevilla | C80: infanta-elena-kutuphanesi-sevilla | D80: Sevilla'daki Infanta Elena Eyalet Kütüphanesi: adres, çalışma saatleri, ödünç alma ve internet kullanımı | E80: Avenida de María Luisa 8'de; 9 belgeye kadar ödünç, haftada 2 saat internet, fotokopi A4 başına 0,06 euro | F80: Biblioteca Pública Provincial Infanta Elena, Avenida de María Luisa 8, 41003 Sevilla adresindedir (tel. 954 712 305). Kış saatlerinde hafta içi 9:00-21:00, cumartesi 9:00-14:00 açıktır; 16-30 Haziran hafta içi 9:00-21:00, Temmuz-Ağustos hafta içi 9:00-14:00, 1-15 Eylül hafta içi 9:00-21:00 ve cumartesi kapalıdır. Üyelik kartıyla toplam 9 belge ödünç alırsın: 6 kitap ve 3 görsel-işitsel. Kütüphanenin hizmetlerinin çoğu ücretsizdir; yalnız fotokopi ücretlidir. | G80: Infanta Elena kütüphanesi, Sevilla kütüphane, Biblioteca Provincial, kitap ödünç, kütüphane saatleri, ücretsiz internet | H80: new;settled | I80: sevilla:kaynak:201 | J80: 46319 | K80: 1109 | L80: Hayır | M80: Taslak | N80: sevilla:gunluk | O80: Ödünç almak için önce ağ üyelik kartını çıkar. Kitabı raftan al; kırmızı daireli kitaplar ödünç verilmez, yalnız kütüphanede okunur. Süreyi uzatmak istersen kitap için tek yenileme yapabilirsin, 10 gün ek süre verilir. İnternet için birinci kat girişindeki görsel-işitsel tezgâhına kartınla ya da kimliğinle yazıl; haftada iki saat, ardışık olmayan oturumlarla kullanırsın. Etüt masasını 30 dakikadan uzun boş bırakma; yeri kaybedersin. | P80: Kütüphane kartı (ödünç için) Kimlik ya da kart (internet için) | Q80: Kış: hafta içi 9:00-21:00, cumartesi 9:00-14:00 | R80: Fotokopi A4 başına 0,06 euro; hizmetlerin çoğu ücretsiz | S80: Kütüphaneye yiyecek ve içecek sokulamaz; kişisel eşyalar için dolap vardır.
